Workbook

Sheet 案件別採算
A1: 案件別 採算管理 （★黄色セル＝入力 緑セル＝自動計算）
A2: 【売上】⑤売上原票シートをVLOOKUPで参照（D列=集計月 YYYY-MM を入力すると自動セット） 【原価】黄色セルに毎月入力してください
A3: 案件ID | B3: 案件名 | C3: 集計月 (YYYY-MM) | D3: 売上（VLOOKUPで自動参照） | G3: その他 売上合計 | H3: 売上 合計 | I3: 原価 （黄色セルに入力） | P3: 原価 合計 | Q3: 粗利益 | R3: 粗利率 | S3: 採算 判定 | T3: 前月比 売上
D4: 運送 612-1 | E4: 入札 612-2 | F4: 板橋 615-1 | I4: 人件費 | J4: 燃料費 | K4: 車両 維持費 | L4: 中間 処理費 | M4: 搬入 運搬費 | N4: 電子M 代行費 | O4: 管理費
A5: C001 | B5: 東急グループ案件 | C5: 2024-07 | D5: =IFERROR(VLOOKUP(C5,▼売上原票!$A:$P,3,0)*VLOOKUP("612-1",▼マッピング!$A:$G,4,0)/100,0) | E5: =IFERROR(VLOOKUP(C5,▼売上原票!$A:$P,4,0)*VLOOKUP("612-2",▼マッピング!$A:$G,4,0)/100,0) | F5: =IFERROR(VLOOKUP(C5,▼売上原票!$A:$P,10,0)*VLOOKUP("615-1",▼マッピング!$A:$G,4,0)/100,0) | G5: =IFERROR(VLOOKUP(C5,▼売上原票!$A:$P,5,0)*VLOOKUP("613-1",▼マッピング!$A:$G,4,0)/100,0)+IFERROR(VLOOKUP(C5,▼売上原票!$A:$P,6,0)*VLOOKUP("613-2",▼マッピング!$A:$G,4,0)/100,0)+IFERROR(VLOOKUP(C5,▼売上原票!$A:$P,7,0)*VLOOKUP("614-1",▼マッピング!$A:$G,4,0)/100,0)+IFERROR(VLOOKUP(C5,▼売上原票!$A:$P,8,0)*VLOOKUP("614-2",▼マッピング!$A:$G,4,0)/100,0)+IFERROR(VLOOKUP(C5,▼売上原票!$A:$P,9,0)*VLOOKUP("614-3",▼マッピング!$A:$G,4,0)/100,0)+IFERROR(VLOOKUP(C5,▼売上原票!$A:$P,11,0)*VLOOKUP("615-2",▼マッピング!$A:$G,4,0)/100,0)+IFERROR(VLOOKUP(C5,▼売上原票!$A:$P,12,0)*VLOOKUP("615-3",▼マッピング!$A:$G,4,0)/100,0)+IFERROR(VLOOKUP(C5,▼売上原票!$A:$P,13,0)*VLOOKUP("615-4",▼マッピング!$A:$G,4,0)/100,0) | H5: =D5+E5+F5+G5 | P5: =I5+J5+K5+L5+M5+N5+O5 | Q5: =H5-P5 | R5: =IF(H5<>0,Q5/H5,0) | S5: =IF(R5>=0.25,"◎ 優良",IF(R5>=0.15,"○ 良好",IF(R5>=0.05,"△ 要注意","× 赤字"))) | T5: —
A6: C001 | B6: 東急グループ案件 | C6: 2024-08 | D6: =IFERROR(VLOOKUP(C6,▼売上原票!$A:$P,3,0)*VLOOKUP("612-1",▼マッピング!$A:$G,4,0)/100,0) | E6: =IFERROR(VLOOKUP(C6,▼売上原票!$A:$P,4,0)*VLOOKUP("612-2",▼マッピング!$A:$G,4,0)/100,0) | F6: =IFERROR(VLOOKUP(C6,▼売上原票!$A:$P,10,0)*VLOOKUP("615-1",▼マッピング!$A:$G,4,0)/100,0) | G6: =IFERROR(VLOOKUP(C6,▼売上原票!$A:$P,5,0)*VLOOKUP("613-1",▼マッピング!$A:$G,4,0)/100,0)+IFERROR(VLOOKUP(C6,▼売上原票!$A:$P,6,0)*VLOOKUP("613-2",▼マッピング!$A:$G,4,0)/100,0)+IFERROR(VLOOKUP(C6,▼売上原票!$A:$P,7,0)*VLOOKUP("614-1",▼マッピング!$A:$G,4,0)/100,0)+IFERROR(VLOOKUP(C6,▼売上原票!$A:$P,8,0)*VLOOKUP("614-2",▼マッピング!$A:$G,4,0)/100,0)+IFERROR(VLOOKUP(C6,▼売上原票!$A:$P,9,0)*VLOOKUP("614-3",▼マッピング!$A:$G,4,0)/100,0)+IFERROR(VLOOKUP(C6,▼売上原票!$A:$P,11,0)*VLOOKUP("615-2",▼マッピング!$A:$G,4,0)/100,0)+IFERROR(VLOOKUP(C6,▼売上原票!$A:$P,12,0)*VLOOKUP("615-3",▼マッピング!$A:$G,4,0)/100,0)+IFERROR(VLOOKUP(C6,▼売上原票!$A:$P,13,0)*VLOOKUP("615-4",▼マッピング!$A:$G,4,0)/100,0) | H6: =D6+E6+F6+G6 | P6: =I6+J6+K6+L6+M6+N6+O6 | Q6: =H6-P6 | R6: =IF(H6<>0,Q6/H6,0) | S6: =IF(R6>=0.25,"◎ 優良",IF(R6>=0.15,"○ 良好",IF(R6>=0.05,"△ 要注意","× 赤字"))) | T6: =IF(H5<>0,H6/H5-1,"")
A7: C001 | B7: 東急グループ案件 | C7: 2024-09 | D7: =IFERROR(VLOOKUP(C7,▼売上原票!$A:$P,3,0)*VLOOKUP("612-1",▼マッピング!$A:$G,4,0)/100,0) | E7: =IFERROR(VLOOKUP(C7,▼売上原票!$A:$P,4,0)*VLOOKUP("612-2",▼マッピング!$A:$G,4,0)/100,0) | F7: =IFERROR(VLOOKUP(C7,▼売上原票!$A:$P,10,0)*VLOOKUP("615-1",▼マッピング!$A:$G,4,0)/100,0) | G7: =IFERROR(VLOOKUP(C7,▼売上原票!$A:$P,5,0)*VLOOKUP("613-1",▼マッピング!$A:$G,4,0)/100,0)+IFERROR(VLOOKUP(C7,▼売上原票!$A:$P,6,0)*VLOOKUP("613-2",▼マッピング!$A:$G,4,0)/100,0)+IFERROR(VLOOKUP(C7,▼売上原票!$A:$P,7,0)*VLOOKUP("614-1",▼マッピング!$A:$G,4,0)/100,0)+IFERROR(VLOOKUP(C7,▼売上原票!$A:$P,8,0)*VLOOKUP("614-2",▼マッピング!$A:$G,4,0)/100,0)+IFERROR(VLOOKUP(C7,▼売上原票!$A:$P,9,0)*VLOOKUP("614-3",▼マッピング!$A:$G,4,0)/100,0)+IFERROR(VLOOKUP(C7,▼売上原票!$A:$P,11,0)*VLOOKUP("615-2",▼マッピング!$A:$G,4,0)/100,0)+IFERROR(VLOOKUP(C7,▼売上原票!$A:$P,12,0)*VLOOKUP("615-3",▼マッピング!$A:$G,4,0)/100,0)+IFERROR(VLOOKUP(C7,▼売上原票!$A:$P,13,0)*VLOOKUP("615-4",▼マッピング!$A:$G,4,0)/100,0) | H7: =D7+E7+F7+G7 | P7: =I7+J7+K7+L7+M7+N7+O7 | Q7: =H7-P7 | R7: =IF(H7<>0,Q7/H7,0) | S7: =IF(R7>=0.25,"◎ 優良",IF(R7>=0.15,"○ 良好",IF(R7>=0.05,"△ 要注意","× 赤字"))) | T7: =IF(H6<>0,H7/H6-1,"")
A8: C001 | B8: 東急グループ案件 | C8: 2024-10 | D8: =IFERROR(VLOOKUP(C8,▼売上原票!$A:$P,3,0)*VLOOKUP("612-1",▼マッピング!$A:$G,4,0)/100,0) | E8: =IFERROR(VLOOKUP(C8,▼売上原票!$A:$P,4,0)*VLOOKUP("612-2",▼マッピング!$A:$G,4,0)/100,0) | F8: =IFERROR(VLOOKUP(C8,▼売上原票!$A:$P,10,0)*VLOOKUP("615-1",▼マッピング!$A:$G,4,0)/100,0) | G8: =IFERROR(VLOOKUP(C8,▼売上原票!$A:$P,5,0)*VLOOKUP("613-1",▼マッピング!$A:$G,4,0)/100,0)+IFERROR(VLOOKUP(C8,▼売上原票!$A:$P,6,0)*VLOOKUP("613-2",▼マッピング!$A:$G,4,0)/100,0)+IFERROR(VLOOKUP(C8,▼売上原票!$A:$P,7,0)*VLOOKUP("614-1",▼マッピング!$A:$G,4,0)/100,0)+IFERROR(VLOOKUP(C8,▼売上原票!$A:$P,8,0)*VLOOKUP("614-2",▼マッピング!$A:$G,4,0)/100,0)+IFERROR(VLOOKUP(C8,▼売上原票!$A:$P,9,0)*VLOOKUP("614-3",▼マッピング!$A:$G,4,0)/100,0)+IFERROR(VLOOKUP(C8,▼売上原票!$A:$P,11,0)*VLOOKUP("615-2",▼マッピング!$A:$G,4,0)/100,0)+IFERROR(VLOOKUP(C8,▼売上原票!$A:$P,12,0)*VLOOKUP("615-3",▼マッピング!$A:$G,4,0)/100,0)+IFERROR(VLOOKUP(C8,▼売上原票!$A:$P,13,0)*VLOOKUP("615-4",▼マッピング!$A:$G,4,0)/100,0) | H8: =D8+E8+F8+G8 | P8: =I8+J8+K8+L8+M8+N8+O8 | Q8: =H8-P8 | R8: =IF(H8<>0,Q8/H8,0) | S8: =IF(R8>=0.25,"◎ 優良",IF(R8>=0.15,"○ 良好",IF(R8>=0.05,"△ 要注意","× 赤字"))) | T8: =IF(H7<>0,H8/H7-1,"")
A9: C001 | B9: 東急グループ案件 | C9: 2024-11 | D9: =IFERROR(VLOOKUP(C9,▼売上原票!$A:$P,3,0)*VLOOKUP("612-1",▼マッピング!$A:$G,4,0)/100,0) | E9: =IFERROR(VLOOKUP(C9,▼売上原票!$A:$P,4,0)*VLOOKUP("612-2",▼マッピング!$A:$G,4,0)/100,0) | F9: =IFERROR(VLOOKUP(C9,▼売上原票!$A:$P,10,0)*VLOOKUP("615-1",▼マッピング!$A:$G,4,0)/100,0) | G9: =IFERROR(VLOOKUP(C9,▼売上原票!$A:$P,5,0)*VLOOKUP("613-1",▼マッピング!$A:$G,4,0)/100,0)+IFERROR(VLOOKUP(C9,▼売上原票!$A:$P,6,0)*VLOOKUP("613-2",▼マッピング!$A:$G,4,0)/100,0)+IFERROR(VLOOKUP(C9,▼売上原票!$A:$P,7,0)*VLOOKUP("614-1",▼マッピング!$A:$G,4,0)/100,0)+IFERROR(VLOOKUP(C9,▼売上原票!$A:$P,8,0)*VLOOKUP("614-2",▼マッピング!$A:$G,4,0)/100,0)+IFERROR(VLOOKUP(C9,▼売上原票!$A:$P,9,0)*VLOOKUP("614-3",▼マッピング!$A:$G,4,0)/100,0)+IFERROR(VLOOKUP(C9,▼売上原票!$A:$P,11,0)*VLOOKUP("615-2",▼マッピング!$A:$G,4,0)/100,0)+IFERROR(VLOOKUP(C9,▼売上原票!$A:$P,12,0)*VLOOKUP("615-3",▼マッピング!$A:$G,4,0)/100,0)+IFERROR(VLOOKUP(C9,▼売上原票!$A:$P,13,0)*VLOOKUP("615-4",▼マッピング!$A:$G,4,0)/100,0) | H9: =D9+E9+F9+G9 | P9: =I9+J9+K9+L9+M9+N9+O9 | Q9: =H9-P9 | R9: =IF(H9<>0,Q9/H9,0) | S9: =IF(R9>=0.25,"◎ 優良",IF(R9>=0.15,"○ 良好",IF(R9>=0.05,"△ 要注意","× 赤字"))) | T9: =IF(H8<>0,H9/H8-1,"")
A10: C001 | B10: 東急グループ案件 | C10: 2024-12 | D10: =IFERROR(VLOOKUP(C10,▼売上原票!$A:$P,3,0)*VLOOKUP("612-1",▼マッピング!$A:$G,4,0)/100,0) | E10: =IFERROR(VLOOKUP(C10,▼売上原票!$A:$P,4,0)*VLOOKUP("612-2",▼マッピング!$A:$G,4,0)/100,0) | F10: =IFERROR(VLOOKUP(C10,▼売上原票!$A:$P,10,0)*VLOOKUP("615-1",▼マッピング!$A:$G,4,0)/100,0) | G10: =IFERROR(VLOOKUP(C10,▼売上原票!$A:$P,5,0)*VLOOKUP("613-1",▼マッピング!$A:$G,4,0)/100,0)+IFERROR(VLOOKUP(C10,▼売上原票!$A:$P,6,0)*VLOOKUP("613-2",▼マッピング!$A:$G,4,0)/100,0)+IFERROR(VLOOKUP(C10,▼売上原票!$A:$P,7,0)*VLOOKUP("614-1",▼マッピング!$A:$G,4,0)/100,0)+IFERROR(VLOOKUP(C10,▼売上原票!$A:$P,8,0)*VLOOKUP("614-2",▼マッピング!$A:$G,4,0)/100,0)+IFERROR(VLOOKUP(C10,▼売上原票!$A:$P,9,0)*VLOOKUP("614-3",▼マッピング!$A:$G,4,0)/100,0)+IFERROR(VLOOKUP(C10,▼売上原票!$A:$P,11,0)*VLOOKUP("615-2",▼マッピング!$A:$G,4,0)/100,0)+IFERROR(VLOOKUP(C10,▼売上原票!$A:$P,12,0)*VLOOKUP("615-3",▼マッピング!$A:$G,4,0)/100,0)+IFERROR(VLOOKUP(C10,▼売上原票!$A:$P,13,0)*VLOOKUP("615-4",▼マッピング!$A:$G,4,0)/100,0) | H10: =D10+E10+F10+G10 | P10: =I10+J10+K10+L10+M10+N10+O10 | Q10: =H10-P10 | R10: =IF(H10<>0,Q10/H10,0) | S10: =IF(R10>=0.25,"◎ 優良",IF(R10>=0.15,"○ 良好",IF(R10>=0.05,"△ 要注意","× 赤字"))) | T10: =IF(H9<>0,H10/H9-1,"")
A11: C001 | B11: 東急グループ案件 | C11: 2025-01 | D11: =IFERROR(VLOOKUP(C11,▼売上原票!$A:$P,3,0)*VLOOKUP("612-1",▼マッピング!$A:$G,4,0)/100,0) | E11: =IFERROR(VLOOKUP(C11,▼売上原票!$A:$P,4,0)*VLOOKUP("612-2",▼マッピング!$A:$G,4,0)/100,0) | F11: =IFERROR(VLOOKUP(C11,▼売上原票!$A:$P,10,0)*VLOOKUP("615-1",▼マッピング!$A:$G,4,0)/100,0) | G11: =IFERROR(VLOOKUP(C11,▼売上原票!$A:$P,5,0)*VLOOKUP("613-1",▼マッピング!$A:$G,4,0)/100,0)+IFERROR(VLOOKUP(C11,▼売上原票!$A:$P,6,0)*VLOOKUP("613-2",▼マッピング!$A:$G,4,0)/100,0)+IFERROR(VLOOKUP(C11,▼売上原票!$A:$P,7,0)*VLOOKUP("614-1",▼マッピング!$A:$G,4,0)/100,0)+IFERROR(VLOOKUP(C11,▼売上原票!$A:$P,8,0)*VLOOKUP("614-2",▼マッピング!$A:$G,4,0)/100,0)+IFERROR(VLOOKUP(C11,▼売上原票!$A:$P,9,0)*VLOOKUP("614-3",▼マッピング!$A:$G,4,0)/100,0)+IFERROR(VLOOKUP(C11,▼売上原票!$A:$P,11,0)*VLOOKUP("615-2",▼マッピング!$A:$G,4,0)/100,0)+IFERROR(VLOOKUP(C11,▼売上原票!$A:$P,12,0)*VLOOKUP("615-3",▼マッピング!$A:$G,4,0)/100,0)+IFERROR(VLOOKUP(C11,▼売上原票!$A:$P,13,0)*VLOOKUP("615-4",▼マッピング!$A:$G,4,0)/100,0) | H11: =D11+E11+F11+G11 | P11: =I11+J11+K11+L11+M11+N11+O11 | Q11: =H11-P11 | R11: =IF(H11<>0,Q11/H11,0) | S11: =IF(R11>=0.25,"◎ 優良",IF(R11>=0.15,"○ 良好",IF(R11>=0.05,"△ 要注意","× 赤字"))) | T11: =IF(H10<>0,H11/H10-1,"")
A12: C001 | B12: 東急グループ案件 | C12: 2025-02 | D12: =IFERROR(VLOOKUP(C12,▼売上原票!$A:$P,3,0)*VLOOKUP("612-1",▼マッピング!$A:$G,4,0)/100,0) | E12: =IFERROR(VLOOKUP(C12,▼売上原票!$A:$P,4,0)*VLOOKUP("612-2",▼マッピング!$A:$G,4,0)/100,0) | F12: =IFERROR(VLOOKUP(C12,▼売上原票!$A:$P,10,0)*VLOOKUP("615-1",▼マッピング!$A:$G,4,0)/100,0) | G12: =IFERROR(VLOOKUP(C12,▼売上原票!$A:$P,5,0)*VLOOKUP("613-1",▼マッピング!$A:$G,4,0)/100,0)+IFERROR(VLOOKUP(C12,▼売上原票!$A:$P,6,0)*VLOOKUP("613-2",▼マッピング!$A:$G,4,0)/100,0)+IFERROR(VLOOKUP(C12,▼売上原票!$A:$P,7,0)*VLOOKUP("614-1",▼マッピング!$A:$G,4,0)/100,0)+IFERROR(VLOOKUP(C12,▼売上原票!$A:$P,8,0)*VLOOKUP("614-2",▼マッピング!$A:$G,4,0)/100,0)+IFERROR(VLOOKUP(C12,▼売上原票!$A:$P,9,0)*VLOOKUP("614-3",▼マッピング!$A:$G,4,0)/100,0)+IFERROR(VLOOKUP(C12,▼売上原票!$A:$P,11,0)*VLOOKUP("615-2",▼マッピング!$A:$G,4,0)/100,0)+IFERROR(VLOOKUP(C12,▼売上原票!$A:$P,12,0)*VLOOKUP("615-3",▼マッピング!$A:$G,4,0)/100,0)+IFERROR(VLOOKUP(C12,▼売上原票!$A:$P,13,0)*VLOOKUP("615-4",▼マッピング!$A:$G,4,0)/100,0) | H12: =D12+E12+F12+G12 | P12: =I12+J12+K12+L12+M12+N12+O12 | Q12: =H12-P12 | R12: =IF(H12<>0,Q12/H12,0) | S12: =IF(R12>=0.25,"◎ 優良",IF(R12>=0.15,"○ 良好",IF(R12>=0.05,"△ 要注意","× 赤字"))) | T12: =IF(H11<>0,H12/H11-1,"")
A13: C001 | B13: 東急グループ案件 | C13: 2025-03 | D13: =IFERROR(VLOOKUP(C13,▼売上原票!$A:$P,3,0)*VLOOKUP("612-1",▼マッピング!$A:$G,4,0)/100,0) | E13: =IFERROR(VLOOKUP(C13,▼売上原票!$A:$P,4,0)*VLOOKUP("612-2",▼マッピング!$A:$G,4,0)/100,0) | F13: =IFERROR(VLOOKUP(C13,▼売上原票!$A:$P,10,0)*VLOOKUP("615-1",▼マッピング!$A:$G,4,0)/100,0) | G13: =IFERROR(VLOOKUP(C13,▼売上原票!$A:$P,5,0)*VLOOKUP("613-1",▼マッピング!$A:$G,4,0)/100,0)+IFERROR(VLOOKUP(C13,▼売上原票!$A:$P,6,0)*VLOOKUP("613-2",▼マッピング!$A:$G,4,0)/100,0)+IFERROR(VLOOKUP(C13,▼売上原票!$A:$P,7,0)*VLOOKUP("614-1",▼マッピング!$A:$G,4,0)/100,0)+IFERROR(VLOOKUP(C13,▼売上原票!$A:$P,8,0)*VLOOKUP("614-2",▼マッピング!$A:$G,4,0)/100,0)+IFERROR(VLOOKUP(C13,▼売上原票!$A:$P,9,0)*VLOOKUP("614-3",▼マッピング!$A:$G,4,0)/100,0)+IFERROR(VLOOKUP(C13,▼売上原票!$A:$P,11,0)*VLOOKUP("615-2",▼マッピング!$A:$G,4,0)/100,0)+IFERROR(VLOOKUP(C13,▼売上原票!$A:$P,12,0)*VLOOKUP("615-3",▼マッピング!$A:$G,4,0)/100,0)+IFERROR(VLOOKUP(C13,▼売上原票!$A:$P,13,0)*VLOOKUP("615-4",▼マッピング!$A:$G,4,0)/100,0) | H13: =D13+E13+F13+G13 | P13: =I13+J13+K13+L13+M13+N13+O13 | Q13: =H13-P13 | R13: =IF(H13<>0,Q13/H13,0) | S13: =IF(R13>=0.25,"◎ 優良",IF(R13>=0.15,"○ 良好",IF(R13>=0.05,"△ 要注意","× 赤字"))) | T13: =IF(H12<>0,H13/H12-1,"")
A14: C001 | B14: 東急グループ案件 | C14: 2025-04 | D14: =IFERROR(VLOOKUP(C14,▼売上原票!$A:$P,3,0)*VLOOKUP("612-1",▼マッピング!$A:$G,4,0)/100,0) | E14: =IFERROR(VLOOKUP(C14,▼売上原票!$A:$P,4,0)*VLOOKUP("612-2",▼マッピング!$A:$G,4,0)/100,0) | F14: =IFERROR(VLOOKUP(C14,▼売上原票!$A:$P,10,0)*VLOOKUP("615-1",▼マッピング!$A:$G,4,0)/100,0) | G14: =IFERROR(VLOOKUP(C14,▼売上原票!$A:$P,5,0)*VLOOKUP("613-1",▼マッピング!$A:$G,4,0)/100,0)+IFERROR(VLOOKUP(C14,▼売上原票!$A:$P,6,0)*VLOOKUP("613-2",▼マッピング!$A:$G,4,0)/100,0)+IFERROR(VLOOKUP(C14,▼売上原票!$A:$P,7,0)*VLOOKUP("614-1",▼マッピング!$A:$G,4,0)/100,0)+IFERROR(VLOOKUP(C14,▼売上原票!$A:$P,8,0)*VLOOKUP("614-2",▼マッピング!$A:$G,4,0)/100,0)+IFERROR(VLOOKUP(C14,▼売上原票!$A:$P,9,0)*VLOOKUP("614-3",▼マッピング!$A:$G,4,0)/100,0)+IFERROR(VLOOKUP(C14,▼売上原票!$A:$P,11,0)*VLOOKUP("615-2",▼マッピング!$A:$G,4,0)/100,0)+IFERROR(VLOOKUP(C14,▼売上原票!$A:$P,12,0)*VLOOKUP("615-3",▼マッピング!$A:$G,4,0)/100,0)+IFERROR(VLOOKUP(C14,▼売上原票!$A:$P,13,0)*VLOOKUP("615-4",▼マッピング!$A:$G,4,0)/100,0) | H14: =D14+E14+F14+G14 | P14: =I14+J14+K14+L14+M14+N14+O14 | Q14: =H14-P14 | R14: =IF(H14<>0,Q14/H14,0) | S14: =IF(R14>=0.25,"◎ 優良",IF(R14>=0.15,"○ 良好",IF(R14>=0.05,"△ 要注意","× 赤字"))) | T14: =IF(H13<>0,H14/H13-1,"")
A15: C001 | B15: 東急グループ案件 | C15: 2025-05 | D15: =IFERROR(VLOOKUP(C15,▼売上原票!$A:$P,3,0)*VLOOKUP("612-1",▼マッピング!$A:$G,4,0)/100,0) | E15: =IFERROR(VLOOKUP(C15,▼売上原票!$A:$P,4,0)*VLOOKUP("612-2",▼マッピング!$A:$G,4,0)/100,0) | F15: =IFERROR(VLOOKUP(C15,▼売上原票!$A:$P,10,0)*VLOOKUP("615-1",▼マッピング!$A:$G,4,0)/100,0) | G15: =IFERROR(VLOOKUP(C15,▼売上原票!$A:$P,5,0)*VLOOKUP("613-1",▼マッピング!$A:$G,4,0)/100,0)+IFERROR(VLOOKUP(C15,▼売上原票!$A:$P,6,0)*VLOOKUP("613-2",▼マッピング!$A:$G,4,0)/100,0)+IFERROR(VLOOKUP(C15,▼売上原票!$A:$P,7,0)*VLOOKUP("614-1",▼マッピング!$A:$G,4,0)/100,0)+IFERROR(VLOOKUP(C15,▼売上原票!$A:$P,8,0)*VLOOKUP("614-2",▼マッピング!$A:$G,4,0)/100,0)+IFERROR(VLOOKUP(C15,▼売上原票!$A:$P,9,0)*VLOOKUP("614-3",▼マッピング!$A:$G,4,0)/100,0)+IFERROR(VLOOKUP(C15,▼売上原票!$A:$P,11,0)*VLOOKUP("615-2",▼マッピング!$A:$G,4,0)/100,0)+IFERROR(VLOOKUP(C15,▼売上原票!$A:$P,12,0)*VLOOKUP("615-3",▼マッピング!$A:$G,4,0)/100,0)+IFERROR(VLOOKUP(C15,▼売上原票!$A:$P,13,0)*VLOOKUP("615-4",▼マッピング!$A:$G,4,0)/100,0) | H15: =D15+E15+F15+G15 | P15: =I15+J15+K15+L15+M15+N15+O15 | Q15: =H15-P15 | R15: =IF(H15<>0,Q15/H15,0) | S15: =IF(R15>=0.25,"◎ 優良",IF(R15>=0.15,"○ 良好",IF(R15>=0.05,"△ 要注意","× 赤字"))) | T15: =IF(H14<>0,H15/H14-1,"")
A16: C001 | B16: 東急グループ案件 | C16: 2025-06 | D16: =IFERROR(VLOOKUP(C16,▼売上原票!$A:$P,3,0)*VLOOKUP("612-1",▼マッピング!$A:$G,4,0)/100,0) | E16: =IFERROR(VLOOKUP(C16,▼売上原票!$A:$P,4,0)*VLOOKUP("612-2",▼マッピング!$A:$G,4,0)/100,0) | F16: =IFERROR(VLOOKUP(C16,▼売上原票!$A:$P,10,0)*VLOOKUP("615-1",▼マッピング!$A:$G,4,0)/100,0) | G16: =IFERROR(VLOOKUP(C16,▼売上原票!$A:$P,5,0)*VLOOKUP("613-1",▼マッピング!$A:$G,4,0)/100,0)+IFERROR(VLOOKUP(C16,▼売上原票!$A:$P,6,0)*VLOOKUP("613-2",▼マッピング!$A:$G,4,0)/100,0)+IFERROR(VLOOKUP(C16,▼売上原票!$A:$P,7,0)*VLOOKUP("614-1",▼マッピング!$A:$G,4,0)/100,0)+IFERROR(VLOOKUP(C16,▼売上原票!$A:$P,8,0)*VLOOKUP("614-2",▼マッピング!$A:$G,4,0)/100,0)+IFERROR(VLOOKUP(C16,▼売上原票!$A:$P,9,0)*VLOOKUP("614-3",▼マッピング!$A:$G,4,0)/100,0)+IFERROR(VLOOKUP(C16,▼売上原票!$A:$P,11,0)*VLOOKUP("615-2",▼マッピング!$A:$G,4,0)/100,0)+IFERROR(VLOOKUP(C16,▼売上原票!$A:$P,12,0)*VLOOKUP("615-3",▼マッピング!$A:$G,4,0)/100,0)+IFERROR(VLOOKUP(C16,▼売上原票!$A:$P,13,0)*VLOOKUP("615-4",▼マッピング!$A:$G,4,0)/100,0) | H16: =D16+E16+F16+G16 | P16: =I16+J16+K16+L16+M16+N16+O16 | Q16: =H16-P16 | R16: =IF(H16<>0,Q16/H16,0) | S16: =IF(R16>=0.25,"◎ 優良",IF(R16>=0.15,"○ 良好",IF(R16>=0.05,"△ 要注意","× 赤字"))) | T16: =IF(H15<>0,H16/H15-1,"")
A17: C001 | B17: 東急グループ案件 | C17: 2025-07 | D17: =IFERROR(VLOOKUP(C17,▼売上原票!$A:$P,3,0)*VLOOKUP("612-1",▼マッピング!$A:$G,4,0)/100,0) | E17: =IFERROR(VLOOKUP(C17,▼売上原票!$A:$P,4,0)*VLOOKUP("612-2",▼マッピング!$A:$G,4,0)/100,0) | F17: =IFERROR(VLOOKUP(C17,▼売上原票!$A:$P,10,0)*VLOOKUP("615-1",▼マッピング!$A:$G,4,0)/100,0) | G17: =IFERROR(VLOOKUP(C17,▼売上原票!$A:$P,5,0)*VLOOKUP("613-1",▼マッピング!$A:$G,4,0)/100,0)+IFERROR(VLOOKUP(C17,▼売上原票!$A:$P,6,0)*VLOOKUP("613-2",▼マッピング!$A:$G,4,0)/100,0)+IFERROR(VLOOKUP(C17,▼売上原票!$A:$P,7,0)*VLOOKUP("614-1",▼マッピング!$A:$G,4,0)/100,0)+IFERROR(VLOOKUP(C17,▼売上原票!$A:$P,8,0)*VLOOKUP("614-2",▼マッピング!$A:$G,4,0)/100,0)+IFERROR(VLOOKUP(C17,▼売上原票!$A:$P,9,0)*VLOOKUP("614-3",▼マッピング!$A:$G,4,0)/100,0)+IFERROR(VLOOKUP(C17,▼売上原票!$A:$P,11,0)*VLOOKUP("615-2",▼マッピング!$A:$G,4,0)/100,0)+IFERROR(VLOOKUP(C17,▼売上原票!$A:$P,12,0)*VLOOKUP("615-3",▼マッピング!$A:$G,4,0)/100,0)+IFERROR(VLOOKUP(C17,▼売上原票!$A:$P,13,0)*VLOOKUP("615-4",▼マッピング!$A:$G,4,0)/100,0) | H17: =D17+E17+F17+G17 | P17: =I17+J17+K17+L17+M17+N17+O17 | Q17: =H17-P17 | R17: =IF(H17<>0,Q17/H17,0) | S17: =IF(R17>=0.25,"◎ 優良",IF(R17>=0.15,"○ 良好",IF(R17>=0.05,"△ 要注意","× 赤字"))) | T17: =IF(H16<>0,H17/H16-1,"")
... A21: C001 | B21: 東急グループ案件 | C21: 2025-11 | D21: =IFERROR(VLOOKUP(C21,▼売上原票!$A:$P,3,0)*VLOOKUP("612-1",▼マッピング!$A:$G,4,0)/100,0) | E21: =IFERROR(VLOOKUP(C21,▼売上原票!$A:$P,4,0)*VLOOKUP("612-2",▼マッピング!$A:$G,4,0)/100,0) | F21: =IFERROR(VLOOKUP(C21,▼売上原票!$A:$P,10,0)*VLOOKUP("615-1",▼マッピング!$A:$G,4,0)/100,0) | G21: =IFERROR(VLOOKUP(C21,▼売上原票!$A:$P,5,0)*VLOOKUP("613-1",▼マッピング!$A:$G,4,0)/100,0)+IFERROR(VLOOKUP(C21,▼売上原票!$A:$P,6,0)*VLOOKUP("613-2",▼マッピング!$A:$G,4,0)/100,0)+IFERROR(VLOOKUP(C21,▼売上原票!$A:$P,7,0)*VLOOKUP("614-1",▼マッピング!$A:$G,4,0)/100,0)+IFERROR(VLOOKUP(C21,▼売上原票!$A:$P,8,0)*VLOOKUP("614-2",▼マッピング!$A:$G,4,0)/100,0)+IFERROR(VLOOKUP(C21,▼売上原票!$A:$P,9,0)*VLOOKUP("614-3",▼マッピング!$A:$G,4,0)/100,0)+IFERROR(VLOOKUP(C21,▼売上原票!$A:$P,11,0)*VLOOKUP("615-2",▼マッピング!$A:$G,4,0)/100,0)+IFERROR(VLOOKUP(C21,▼売上原票!$A:$P,12,0)*VLOOKUP("615-3",▼マッピング!$A:$G,4,0)/100,0)+IFERROR(VLOOKUP(C21,▼売上原票!$A:$P,13,0)*VLOOKUP("615-4",▼マッピング!$A:$G,4,0)/100,0) | H21: =D21+E21+F21+G21 | P21: =I21+J21+K21+L21+M21+N21+O21 | Q21: =H21-P21 | R21: =IF(H21<>0,Q21/H21,0) | S21: =IF(R21>=0.25,"◎ 優良",IF(R21>=0.15,"○ 良好",IF(R21>=0.05,"△ 要注意","× 赤字"))) | T21: =IF(H20<>0,H21/H20-1,"")
A23: C002 | B23: 都営地下鉄案件 | C23: 2024-07 | D23: =IFERROR(VLOOKUP(C23,▼売上原票!$A:$P,3,0)*VLOOKUP("612-1",▼マッピング!$A:$G,5,0)/100,0) | E23: =IFERROR(VLOOKUP(C23,▼売上原票!$A:$P,4,0)*VLOOKUP("612-2",▼マッピング!$A:$G,5,0)/100,0) | F23: =IFERROR(VLOOKUP(C23,▼売上原票!$A:$P,10,0)*VLOOKUP("615-1",▼マッピング!$A:$G,5,0)/100,0) | G23: =IFERROR(VLOOKUP(C23,▼売上原票!$A:$P,5,0)*VLOOKUP("613-1",▼マッピング!$A:$G,5,0)/100,0)+IFERROR(VLOOKUP(C23,▼売上原票!$A:$P,6,0)*VLOOKUP("613-2",▼マッピング!$A:$G,5,0)/100,0)+IFERROR(VLOOKUP(C23,▼売上原票!$A:$P,7,0)*VLOOKUP("614-1",▼マッピング!$A:$G,5,0)/100,0)+IFERROR(VLOOKUP(C23,▼売上原票!$A:$P,8,0)*VLOOKUP("614-2",▼マッピング!$A:$G,5,0)/100,0)+IFERROR(VLOOKUP(C23,▼売上原票!$A:$P,9,0)*VLOOKUP("614-3",▼マッピング!$A:$G,5,0)/100,0)+IFERROR(VLOOKUP(C23,▼売上原票!$A:$P,11,0)*VLOOKUP("615-2",▼マッピング!$A:$G,5,0)/100,0)+IFERROR(VLOOKUP(C23,▼売上原票!$A:$P,12,0)*VLOOKUP("615-3",▼マッピング!$A:$G,5,0)/100,0)+IFERROR(VLOOKUP(C23,▼売上原票!$A:$P,13,0)*VLOOKUP("615-4",▼マッピング!$A:$G,5,0)/100,0) | H23: =D23+E23+F23+G23 | P23: =I23+J23+K23+L23+M23+N23+O23 | Q23: =H23-P23 | R23: =IF(H23<>0,Q23/H23,0) | S23: =IF(R23>=0.25,"◎ 優良",IF(R23>=0.15,"○ 良好",IF(R23>=0.05,"△ 要注意","× 赤字"))) | T23: —
A24: C002 | B24: 都営地下鉄案件 | C24: 2024-08 | D24: =IFERROR(VLOOKUP(C24,▼売上原票!$A:$P,3,0)*VLOOKUP("612-1",▼マッピング!$A:$G,5,0)/100,0) | E24: =IFERROR(VLOOKUP(C24,▼売上原票!$A:$P,4,0)*VLOOKUP("612-2",▼マッピング!$A:$G,5,0)/100,0) | F24: =IFERROR(VLOOKUP(C24,▼売上原票!$A:$P,10,0)*VLOOKUP("615-1",▼マッピング!$A:$G,5,0)/100,0) | G24: =IFERROR(VLOOKUP(C24,▼売上原票!$A:$P,5,0)*VLOOKUP("613-1",▼マッピング!$A:$G,5,0)/100,0)+IFERROR(VLOOKUP(C24,▼売上原票!$A:$P,6,0)*VLOOKUP("613-2",▼マッピング!$A:$G,5,0)/100,0)+IFERROR(VLOOKUP(C24,▼売上原票!$A:$P,7,0)*VLOOKUP("614-1",▼マッピング!$A:$G,5,0)/100,0)+IFERROR(VLOOKUP(C24,▼売上原票!$A:$P,8,0)*VLOOKUP("614-2",▼マッピング!$A:$G,5,0)/100,0)+IFERROR(VLOOKUP(C24,▼売上原票!$A:$P,9,0)*VLOOKUP("614-3",▼マッピング!$A:$G,5,0)/100,0)+IFERROR(VLOOKUP(C24,▼売上原票!$A:$P,11,0)*VLOOKUP("615-2",▼マッピング!$A:$G,5,0)/100,0)+IFERROR(VLOOKUP(C24,▼売上原票!$A:$P,12,0)*VLOOKUP("615-3",▼マッピング!$A:$G,5,0)/100,0)+IFERROR(VLOOKUP(C24,▼売上原票!$A:$P,13,0)*VLOOKUP("615-4",▼マッピング!$A:$G,5,0)/100,0) | H24: =D24+E24+F24+G24 | P24: =I24+J24+K24+L24+M24+N24+O24 | Q24: =H24-P24 | R24: =IF(H24<>0,Q24/H24,0) | S24: =IF(R24>=0.25,"◎ 優良",IF(R24>=0.15,"○ 良好",IF(R24>=0.05,"△ 要注意","× 赤字"))) | T24: =IF(H23<>0,H24/H23-1,"")
A25: C002 | B25: 都営地下鉄案件 | C25: 2024-09 | D25: =IFERROR(VLOOKUP(C25,▼売上原票!$A:$P,3,0)*VLOOKUP("612-1",▼マッピング!$A:$G,5,0)/100,0) | E25: =IFERROR(VLOOKUP(C25,▼売上原票!$A:$P,4,0)*VLOOKUP("612-2",▼マッピング!$A:$G,5,0)/100,0) | F25: =IFERROR(VLOOKUP(C25,▼売上原票!$A:$P,10,0)*VLOOKUP("615-1",▼マッピング!$A:$G,5,0)/100,0) | G25: =IFERROR(VLOOKUP(C25,▼売上原票!$A:$P,5,0)*VLOOKUP("613-1",▼マッピング!$A:$G,5,0)/100,0)+IFERROR(VLOOKUP(C25,▼売上原票!$A:$P,6,0)*VLOOKUP("613-2",▼マッピング!$A:$G,5,0)/100,0)+IFERROR(VLOOKUP(C25,▼売上原票!$A:$P,7,0)*VLOOKUP("614-1",▼マッピング!$A:$G,5,0)/100,0)+IFERROR(VLOOKUP(C25,▼売上原票!$A:$P,8,0)*VLOOKUP("614-2",▼マッピング!$A:$G,5,0)/100,0)+IFERROR(VLOOKUP(C25,▼売上原票!$A:$P,9,0)*VLOOKUP("614-3",▼マッピング!$A:$G,5,0)/100,0)+IFERROR(VLOOKUP(C25,▼売上原票!$A:$P,11,0)*VLOOKUP("615-2",▼マッピング!$A:$G,5,0)/100,0)+IFERROR(VLOOKUP(C25,▼売上原票!$A:$P,12,0)*VLOOKUP("615-3",▼マッピング!$A:$G,5,0)/100,0)+IFERROR(VLOOKUP(C25,▼売上原票!$A:$P,13,0)*VLOOKUP("615-4",▼マッピング!$A:$G,5,0)/100,0) | H25: =D25+E25+F25+G25 | P25: =I25+J25+K25+L25+M25+N25+O25 | Q25: =H25-P25 | R25: =IF(H25<>0,Q25/H25,0) | S25: =IF(R25>=0.25,"◎ 優良",IF(R25>=0.15,"○ 良好",IF(R25>=0.05,"△ 要注意","× 赤字"))) | T25: =IF(H24<>0,H25/H24-1,"")
A26: C002 | B26: 都営地下鉄案件 | C26: 2024-10 | D26: =IFERROR(VLOOKUP(C26,▼売上原票!$A:$P,3,0)*VLOOKUP("612-1",▼マッピング!$A:$G,5,0)/100,0) | E26: =IFERROR(VLOOKUP(C26,▼売上原票!$A:$P,4,0)*VLOOKUP("612-2",▼マッピング!$A:$G,5,0)/100,0) | F26: =IFERROR(VLOOKUP(C26,▼売上原票!$A:$P,10,0)*VLOOKUP("615-1",▼マッピング!$A:$G,5,0)/100,0) | G26: =IFERROR(VLOOKUP(C26,▼売上原票!$A:$P,5,0)*VLOOKUP("613-1",▼マッピング!$A:$G,5,0)/100,0)+IFERROR(VLOOKUP(C26,▼売上原票!$A:$P,6,0)*VLOOKUP("613-2",▼マッピング!$A:$G,5,0)/100,0)+IFERROR(VLOOKUP(C26,▼売上原票!$A:$P,7,0)*VLOOKUP("614-1",▼マッピング!$A:$G,5,0)/100,0)+IFERROR(VLOOKUP(C26,▼売上原票!$A:$P,8,0)*VLOOKUP("614-2",▼マッピング!$A:$G,5,0)/100,0)+IFERROR(VLOOKUP(C26,▼売上原票!$A:$P,9,0)*VLOOKUP("614-3",▼マッピング!$A:$G,5,0)/100,0)+IFERROR(VLOOKUP(C26,▼売上原票!$A:$P,11,0)*VLOOKUP("615-2",▼マッピング!$A:$G,5,0)/100,0)+IFERROR(VLOOKUP(C26,▼売上原票!$A:$P,12,0)*VLOOKUP("615-3",▼マッピング!$A:$G,5,0)/100,0)+IFERROR(VLOOKUP(C26,▼売上原票!$A:$P,13,0)*VLOOKUP("615-4",▼マッピング!$A:$G,5,0)/100,0) | H26: =D26+E26+F26+G26 | P26: =I26+J26+K26+L26+M26+N26+O26 | Q26: =H26-P26 | R26: =IF(H26<>0,Q26/H26,0) | S26: =IF(R26>=0.25,"◎ 優良",IF(R26>=0.15,"○ 良好",IF(R26>=0.05,"△ 要注意","× 赤字"))) | T26: =IF(H25<>0,H26/H25-1,"")
A27: C002 | B27: 都営地下鉄案件 | C27: 2024-11 | D27: =IFERROR(VLOOKUP(C27,▼売上原票!$A:$P,3,0)*VLOOKUP("612-1",▼マッピング!$A:$G,5,0)/100,0) | E27: =IFERROR(VLOOKUP(C27,▼売上原票!$A:$P,4,0)*VLOOKUP("612-2",▼マッピング!$A:$G,5,0)/100,0) | F27: =IFERROR(VLOOKUP(C27,▼売上原票!$A:$P,10,0)*VLOOKUP("615-1",▼マッピング!$A:$G,5,0)/100,0) | G27: =IFERROR(VLOOKUP(C27,▼売上原票!$A:$P,5,0)*VLOOKUP("613-1",▼マッピング!$A:$G,5,0)/100,0)+IFERROR(VLOOKUP(C27,▼売上原票!$A:$P,6,0)*VLOOKUP("613-2",▼マッピング!$A:$G,5,0)/100,0)+IFERROR(VLOOKUP(C27,▼売上原票!$A:$P,7,0)*VLOOKUP("614-1",▼マッピング!$A:$G,5,0)/100,0)+IFERROR(VLOOKUP(C27,▼売上原票!$A:$P,8,0)*VLOOKUP("614-2",▼マッピング!$A:$G,5,0)/100,0)+IFERROR(VLOOKUP(C27,▼売上原票!$A:$P,9,0)*VLOOKUP("614-3",▼マッピング!$A:$G,5,0)/100,0)+IFERROR(VLOOKUP(C27,▼売上原票!$A:$P,11,0)*VLOOKUP("615-2",▼マッピング!$A:$G,5,0)/100,0)+IFERROR(VLOOKUP(C27,▼売上原票!$A:$P,12,0)*VLOOKUP("615-3",▼マッピング!$A:$G,5,0)/100,0)+IFERROR(VLOOKUP(C27,▼売上原票!$A:$P,13,0)*VLOOKUP("615-4",▼マッピング!$A:$G,5,0)/100,0) | H27: =D27+E27+F27+G27 | P27: =I27+J27+K27+L27+M27+N27+O27 | Q27: =H27-P27 | R27: =IF(H27<>0,Q27/H27,0) | S27: =IF(R27>=0.25,"◎ 優良",IF(R27>=0.15,"○ 良好",IF(R27>=0.05,"△ 要注意","× 赤字"))) | T27: =IF(H26<>0,H27/H26-1,"")
A28: C002 | B28: 都営地下鉄案件 | C28: 2024-12 | D28: =IFERROR(VLOOKUP(C28,▼売上原票!$A:$P,3,0)*VLOOKUP("612-1",▼マッピング!$A:$G,5,0)/100,0) | E28: =IFERROR(VLOOKUP(C28,▼売上原票!$A:$P,4,0)*VLOOKUP("612-2",▼マッピング!$A:$G,5,0)/100,0) | F28: =IFERROR(VLOOKUP(C28,▼売上原票!$A:$P,10,0)*VLOOKUP("615-1",▼マッピング!$A:$G,5,0)/100,0) | G28: =IFERROR(VLOOKUP(C28,▼売上原票!$A:$P,5,0)*VLOOKUP("613-1",▼マッピング!$A:$G,5,0)/100,0)+IFERROR(VLOOKUP(C28,▼売上原票!$A:$P,6,0)*VLOOKUP("613-2",▼マッピング!$A:$G,5,0)/100,0)+IFERROR(VLOOKUP(C28,▼売上原票!$A:$P,7,0)*VLOOKUP("614-1",▼マッピング!$A:$G,5,0)/100,0)+IFERROR(VLOOKUP(C28,▼売上原票!$A:$P,8,0)*VLOOKUP("614-2",▼マッピング!$A:$G,5,0)/100,0)+IFERROR(VLOOKUP(C28,▼売上原票!$A:$P,9,0)*VLOOKUP("614-3",▼マッピング!$A:$G,5,0)/100,0)+IFERROR(VLOOKUP(C28,▼売上原票!$A:$P,11,0)*VLOOKUP("615-2",▼マッピング!$A:$G,5,0)/100,0)+IFERROR(VLOOKUP(C28,▼売上原票!$A:$P,12,0)*VLOOKUP("615-3",▼マッピング!$A:$G,5,0)/100,0)+IFERROR(VLOOKUP(C28,▼売上原票!$A:$P,13,0)*VLOOKUP("615-4",▼マッピング!$A:$G,5,0)/100,0) | H28: =D28+E28+F28+G28 | P28: =I28+J28+K28+L28+M28+N28+O28 | Q28: =H28-P28 | R28: =IF(H28<>0,Q28/H28,0) | S28: =IF(R28>=0.25,"◎ 優良",IF(R28>=0.15,"○ 良好",IF(R28>=0.05,"△ 要注意","× 赤字"))) | T28: =IF(H27<>0,H28/H27-1,"")
A29: C002 | B29: 都営地下鉄案件 | C29: 2025-01 | D29: =IFERROR(VLOOKUP(C29,▼売上原票!$A:$P,3,0)*VLOOKUP("612-1",▼マッピング!$A:$G,5,0)/100,0) | E29: =IFERROR(VLOOKUP(C29,▼売上原票!$A:$P,4,0)*VLOOKUP("612-2",▼マッピング!$A:$G,5,0)/100,0) | F29: =IFERROR(VLOOKUP(C29,▼売上原票!$A:$P,10,0)*VLOOKUP("615-1",▼マッピング!$A:$G,5,0)/100,0) | G29: =IFERROR(VLOOKUP(C29,▼売上原票!$A:$P,5,0)*VLOOKUP("613-1",▼マッピング!$A:$G,5,0)/100,0)+IFERROR(VLOOKUP(C29,▼売上原票!$A:$P,6,0)*VLOOKUP("613-2",▼マッピング!$A:$G,5,0)/100,0)+IFERROR(VLOOKUP(C29,▼売上原票!$A:$P,7,0)*VLOOKUP("614-1",▼マッピング!$A:$G,5,0)/100,0)+IFERROR(VLOOKUP(C29,▼売上原票!$A:$P,8,0)*VLOOKUP("614-2",▼マッピング!$A:$G,5,0)/100,0)+IFERROR(VLOOKUP(C29,▼売上原票!$A:$P,9,0)*VLOOKUP("614-3",▼マッピング!$A:$G,5,0)/100,0)+IFERROR(VLOOKUP(C29,▼売上原票!$A:$P,11,0)*VLOOKUP("615-2",▼マッピング!$A:$G,5,0)/100,0)+IFERROR(VLOOKUP(C29,▼売上原票!$A:$P,12,0)*VLOOKUP("615-3",▼マッピング!$A:$G,5,0)/100,0)+IFERROR(VLOOKUP(C29,▼売上原票!$A:$P,13,0)*VLOOKUP("615-4",▼マッピング!$A:$G,5,0)/100,0) | H29: =D29+E29+F29+G29 | P29: =I29+J29+K29+L29+M29+N29+O29 | Q29: =H29-P29 | R29: =IF(H29<>0,Q29/H29,0) | S29: =IF(R29>=0.25,"◎ 優良",IF(R29>=0.15,"○ 良好",IF(R29>=0.05,"△ 要注意","× 赤字"))) | T29: =IF(H28<>0,H29/H28-1,"")
A30: C002 | B30: 都営地下鉄案件 | C30: 2025-02 | D30: =IFERROR(VLOOKUP(C30,▼売上原票!$A:$P,3,0)*VLOOKUP("612-1",▼マッピング!$A:$G,5,0)/100,0) | E30: =IFERROR(VLOOKUP(C30,▼売上原票!$A:$P,4,0)*VLOOKUP("612-2",▼マッピング!$A:$G,5,0)/100,0) | F30: =IFERROR(VLOOKUP(C30,▼売上原票!$A:$P,10,0)*VLOOKUP("615-1",▼マッピング!$A:$G,5,0)/100,0) | G30: =IFERROR(VLOOKUP(C30,▼売上原票!$A:$P,5,0)*VLOOKUP("613-1",▼マッピング!$A:$G,5,0)/100,0)+IFERROR(VLOOKUP(C30,▼売上原票!$A:$P,6,0)*VLOOKUP("613-2",▼マッピング!$A:$G,5,0)/100,0)+IFERROR(VLOOKUP(C30,▼売上原票!$A:$P,7,0)*VLOOKUP("614-1",▼マッピング!$A:$G,5,0)/100,0)+IFERROR(VLOOKUP(C30,▼売上原票!$A:$P,8,0)*VLOOKUP("614-2",▼マッピング!$A:$G,5,0)/100,0)+IFERROR(VLOOKUP(C30,▼売上原票!$A:$P,9,0)*VLOOKUP("614-3",▼マッピング!$A:$G,5,0)/100,0)+IFERROR(VLOOKUP(C30,▼売上原票!$A:$P,11,0)*VLOOKUP("615-2",▼マッピング!$A:$G,5,0)/100,0)+IFERROR(VLOOKUP(C30,▼売上原票!$A:$P,12,0)*VLOOKUP("615-3",▼マッピング!$A:$G,5,0)/100,0)+IFERROR(VLOOKUP(C30,▼売上原票!$A:$P,13,0)*VLOOKUP("615-4",▼マッピング!$A:$G,5,0)/100,0) | H30: =D30+E30+F30+G30 | P30: =I30+J30+K30+L30+M30+N30+O30 | Q30: =H30-P30 | R30: =IF(H30<>0,Q30/H30,0) | S30: =IF(R30>=0.25,"◎ 優良",IF(R30>=0.15,"○ 良好",IF(R30>=0.05,"△ 要注意","× 赤字"))) | T30: =IF(H29<>0,H30/H29-1,"")
A31: C002 | B31: 都営地下鉄案件 | C31: 2025-03 | D31: =IFERROR(VLOOKUP(C31,▼売上原票!$A:$P,3,0)*VLOOKUP("612-1",▼マッピング!$A:$G,5,0)/100,0) | E31: =IFERROR(VLOOKUP(C31,▼売上原票!$A:$P,4,0)*VLOOKUP("612-2",▼マッピング!$A:$G,5,0)/100,0) | F31: =IFERROR(VLOOKUP(C31,▼売上原票!$A:$P,10,0)*VLOOKUP("615-1",▼マッピング!$A:$G,5,0)/100,0) | G31: =IFERROR(VLOOKUP(C31,▼売上原票!$A:$P,5,0)*VLOOKUP("613-1",▼マッピング!$A:$G,5,0)/100,0)+IFERROR(VLOOKUP(C31,▼売上原票!$A:$P,6,0)*VLOOKUP("613-2",▼マッピング!$A:$G,5,0)/100,0)+IFERROR(VLOOKUP(C31,▼売上原票!$A:$P,7,0)*VLOOKUP("614-1",▼マッピング!$A:$G,5,0)/100,0)+IFERROR(VLOOKUP(C31,▼売上原票!$A:$P,8,0)*VLOOKUP("614-2",▼マッピング!$A:$G,5,0)/100,0)+IFERROR(VLOOKUP(C31,▼売上原票!$A:$P,9,0)*VLOOKUP("614-3",▼マッピング!$A:$G,5,0)/100,0)+IFERROR(VLOOKUP(C31,▼売上原票!$A:$P,11,0)*VLOOKUP("615-2",▼マッピング!$A:$G,5,0)/100,0)+IFERROR(VLOOKUP(C31,▼売上原票!$A:$P,12,0)*VLOOKUP("615-3",▼マッピング!$A:$G,5,0)/100,0)+IFERROR(VLOOKUP(C31,▼売上原票!$A:$P,13,0)*VLOOKUP("615-4",▼マッピング!$A:$G,5,0)/100,0) | H31: =D31+E31+F31+G31 | P31: =I31+J31+K31+L31+M31+N31+O31 | Q31: =H31-P31 | R31: =IF(H31<>0,Q31/H31,0) | S31: =IF(R31>=0.25,"◎ 優良",IF(R31>=0.15,"○ 良好",IF(R31>=0.05,"△ 要注意","× 赤字"))) | T31: =IF(H30<>0,H31/H30-1,"")
A32: C002 | B32: 都営地下鉄案件 | C32: 2025-04 | D32: =IFERROR(VLOOKUP(C32,▼売上原票!$A:$P,3,0)*VLOOKUP("612-1",▼マッピング!$A:$G,5,0)/100,0) | E32: =IFERROR(VLOOKUP(C32,▼売上原票!$A:$P,4,0)*VLOOKUP("612-2",▼マッピング!$A:$G,5,0)/100,0) | F32: =IFERROR(VLOOKUP(C32,▼売上原票!$A:$P,10,0)*VLOOKUP("615-1",▼マッピング!$A:$G,5,0)/100,0) | G32: =IFERROR(VLOOKUP(C32,▼売上原票!$A:$P,5,0)*VLOOKUP("613-1",▼マッピング!$A:$G,5,0)/100,0)+IFERROR(VLOOKUP(C32,▼売上原票!$A:$P,6,0)*VLOOKUP("613-2",▼マッピング!$A:$G,5,0)/100,0)+IFERROR(VLOOKUP(C32,▼売上原票!$A:$P,7,0)*VLOOKUP("614-1",▼マッピング!$A:$G,5,0)/100,0)+IFERROR(VLOOKUP(C32,▼売上原票!$A:$P,8,0)*VLOOKUP("614-2",▼マッピング!$A:$G,5,0)/100,0)+IFERROR(VLOOKUP(C32,▼売上原票!$A:$P,9,0)*VLOOKUP("614-3",▼マッピング!$A:$G,5,0)/100,0)+IFERROR(VLOOKUP(C32,▼売上原票!$A:$P,11,0)*VLOOKUP("615-2",▼マッピング!$A:$G,5,0)/100,0)+IFERROR(VLOOKUP(C32,▼売上原票!$A:$P,12,0)*VLOOKUP("615-3",▼マッピング!$A:$G,5,0)/100,0)+IFERROR(VLOOKUP(C32,▼売上原票!$A:$P,13,0)*VLOOKUP("615-4",▼マッピング!$A:$G,5,0)/100,0) | H32: =D32+E32+F32+G32 | P32: =I32+J32+K32+L32+M32+N32+O32 | Q32: =H32-P32 | R32: =IF(H32<>0,Q32/H32,0) | S32: =IF(R32>=0.25,"◎ 優良",IF(R32>=0.15,"○ 良好",IF(R32>=0.05,"△ 要注意","× 赤字"))) | T32: =IF(H31<>0,H32/H31-1,"")
A33: C002 | B33: 都営地下鉄案件 | C33: 2025-05 | D33: =IFERROR(VLOOKUP(C33,▼売上原票!$A:$P,3,0)*VLOOKUP("612-1",▼マッピング!$A:$G,5,0)/100,0) | E33: =IFERROR(VLOOKUP(C33,▼売上原票!$A:$P,4,0)*VLOOKUP("612-2",▼マッピング!$A:$G,5,0)/100,0) | F33: =IFERROR(VLOOKUP(C33,▼売上原票!$A:$P,10,0)*VLOOKUP("615-1",▼マッピング!$A:$G,5,0)/100,0) | G33: =IFERROR(VLOOKUP(C33,▼売上原票!$A:$P,5,0)*VLOOKUP("613-1",▼マッピング!$A:$G,5,0)/100,0)+IFERROR(VLOOKUP(C33,▼売上原票!$A:$P,6,0)*VLOOKUP("613-2",▼マッピング!$A:$G,5,0)/100,0)+IFERROR(VLOOKUP(C33,▼売上原票!$A:$P,7,0)*VLOOKUP("614-1",▼マッピング!$A:$G,5,0)/100,0)+IFERROR(VLOOKUP(C33,▼売上原票!$A:$P,8,0)*VLOOKUP("614-2",▼マッピング!$A:$G,5,0)/100,0)+IFERROR(VLOOKUP(C33,▼売上原票!$A:$P,9,0)*VLOOKUP("614-3",▼マッピング!$A:$G,5,0)/100,0)+IFERROR(VLOOKUP(C33,▼売上原票!$A:$P,11,0)*VLOOKUP("615-2",▼マッピング!$A:$G,5,0)/100,0)+IFERROR(VLOOKUP(C33,▼売上原票!$A:$P,12,0)*VLOOKUP("615-3",▼マッピング!$A:$G,5,0)/100,0)+IFERROR(VLOOKUP(C33,▼売上原票!$A:$P,13,0)*VLOOKUP("615-4",▼マッピング!$A:$G,5,0)/100,0) | H33: =D33+E33+F33+G33 | P33: =I33+J33+K33+L33+M33+N33+O33 | Q33: =H33-P33 | R33: =IF(H33<>0,Q33/H33,0) | S33: =IF(R33>=0.25,"◎ 優良",IF(R33>=0.15,"○ 良好",IF(R33>=0.05,"△ 要注意","× 赤字"))) | T33: =IF(H32<>0,H33/H32-1,"")
A34: C002 | B34: 都営地下鉄案件 | C34: 2025-06 | D34: =IFERROR(VLOOKUP(C34,▼売上原票!$A:$P,3,0)*VLOOKUP("612-1",▼マッピング!$A:$G,5,0)/100,0) | E34: =IFERROR(VLOOKUP(C34,▼売上原票!$A:$P,4,0)*VLOOKUP("612-2",▼マッピング!$A:$G,5,0)/100,0) | F34: =IFERROR(VLOOKUP(C34,▼売上原票!$A:$P,10,0)*VLOOKUP("615-1",▼マッピング!$A:$G,5,0)/100,0) | G34: =IFERROR(VLOOKUP(C34,▼売上原票!$A:$P,5,0)*VLOOKUP("613-1",▼マッピング!$A:$G,5,0)/100,0)+IFERROR(VLOOKUP(C34,▼売上原票!$A:$P,6,0)*VLOOKUP("613-2",▼マッピング!$A:$G,5,0)/100,0)+IFERROR(VLOOKUP(C34,▼売上原票!$A:$P,7,0)*VLOOKUP("614-1",▼マッピング!$A:$G,5,0)/100,0)+IFERROR(VLOOKUP(C34,▼売上原票!$A:$P,8,0)*VLOOKUP("614-2",▼マッピング!$A:$G,5,0)/100,0)+IFERROR(VLOOKUP(C34,▼売上原票!$A:$P,9,0)*VLOOKUP("614-3",▼マッピング!$A:$G,5,0)/100,0)+IFERROR(VLOOKUP(C34,▼売上原票!$A:$P,11,0)*VLOOKUP("615-2",▼マッピング!$A:$G,5,0)/100,0)+IFERROR(VLOOKUP(C34,▼売上原票!$A:$P,12,0)*VLOOKUP("615-3",▼マッピング!$A:$G,5,0)/100,0)+IFERROR(VLOOKUP(C34,▼売上原票!$A:$P,13,0)*VLOOKUP("615-4",▼マッピング!$A:$G,5,0)/100,0) | H34: =D34+E34+F34+G34 | P34: =I34+J34+K34+L34+M34+N34+O34 | Q34: =H34-P34 | R34: =IF(H34<>0,Q34/H34,0) | S34: =IF(R34>=0.25,"◎ 優良",IF(R34>=0.15,"○ 良好",IF(R34>=0.05,"△ 要注意","× 赤字"))) | T34: =IF(H33<>0,H34/H33-1,"")
A35: C002 | B35: 都営地下鉄案件 | C35: 2025-07 | D35: =IFERROR(VLOOKUP(C35,▼売上原票!$A:$P,3,0)*VLOOKUP("612-1",▼マッピング!$A:$G,5,0)/100,0) | E35: =IFERROR(VLOOKUP(C35,▼売上原票!$A:$P,4,0)*VLOOKUP("612-2",▼マッピング!$A:$G,5,0)/100,0) | F35: =IFERROR(VLOOKUP(C35,▼売上原票!$A:$P,10,0)*VLOOKUP("615-1",▼マッピング!$A:$G,5,0)/100,0) | G35: =IFERROR(VLOOKUP(C35,▼売上原票!$A:$P,5,0)*VLOOKUP("613-1",▼マッピング!$A:$G,5,0)/100,0)+IFERROR(VLOOKUP(C35,▼売上原票!$A:$P,6,0)*VLOOKUP("613-2",▼マッピング!$A:$G,5,0)/100,0)+IFERROR(VLOOKUP(C35,▼売上原票!$A:$P,7,0)*VLOOKUP("614-1",▼マッピング!$A:$G,5,0)/100,0)+IFERROR(VLOOKUP(C35,▼売上原票!$A:$P,8,0)*VLOOKUP("614-2",▼マッピング!$A:$G,5,0)/100,0)+IFERROR(VLOOKUP(C35,▼売上原票!$A:$P,9,0)*VLOOKUP("614-3",▼マッピング!$A:$G,5,0)/100,0)+IFERROR(VLOOKUP(C35,▼売上原票!$A:$P,11,0)*VLOOKUP("615-2",▼マッピング!$A:$G,5,0)/100,0)+IFERROR(VLOOKUP(C35,▼売上原票!$A:$P,12,0)*VLOOKUP("615-3",▼マッピング!$A:$G,5,0)/100,0)+IFERROR(VLOOKUP(C35,▼売上原票!$A:$P,13,0)*VLOOKUP("615-4",▼マッピング!$A:$G,5,0)/100,0) | H35: =D35+E35+F35+G35 | P35: =I35+J35+K35+L35+M35+N35+O35 | Q35: =H35-P35 | R35: =IF(H35<>0,Q35/H35,0) | S35: =IF(R35>=0.25,"◎ 優良",IF(R35>=0.15,"○ 良好",IF(R35>=0.05,"△ 要注意","× 赤字"))) | T35: =IF(H34<>0,H35/H34-1,"")
... A39: C002 | B39: 都営地下鉄案件 | C39: 2025-11 | D39: =IFERROR(VLOOKUP(C39,▼売上原票!$A:$P,3,0)*VLOOKUP("612-1",▼マッピング!$A:$G,5,0)/100,0) | E39: =IFERROR(VLOOKUP(C39,▼売上原票!$A:$P,4,0)*VLOOKUP("612-2",▼マッピング!$A:$G,5,0)/100,0) | F39: =IFERROR(VLOOKUP(C39,▼売上原票!$A:$P,10,0)*VLOOKUP("615-1",▼マッピング!$A:$G,5,0)/100,0) | G39: =IFERROR(VLOOKUP(C39,▼売上原票!$A:$P,5,0)*VLOOKUP("613-1",▼マッピング!$A:$G,5,0)/100,0)+IFERROR(VLOOKUP(C39,▼売上原票!$A:$P,6,0)*VLOOKUP("613-2",▼マッピング!$A:$G,5,0)/100,0)+IFERROR(VLOOKUP(C39,▼売上原票!$A:$P,7,0)*VLOOKUP("614-1",▼マッピング!$A:$G,5,0)/100,0)+IFERROR(VLOOKUP(C39,▼売上原票!$A:$P,8,0)*VLOOKUP("614-2",▼マッピング!$A:$G,5,0)/100,0)+IFERROR(VLOOKUP(C39,▼売上原票!$A:$P,9,0)*VLOOKUP("614-3",▼マッピング!$A:$G,5,0)/100,0)+IFERROR(VLOOKUP(C39,▼売上原票!$A:$P,11,0)*VLOOKUP("615-2",▼マッピング!$A:$G,5,0)/100,0)+IFERROR(VLOOKUP(C39,▼売上原票!$A:$P,12,0)*VLOOKUP("615-3",▼マッピング!$A:$G,5,0)/100,0)+IFERROR(VLOOKUP(C39,▼売上原票!$A:$P,13,0)*VLOOKUP("615-4",▼マッピング!$A:$G,5,0)/100,0) | H39: =D39+E39+F39+G39 | P39: =I39+J39+K39+L39+M39+N39+O39 | Q39: =H39-P39 | R39: =IF(H39<>0,Q39/H39,0) | S39: =IF(R39>=0.25,"◎ 優良",IF(R39>=0.15,"○ 良好",IF(R39>=0.05,"△ 要注意","× 赤字"))) | T39: =IF(H38<>0,H39/H38-1,"")
A41: C003 | B41: 一般事業者案件 | C41: 2024-07 | D41: =IFERROR(VLOOKUP(C41,▼売上原票!$A:$P,3,0)*VLOOKUP("612-1",▼マッピング!$A:$G,6,0)/100,0) | E41: =IFERROR(VLOOKUP(C41,▼売上原票!$A:$P,4,0)*VLOOKUP("612-2",▼マッピング!$A:$G,6,0)/100,0) | F41: =IFERROR(VLOOKUP(C41,▼売上原票!$A:$P,10,0)*VLOOKUP("615-1",▼マッピング!$A:$G,6,0)/100,0) | G41: =IFERROR(VLOOKUP(C41,▼売上原票!$A:$P,5,0)*VLOOKUP("613-1",▼マッピング!$A:$G,6,0)/100,0)+IFERROR(VLOOKUP(C41,▼売上原票!$A:$P,6,0)*VLOOKUP("613-2",▼マッピング!$A:$G,6,0)/100,0)+IFERROR(VLOOKUP(C41,▼売上原票!$A:$P,7,0)*VLOOKUP("614-1",▼マッピング!$A:$G,6,0)/100,0)+IFERROR(VLOOKUP(C41,▼売上原票!$A:$P,8,0)*VLOOKUP("614-2",▼マッピング!$A:$G,6,0)/100,0)+IFERROR(VLOOKUP(C41,▼売上原票!$A:$P,9,0)*VLOOKUP("614-3",▼マッピング!$A:$G,6,0)/100,0)+IFERROR(VLOOKUP(C41,▼売上原票!$A:$P,11,0)*VLOOKUP("615-2",▼マッピング!$A:$G,6,0)/100,0)+IFERROR(VLOOKUP(C41,▼売上原票!$A:$P,12,0)*VLOOKUP("615-3",▼マッピング!$A:$G,6,0)/100,0)+IFERROR(VLOOKUP(C41,▼売上原票!$A:$P,13,0)*VLOOKUP("615-4",▼マッピング!$A:$G,6,0)/100,0) | H41: =D41+E41+F41+G41 | P41: =I41+J41+K41+L41+M41+N41+O41 | Q41: =H41-P41 | R41: =IF(H41<>0,Q41/H41,0) | S41: =IF(R41>=0.25,"◎ 優良",IF(R41>=0.15,"○ 良好",IF(R41>=0.05,"△ 要注意","× 赤字"))) | T41: —
A42: C003 | B42: 一般事業者案件 | C42: 2024-08 | D42: =IFERROR(VLOOKUP(C42,▼売上原票!$A:$P,3,0)*VLOOKUP("612-1",▼マッピング!$A:$G,6,0)/100,0) | E42: =IFERROR(VLOOKUP(C42,▼売上原票!$A:$P,4,0)*VLOOKUP("612-2",▼マッピング!$A:$G,6,0)/100,0) | F42: =IFERROR(VLOOKUP(C42,▼売上原票!$A:$P,10,0)*VLOOKUP("615-1",▼マッピング!$A:$G,6,0)/100,0) | G42: =IFERROR(VLOOKUP(C42,▼売上原票!$A:$P,5,0)*VLOOKUP("613-1",▼マッピング!$A:$G,6,0)/100,0)+IFERROR(VLOOKUP(C42,▼売上原票!$A:$P,6,0)*VLOOKUP("613-2",▼マッピング!$A:$G,6,0)/100,0)+IFERROR(VLOOKUP(C42,▼売上原票!$A:$P,7,0)*VLOOKUP("614-1",▼マッピング!$A:$G,6,0)/100,0)+IFERROR(VLOOKUP(C42,▼売上原票!$A:$P,8,0)*VLOOKUP("614-2",▼マッピング!$A:$G,6,0)/100,0)+IFERROR(VLOOKUP(C42,▼売上原票!$A:$P,9,0)*VLOOKUP("614-3",▼マッピング!$A:$G,6,0)/100,0)+IFERROR(VLOOKUP(C42,▼売上原票!$A:$P,11,0)*VLOOKUP("615-2",▼マッピング!$A:$G,6,0)/100,0)+IFERROR(VLOOKUP(C42,▼売上原票!$A:$P,12,0)*VLOOKUP("615-3",▼マッピング!$A:$G,6,0)/100,0)+IFERROR(VLOOKUP(C42,▼売上原票!$A:$P,13,0)*VLOOKUP("615-4",▼マッピング!$A:$G,6,0)/100,0) | H42: =D42+E42+F42+G42 | P42: =I42+J42+K42+L42+M42+N42+O42 | Q42: =H42-P42 | R42: =IF(H42<>0,Q42/H42,0) | S42: =IF(R42>=0.25,"◎ 優良",IF(R42>=0.15,"○ 良好",IF(R42>=0.05,"△ 要注意","× 赤字"))) | T42: =IF(H41<>0,H42/H41-1,"")
A43: C003 | B43: 一般事業者案件 | C43: 2024-09 | D43: =IFERROR(VLOOKUP(C43,▼売上原票!$A:$P,3,0)*VLOOKUP("612-1",▼マッピング!$A:$G,6,0)/100,0) | E43: =IFERROR(VLOOKUP(C43,▼売上原票!$A:$P,4,0)*VLOOKUP("612-2",▼マッピング!$A:$G,6,0)/100,0) | F43: =IFERROR(VLOOKUP(C43,▼売上原票!$A:$P,10,0)*VLOOKUP("615-1",▼マッピング!$A:$G,6,0)/100,0) | G43: =IFERROR(VLOOKUP(C43,▼売上原票!$A:$P,5,0)*VLOOKUP("613-1",▼マッピング!$A:$G,6,0)/100,0)+IFERROR(VLOOKUP(C43,▼売上原票!$A:$P,6,0)*VLOOKUP("613-2",▼マッピング!$A:$G,6,0)/100,0)+IFERROR(VLOOKUP(C43,▼売上原票!$A:$P,7,0)*VLOOKUP("614-1",▼マッピング!$A:$G,6,0)/100,0)+IFERROR(VLOOKUP(C43,▼売上原票!$A:$P,8,0)*VLOOKUP("614-2",▼マッピング!$A:$G,6,0)/100,0)+IFERROR(VLOOKUP(C43,▼売上原票!$A:$P,9,0)*VLOOKUP("614-3",▼マッピング!$A:$G,6,0)/100,0)+IFERROR(VLOOKUP(C43,▼売上原票!$A:$P,11,0)*VLOOKUP("615-2",▼マッピング!$A:$G,6,0)/100,0)+IFERROR(VLOOKUP(C43,▼売上原票!$A:$P,12,0)*VLOOKUP("615-3",▼マッピング!$A:$G,6,0)/100,0)+IFERROR(VLOOKUP(C43,▼売上原票!$A:$P,13,0)*VLOOKUP("615-4",▼マッピング!$A:$G,6,0)/100,0) | H43: =D43+E43+F43+G43 | P43: =I43+J43+K43+L43+M43+N43+O43 | Q43: =H43-P43 | R43: =IF(H43<>0,Q43/H43,0) | S43: =IF(R43>=0.25,"◎ 優良",IF(R43>=0.15,"○ 良好",IF(R43>=0.05,"△ 要注意","× 赤字"))) | T43: =IF(H42<>0,H43/H42-1,"")
A44: C003 | B44: 一般事業者案件 | C44: 2024-10 | D44: =IFERROR(VLOOKUP(C44,▼売上原票!$A:$P,3,0)*VLOOKUP("612-1",▼マッピング!$A:$G,6,0)/100,0) | E44: =IFERROR(VLOOKUP(C44,▼売上原票!$A:$P,4,0)*VLOOKUP("612-2",▼マッピング!$A:$G,6,0)/100,0) | F44: =IFERROR(VLOOKUP(C44,▼売上原票!$A:$P,10,0)*VLOOKUP("615-1",▼マッピング!$A:$G,6,0)/100,0) | G44: =IFERROR(VLOOKUP(C44,▼売上原票!$A:$P,5,0)*VLOOKUP("613-1",▼マッピング!$A:$G,6,0)/100,0)+IFERROR(VLOOKUP(C44,▼売上原票!$A:$P,6,0)*VLOOKUP("613-2",▼マッピング!$A:$G,6,0)/100,0)+IFERROR(VLOOKUP(C44,▼売上原票!$A:$P,7,0)*VLOOKUP("614-1",▼マッピング!$A:$G,6,0)/100,0)+IFERROR(VLOOKUP(C44,▼売上原票!$A:$P,8,0)*VLOOKUP("614-2",▼マッピング!$A:$G,6,0)/100,0)+IFERROR(VLOOKUP(C44,▼売上原票!$A:$P,9,0)*VLOOKUP("614-3",▼マッピング!$A:$G,6,0)/100,0)+IFERROR(VLOOKUP(C44,▼売上原票!$A:$P,11,0)*VLOOKUP("615-2",▼マッピング!$A:$G,6,0)/100,0)+IFERROR(VLOOKUP(C44,▼売上原票!$A:$P,12,0)*VLOOKUP("615-3",▼マッピング!$A:$G,6,0)/100,0)+IFERROR(VLOOKUP(C44,▼売上原票!$A:$P,13,0)*VLOOKUP("615-4",▼マッピング!$A:$G,6,0)/100,0) | H44: =D44+E44+F44+G44 | P44: =I44+J44+K44+L44+M44+N44+O44 | Q44: =H44-P44 | R44: =IF(H44<>0,Q44/H44,0) | S44: =IF(R44>=0.25,"◎ 優良",IF(R44>=0.15,"○ 良好",IF(R44>=0.05,"△ 要注意","× 赤字"))) | T44: =IF(H43<>0,H44/H43-1,"")
A45: C003 | B45: 一般事業者案件 | C45: 2024-11 | D45: =IFERROR(VLOOKUP(C45,▼売上原票!$A:$P,3,0)*VLOOKUP("612-1",▼マッピング!$A:$G,6,0)/100,0) | E45: =IFERROR(VLOOKUP(C45,▼売上原票!$A:$P,4,0)*VLOOKUP("612-2",▼マッピング!$A:$G,6,0)/100,0) | F45: =IFERROR(VLOOKUP(C45,▼売上原票!$A:$P,10,0)*VLOOKUP("615-1",▼マッピング!$A:$G,6,0)/100,0) | G45: =IFERROR(VLOOKUP(C45,▼売上原票!$A:$P,5,0)*VLOOKUP("613-1",▼マッピング!$A:$G,6,0)/100,0)+IFERROR(VLOOKUP(C45,▼売上原票!$A:$P,6,0)*VLOOKUP("613-2",▼マッピング!$A:$G,6,0)/100,0)+IFERROR(VLOOKUP(C45,▼売上原票!$A:$P,7,0)*VLOOKUP("614-1",▼マッピング!$A:$G,6,0)/100,0)+IFERROR(VLOOKUP(C45,▼売上原票!$A:$P,8,0)*VLOOKUP("614-2",▼マッピング!$A:$G,6,0)/100,0)+IFERROR(VLOOKUP(C45,▼売上原票!$A:$P,9,0)*VLOOKUP("614-3",▼マッピング!$A:$G,6,0)/100,0)+IFERROR(VLOOKUP(C45,▼売上原票!$A:$P,11,0)*VLOOKUP("615-2",▼マッピング!$A:$G,6,0)/100,0)+IFERROR(VLOOKUP(C45,▼売上原票!$A:$P,12,0)*VLOOKUP("615-3",▼マッピング!$A:$G,6,0)/100,0)+IFERROR(VLOOKUP(C45,▼売上原票!$A:$P,13,0)*VLOOKUP("615-4",▼マッピング!$A:$G,6,0)/100,0) | H45: =D45+E45+F45+G45 | P45: =I45+J45+K45+L45+M45+N45+O45 | Q45: =H45-P45 | R45: =IF(H45<>0,Q45/H45,0) | S45: =IF(R45>=0.25,"◎ 優良",IF(R45>=0.15,"○ 良好",IF(R45>=0.05,"△ 要注意","× 赤字"))) | T45: =IF(H44<>0,H45/H44-1,"")
A46: C003 | B46: 一般事業者案件 | C46: 2024-12 | D46: =IFERROR(VLOOKUP(C46,▼売上原票!$A:$P,3,0)*VLOOKUP("612-1",▼マッピング!$A:$G,6,0)/100,0) | E46: =IFERROR(VLOOKUP(C46,▼売上原票!$A:$P,4,0)*VLOOKUP("612-2",▼マッピング!$A:$G,6,0)/100,0) | F46: =IFERROR(VLOOKUP(C46,▼売上原票!$A:$P,10,0)*VLOOKUP("615-1",▼マッピング!$A:$G,6,0)/100,0) | G46: =IFERROR(VLOOKUP(C46,▼売上原票!$A:$P,5,0)*VLOOKUP("613-1",▼マッピング!$A:$G,6,0)/100,0)+IFERROR(VLOOKUP(C46,▼売上原票!$A:$P,6,0)*VLOOKUP("613-2",▼マッピング!$A:$G,6,0)/100,0)+IFERROR(VLOOKUP(C46,▼売上原票!$A:$P,7,0)*VLOOKUP("614-1",▼マッピング!$A:$G,6,0)/100,0)+IFERROR(VLOOKUP(C46,▼売上原票!$A:$P,8,0)*VLOOKUP("614-2",▼マッピング!$A:$G,6,0)/100,0)+IFERROR(VLOOKUP(C46,▼売上原票!$A:$P,9,0)*VLOOKUP("614-3",▼マッピング!$A:$G,6,0)/100,0)+IFERROR(VLOOKUP(C46,▼売上原票!$A:$P,11,0)*VLOOKUP("615-2",▼マッピング!$A:$G,6,0)/100,0)+IFERROR(VLOOKUP(C46,▼売上原票!$A:$P,12,0)*VLOOKUP("615-3",▼マッピング!$A:$G,6,0)/100,0)+IFERROR(VLOOKUP(C46,▼売上原票!$A:$P,13,0)*VLOOKUP("615-4",▼マッピング!$A:$G,6,0)/100,0) | H46: =D46+E46+F46+G46 | P46: =I46+J46+K46+L46+M46+N46+O46 | Q46: =H46-P46 | R46: =IF(H46<>0,Q46/H46,0) | S46: =IF(R46>=0.25,"◎ 優良",IF(R46>=0.15,"○ 良好",IF(R46>=0.05,"△ 要注意","× 赤字"))) | T46: =IF(H45<>0,H46/H45-1,"")
A47: C003 | B47: 一般事業者案件 | C47: 2025-01 | D47: =IFERROR(VLOOKUP(C47,▼売上原票!$A:$P,3,0)*VLOOKUP("612-1",▼マッピング!$A:$G,6,0)/100,0) | E47: =IFERROR(VLOOKUP(C47,▼売上原票!$A:$P,4,0)*VLOOKUP("612-2",▼マッピング!$A:$G,6,0)/100,0) | F47: =IFERROR(VLOOKUP(C47,▼売上原票!$A:$P,10,0)*VLOOKUP("615-1",▼マッピング!$A:$G,6,0)/100,0) | G47: =IFERROR(VLOOKUP(C47,▼売上原票!$A:$P,5,0)*VLOOKUP("613-1",▼マッピング!$A:$G,6,0)/100,0)+IFERROR(VLOOKUP(C47,▼売上原票!$A:$P,6,0)*VLOOKUP("613-2",▼マッピング!$A:$G,6,0)/100,0)+IFERROR(VLOOKUP(C47,▼売上原票!$A:$P,7,0)*VLOOKUP("614-1",▼マッピング!$A:$G,6,0)/100,0)+IFERROR(VLOOKUP(C47,▼売上原票!$A:$P,8,0)*VLOOKUP("614-2",▼マッピング!$A:$G,6,0)/100,0)+IFERROR(VLOOKUP(C47,▼売上原票!$A:$P,9,0)*VLOOKUP("614-3",▼マッピング!$A:$G,6,0)/100,0)+IFERROR(VLOOKUP(C47,▼売上原票!$A:$P,11,0)*VLOOKUP("615-2",▼マッピング!$A:$G,6,0)/100,0)+IFERROR(VLOOKUP(C47,▼売上原票!$A:$P,12,0)*VLOOKUP("615-3",▼マッピング!$A:$G,6,0)/100,0)+IFERROR(VLOOKUP(C47,▼売上原票!$A:$P,13,0)*VLOOKUP("615-4",▼マッピング!$A:$G,6,0)/100,0) | H47: =D47+E47+F47+G47 | P47: =I47+J47+K47+L47+M47+N47+O47 | Q47: =H47-P47 | R47: =IF(H47<>0,Q47/H47,0) | S47: =IF(R47>=0.25,"◎ 優良",IF(R47>=0.15,"○ 良好",IF(R47>=0.05,"△ 要注意","× 赤字"))) | T47: =IF(H46<>0,H47/H46-1,"")
A48: C003 | B48: 一般事業者案件 | C48: 2025-02 | D48: =IFERROR(VLOOKUP(C48,▼売上原票!$A:$P,3,0)*VLOOKUP("612-1",▼マッピング!$A:$G,6,0)/100,0) | E48: =IFERROR(VLOOKUP(C48,▼売上原票!$A:$P,4,0)*VLOOKUP("612-2",▼マッピング!$A:$G,6,0)/100,0) | F48: =IFERROR(VLOOKUP(C48,▼売上原票!$A:$P,10,0)*VLOOKUP("615-1",▼マッピング!$A:$G,6,0)/100,0) | G48: =IFERROR(VLOOKUP(C48,▼売上原票!$A:$P,5,0)*VLOOKUP("613-1",▼マッピング!$A:$G,6,0)/100,0)+IFERROR(VLOOKUP(C48,▼売上原票!$A:$P,6,0)*VLOOKUP("613-2",▼マッピング!$A:$G,6,0)/100,0)+IFERROR(VLOOKUP(C48,▼売上原票!$A:$P,7,0)*VLOOKUP("614-1",▼マッピング!$A:$G,6,0)/100,0)+IFERROR(VLOOKUP(C48,▼売上原票!$A:$P,8,0)*VLOOKUP("614-2",▼マッピング!$A:$G,6,0)/100,0)+IFERROR(VLOOKUP(C48,▼売上原票!$A:$P,9,0)*VLOOKUP("614-3",▼マッピング!$A:$G,6,0)/100,0)+IFERROR(VLOOKUP(C48,▼売上原票!$A:$P,11,0)*VLOOKUP("615-2",▼マッピング!$A:$G,6,0)/100,0)+IFERROR(VLOOKUP(C48,▼売上原票!$A:$P,12,0)*VLOOKUP("615-3",▼マッピング!$A:$G,6,0)/100,0)+IFERROR(VLOOKUP(C48,▼売上原票!$A:$P,13,0)*VLOOKUP("615-4",▼マッピング!$A:$G,6,0)/100,0) | H48: =D48+E48+F48+G48 | P48: =I48+J48+K48+L48+M48+N48+O48 | Q48: =H48-P48 | R48: =IF(H48<>0,Q48/H48,0) | S48: =IF(R48>=0.25,"◎ 優良",IF(R48>=0.15,"○ 良好",IF(R48>=0.05,"△ 要注意","× 赤字"))) | T48: =IF(H47<>0,H48/H47-1,"")
A49: C003 | B49: 一般事業者案件 | C49: 2025-03 | D49: =IFERROR(VLOOKUP(C49,▼売上原票!$A:$P,3,0)*VLOOKUP("612-1",▼マッピング!$A:$G,6,0)/100,0) | E49: =IFERROR(VLOOKUP(C49,▼売上原票!$A:$P,4,0)*VLOOKUP("612-2",▼マッピング!$A:$G,6,0)/100,0) | F49: =IFERROR(VLOOKUP(C49,▼売上原票!$A:$P,10,0)*VLOOKUP("615-1",▼マッピング!$A:$G,6,0)/100,0) | G49: =IFERROR(VLOOKUP(C49,▼売上原票!$A:$P,5,0)*VLOOKUP("613-1",▼マッピング!$A:$G,6,0)/100,0)+IFERROR(VLOOKUP(C49,▼売上原票!$A:$P,6,0)*VLOOKUP("613-2",▼マッピング!$A:$G,6,0)/100,0)+IFERROR(VLOOKUP(C49,▼売上原票!$A:$P,7,0)*VLOOKUP("614-1",▼マッピング!$A:$G,6,0)/100,0)+IFERROR(VLOOKUP(C49,▼売上原票!$A:$P,8,0)*VLOOKUP("614-2",▼マッピング!$A:$G,6,0)/100,0)+IFERROR(VLOOKUP(C49,▼売上原票!$A:$P,9,0)*VLOOKUP("614-3",▼マッピング!$A:$G,6,0)/100,0)+IFERROR(VLOOKUP(C49,▼売上原票!$A:$P,11,0)*VLOOKUP("615-2",▼マッピング!$A:$G,6,0)/100,0)+IFERROR(VLOOKUP(C49,▼売上原票!$A:$P,12,0)*VLOOKUP("615-3",▼マッピング!$A:$G,6,0)/100,0)+IFERROR(VLOOKUP(C49,▼売上原票!$A:$P,13,0)*VLOOKUP("615-4",▼マッピング!$A:$G,6,0)/100,0) | H49: =D49+E49+F49+G49 | P49: =I49+J49+K49+L49+M49+N49+O49 | Q49: =H49-P49 | R49: =IF(H49<>0,Q49/H49,0) | S49: =IF(R49>=0.25,"◎ 優良",IF(R49>=0.15,"○ 良好",IF(R49>=0.05,"△ 要注意","× 赤字"))) | T49: =IF(H48<>0,H49/H48-1,"")
A50: C003 | B50: 一般事業者案件 | C50: 2025-04 | D50: =IFERROR(VLOOKUP(C50,▼売上原票!$A:$P,3,0)*VLOOKUP("612-1",▼マッピング!$A:$G,6,0)/100,0) | E50: =IFERROR(VLOOKUP(C50,▼売上原票!$A:$P,4,0)*VLOOKUP("612-2",▼マッピング!$A:$G,6,0)/100,0) | F50: =IFERROR(VLOOKUP(C50,▼売上原票!$A:$P,10,0)*VLOOKUP("615-1",▼マッピング!$A:$G,6,0)/100,0) | G50: =IFERROR(VLOOKUP(C50,▼売上原票!$A:$P,5,0)*VLOOKUP("613-1",▼マッピング!$A:$G,6,0)/100,0)+IFERROR(VLOOKUP(C50,▼売上原票!$A:$P,6,0)*VLOOKUP("613-2",▼マッピング!$A:$G,6,0)/100,0)+IFERROR(VLOOKUP(C50,▼売上原票!$A:$P,7,0)*VLOOKUP("614-1",▼マッピング!$A:$G,6,0)/100,0)+IFERROR(VLOOKUP(C50,▼売上原票!$A:$P,8,0)*VLOOKUP("614-2",▼マッピング!$A:$G,6,0)/100,0)+IFERROR(VLOOKUP(C50,▼売上原票!$A:$P,9,0)*VLOOKUP("614-3",▼マッピング!$A:$G,6,0)/100,0)+IFERROR(VLOOKUP(C50,▼売上原票!$A:$P,11,0)*VLOOKUP("615-2",▼マッピング!$A:$G,6,0)/100,0)+IFERROR(VLOOKUP(C50,▼売上原票!$A:$P,12,0)*VLOOKUP("615-3",▼マッピング!$A:$G,6,0)/100,0)+IFERROR(VLOOKUP(C50,▼売上原票!$A:$P,13,0)*VLOOKUP("615-4",▼マッピング!$A:$G,6,0)/100,0) | H50: =D50+E50+F50+G50 | P50: =I50+J50+K50+L50+M50+N50+O50 | Q50: =H50-P50 | R50: =IF(H50<>0,Q50/H50,0) | S50: =IF(R50>=0.25,"◎ 優良",IF(R50>=0.15,"○ 良好",IF(R50>=0.05,"△ 要注意","× 赤字"))) | T50: =IF(H49<>0,H50/H49-1,"")
A51: C003 | B51: 一般事業者案件 | C51: 2025-05 | D51: =IFERROR(VLOOKUP(C51,▼売上原票!$A:$P,3,0)*VLOOKUP("612-1",▼マッピング!$A:$G,6,0)/100,0) | E51: =IFERROR(VLOOKUP(C51,▼売上原票!$A:$P,4,0)*VLOOKUP("612-2",▼マッピング!$A:$G,6,0)/100,0) | F51: =IFERROR(VLOOKUP(C51,▼売上原票!$A:$P,10,0)*VLOOKUP("615-1",▼マッピング!$A:$G,6,0)/100,0) | G51: =IFERROR(VLOOKUP(C51,▼売上原票!$A:$P,5,0)*VLOOKUP("613-1",▼マッピング!$A:$G,6,0)/100,0)+IFERROR(VLOOKUP(C51,▼売上原票!$A:$P,6,0)*VLOOKUP("613-2",▼マッピング!$A:$G,6,0)/100,0)+IFERROR(VLOOKUP(C51,▼売上原票!$A:$P,7,0)*VLOOKUP("614-1",▼マッピング!$A:$G,6,0)/100,0)+IFERROR(VLOOKUP(C51,▼売上原票!$A:$P,8,0)*VLOOKUP("614-2",▼マッピング!$A:$G,6,0)/100,0)+IFERROR(VLOOKUP(C51,▼売上原票!$A:$P,9,0)*VLOOKUP("614-3",▼マッピング!$A:$G,6,0)/100,0)+IFERROR(VLOOKUP(C51,▼売上原票!$A:$P,11,0)*VLOOKUP("615-2",▼マッピング!$A:$G,6,0)/100,0)+IFERROR(VLOOKUP(C51,▼売上原票!$A:$P,12,0)*VLOOKUP("615-3",▼マッピング!$A:$G,6,0)/100,0)+IFERROR(VLOOKUP(C51,▼売上原票!$A:$P,13,0)*VLOOKUP("615-4",▼マッピング!$A:$G,6,0)/100,0) | H51: =D51+E51+F51+G51 | P51: =I51+J51+K51+L51+M51+N51+O51 | Q51: =H51-P51 | R51: =IF(H51<>0,Q51/H51,0) | S51: =IF(R51>=0.25,"◎ 優良",IF(R51>=0.15,"○ 良好",IF(R51>=0.05,"△ 要注意","× 赤字"))) | T51: =IF(H50<>0,H51/H50-1,"")
A52: C003 | B52: 一般事業者案件 | C52: 2025-06 | D52: =IFERROR(VLOOKUP(C52,▼売上原票!$A:$P,3,0)*VLOOKUP("612-1",▼マッピング!$A:$G,6,0)/100,0) | E52: =IFERROR(VLOOKUP(C52,▼売上原票!$A:$P,4,0)*VLOOKUP("612-2",▼マッピング!$A:$G,6,0)/100,0) | F52: =IFERROR(VLOOKUP(C52,▼売上原票!$A:$P,10,0)*VLOOKUP("615-1",▼マッピング!$A:$G,6,0)/100,0) | G52: =IFERROR(VLOOKUP(C52,▼売上原票!$A:$P,5,0)*VLOOKUP("613-1",▼マッピング!$A:$G,6,0)/100,0)+IFERROR(VLOOKUP(C52,▼売上原票!$A:$P,6,0)*VLOOKUP("613-2",▼マッピング!$A:$G,6,0)/100,0)+IFERROR(VLOOKUP(C52,▼売上原票!$A:$P,7,0)*VLOOKUP("614-1",▼マッピング!$A:$G,6,0)/100,0)+IFERROR(VLOOKUP(C52,▼売上原票!$A:$P,8,0)*VLOOKUP("614-2",▼マッピング!$A:$G,6,0)/100,0)+IFERROR(VLOOKUP(C52,▼売上原票!$A:$P,9,0)*VLOOKUP("614-3",▼マッピング!$A:$G,6,0)/100,0)+IFERROR(VLOOKUP(C52,▼売上原票!$A:$P,11,0)*VLOOKUP("615-2",▼マッピング!$A:$G,6,0)/100,0)+IFERROR(VLOOKUP(C52,▼売上原票!$A:$P,12,0)*VLOOKUP("615-3",▼マッピング!$A:$G,6,0)/100,0)+IFERROR(VLOOKUP(C52,▼売上原票!$A:$P,13,0)*VLOOKUP("615-4",▼マッピング!$A:$G,6,0)/100,0) | H52: =D52+E52+F52+G52 | P52: =I52+J52+K52+L52+M52+N52+O52 | Q52: =H52-P52 | R52: =IF(H52<>0,Q52/H52,0) | S52: =IF(R52>=0.25,"◎ 優良",IF(R52>=0.15,"○ 良好",IF(R52>=0.05,"△ 要注意","× 赤字"))) | T52: =IF(H51<>0,H52/H51-1,"")
A53: C003 | B53: 一般事業者案件 | C53: 2025-07 | D53: =IFERROR(VLOOKUP(C53,▼売上原票!$A:$P,3,0)*VLOOKUP("612-1",▼マッピング!$A:$G,6,0)/100,0) | E53: =IFERROR(VLOOKUP(C53,▼売上原票!$A:$P,4,0)*VLOOKUP("612-2",▼マッピング!$A:$G,6,0)/100,0) | F53: =IFERROR(VLOOKUP(C53,▼売上原票!$A:$P,10,0)*VLOOKUP("615-1",▼マッピング!$A:$G,6,0)/100,0) | G53: =IFERROR(VLOOKUP(C53,▼売上原票!$A:$P,5,0)*VLOOKUP("613-1",▼マッピング!$A:$G,6,0)/100,0)+IFERROR(VLOOKUP(C53,▼売上原票!$A:$P,6,0)*VLOOKUP("613-2",▼マッピング!$A:$G,6,0)/100,0)+IFERROR(VLOOKUP(C53,▼売上原票!$A:$P,7,0)*VLOOKUP("614-1",▼マッピング!$A:$G,6,0)/100,0)+IFERROR(VLOOKUP(C53,▼売上原票!$A:$P,8,0)*VLOOKUP("614-2",▼マッピング!$A:$G,6,0)/100,0)+IFERROR(VLOOKUP(C53,▼売上原票!$A:$P,9,0)*VLOOKUP("614-3",▼マッピング!$A:$G,6,0)/100,0)+IFERROR(VLOOKUP(C53,▼売上原票!$A:$P,11,0)*VLOOKUP("615-2",▼マッピング!$A:$G,6,0)/100,0)+IFERROR(VLOOKUP(C53,▼売上原票!$A:$P,12,0)*VLOOKUP("615-3",▼マッピング!$A:$G,6,0)/100,0)+IFERROR(VLOOKUP(C53,▼売上原票!$A:$P,13,0)*VLOOKUP("615-4",▼マッピング!$A:$G,6,0)/100,0) | H53: =D53+E53+F53+G53 | P53: =I53+J53+K53+L53+M53+N53+O53 | Q53: =H53-P53 | R53: =IF(H53<>0,Q53/H53,0) | S53: =IF(R53>=0.25,"◎ 優良",IF(R53>=0.15,"○ 良好",IF(R53>=0.05,"△ 要注意","× 赤字"))) | T53: =IF(H52<>0,H53/H52-1,"")
... A57: C003 | B57: 一般事業者案件 | C57: 2025-11 | D57: =IFERROR(VLOOKUP(C57,▼売上原票!$A:$P,3,0)*VLOOKUP("612-1",▼マッピング!$A:$G,6,0)/100,0) | E57: =IFERROR(VLOOKUP(C57,▼売上原票!$A:$P,4,0)*VLOOKUP("612-2",▼マッピング!$A:$G,6,0)/100,0) | F57: =IFERROR(VLOOKUP(C57,▼売上原票!$A:$P,10,0)*VLOOKUP("615-1",▼マッピング!$A:$G,6,0)/100,0) | G57: =IFERROR(VLOOKUP(C57,▼売上原票!$A:$P,5,0)*VLOOKUP("613-1",▼マッピング!$A:$G,6,0)/100,0)+IFERROR(VLOOKUP(C57,▼売上原票!$A:$P,6,0)*VLOOKUP("613-2",▼マッピング!$A:$G,6,0)/100,0)+IFERROR(VLOOKUP(C57,▼売上原票!$A:$P,7,0)*VLOOKUP("614-1",▼マッピング!$A:$G,6,0)/100,0)+IFERROR(VLOOKUP(C57,▼売上原票!$A:$P,8,0)*VLOOKUP("614-2",▼マッピング!$A:$G,6,0)/100,0)+IFERROR(VLOOKUP(C57,▼売上原票!$A:$P,9,0)*VLOOKUP("614-3",▼マッピング!$A:$G,6,0)/100,0)+IFERROR(VLOOKUP(C57,▼売上原票!$A:$P,11,0)*VLOOKUP("615-2",▼マッピング!$A:$G,6,0)/100,0)+IFERROR(VLOOKUP(C57,▼売上原票!$A:$P,12,0)*VLOOKUP("615-3",▼マッピング!$A:$G,6,0)/100,0)+IFERROR(VLOOKUP(C57,▼売上原票!$A:$P,13,0)*VLOOKUP("615-4",▼マッピング!$A:$G,6,0)/100,0) | H57: =D57+E57+F57+G57 | P57: =I57+J57+K57+L57+M57+N57+O57 | Q57: =H57-P57 | R57: =IF(H57<>0,Q57/H57,0) | S57: =IF(R57>=0.25,"◎ 優良",IF(R57>=0.15,"○ 良好",IF(R57>=0.05,"△ 要注意","× 赤字"))) | T57: =IF(H56<>0,H57/H56-1,"")
H59: =D59+E59+F59+G59 | P59: =IF(I59+J59+K59+L59+M59+N59+O59=0,"",I59+J59+K59+L59+M59+N59+O59) | Q59: =IF(H59<>0,H59-P59,"") | R59: =IF(H59<>0,Q59/H59,"") | S59: =IF(R59="","",IF(R59>=0.25,"◎ 優良",IF(R59>=0.15,"○ 良好",IF(R59>=0.05,"△ 要注意","× 赤字"))))
H60: =D60+E60+F60+G60 | P60: =IF(I60+J60+K60+L60+M60+N60+O60=0,"",I60+J60+K60+L60+M60+N60+O60) | Q60: =IF(H60<>0,H60-P60,"") | R60: =IF(H60<>0,Q60/H60,"") | S60: =IF(R60="","",IF(R60>=0.25,"◎ 優良",IF(R60>=0.15,"○ 良好",IF(R60>=0.05,"△ 要注意","× 赤字"))))
H61: =D61+E61+F61+G61 | P61: =IF(I61+J61+K61+L61+M61+N61+O61=0,"",I61+J61+K61+L61+M61+N61+O61) | Q61: =IF(H61<>0,H61-P61,"") | R61: =IF(H61<>0,Q61/H61,"") | S61: =IF(R61="","",IF(R61>=0.25,"◎ 優良",IF(R61>=0.15,"○ 良好",IF(R61>=0.05,"△ 要注意","× 赤字"))))
H62: =D62+E62+F62+G62 | P62: =IF(I62+J62+K62+L62+M62+N62+O62=0,"",I62+J62+K62+L62+M62+N62+O62) | Q62: =IF(H62<>0,H62-P62,"") | R62: =IF(H62<>0,Q62/H62,"") | S62: =IF(R62="","",IF(R62>=0.25,"◎ 優良",IF(R62>=0.15,"○ 良好",IF(R62>=0.05,"△ 要注意","× 赤字"))))
H63: =D63+E63+F63+G63 | P63: =IF(I63+J63+K63+L63+M63+N63+O63=0,"",I63+J63+K63+L63+M63+N63+O63) | Q63: =IF(H63<>0,H63-P63,"") | R63: =IF(H63<>0,Q63/H63,"") | S63: =IF(R63="","",IF(R63>=0.25,"◎ 優良",IF(R63>=0.15,"○ 良好",IF(R63>=0.05,"△ 要注意","× 赤字"))))
H64: =D64+E64+F64+G64 | P64: =IF(I64+J64+K64+L64+M64+N64+O64=0,"",I64+J64+K64+L64+M64+N64+O64) | Q64: =IF(H64<>0,H64-P64,"") | R64: =IF(H64<>0,Q64/H64,"") | S64: =IF(R64="","",IF(R64>=0.25,"◎ 優良",IF(R64>=0.15,"○ 良好",IF(R64>=0.05,"△ 要注意","× 赤字"))))
H65: =D65+E65+F65+G65 | P65: =IF(I65+J65+K65+L65+M65+N65+O65=0,"",I65+J65+K65+L65+M65+N65+O65) | Q65: =IF(H65<>0,H65-P65,"") | R65: =IF(H65<>0,Q65/H65,"") | S65: =IF(R65="","",IF(R65>=0.25,"◎ 優良",IF(R65>=0.15,"○ 良好",IF(R65>=0.05,"△ 要注意","× 赤字"))))
H66: =D66+E66+F66+G66 | P66: =IF(I66+J66+K66+L66+M66+N66+O66=0,"",I66+J66+K66+L66+M66+N66+O66) | Q66: =IF(H66<>0,H66-P66,"") | R66: =IF(H66<>0,Q66/H66,"") | S66: =IF(R66="","",IF(R66>=0.25,"◎ 優良",IF(R66>=0.15,"○ 良好",IF(R66>=0.05,"△ 要注意","× 赤字"))))
H67: =D67+E67+F67+G67 | P67: =IF(I67+J67+K67+L67+M67+N67+O67=0,"",I67+J67+K67+L67+M67+N67+O67) | Q67: =IF(H67<>0,H67-P67,"") | R67: =IF(H67<>0,Q67/H67,"") | S67: =IF(R67="","",IF(R67>=0.25,"◎ 優良",IF(R67>=0.15,"○ 良好",IF(R67>=0.05,"△ 要注意","× 赤字"))))
H68: =D68+E68+F68+G68 | P68: =IF(I68+J68+K68+L68+M68+N68+O68=0,"",I68+J68+K68+L68+M68+N68+O68) | Q68: =IF(H68<>0,H68-P68,"") | R68: =IF(H68<>0,Q68/H68,"") | S68: =IF(R68="","",IF(R68>=0.25,"◎ 優良",IF(R68>=0.15,"○ 良好",IF(R68>=0.05,"△ 要注意","× 赤字"))))
H69: =D69+E69+F69+G69 | P69: =IF(I69+J69+K69+L69+M69+N69+O69=0,"",I69+J69+K69+L69+M69+N69+O69) | Q69: =IF(H69<>0,H69-P69,"") | R69: =IF(H69<>0,Q69/H69,"") | S69: =IF(R69="","",IF(R69>=0.25,"◎ 優良",IF(R69>=0.15,"○ 良好",IF(R69>=0.05,"△ 要注意","× 赤字"))))
H70: =D70+E70+F70+G70 | P70: =IF(I70+J70+K70+L70+M70+N70+O70=0,"",I70+J70+K70+L70+M70+N70+O70) | Q70: =IF(H70<>0,H70-P70,"") | R70: =IF(H70<>0,Q70/H70,"") | S70: =IF(R70="","",IF(R70>=0.25,"◎ 優良",IF(R70>=0.15,"○ 良好",IF(R70>=0.05,"△ 要注意","× 赤字"))))
... H73: =D73+E73+F73+G73 | P73: =IF(I73+J73+K73+L73+M73+N73+O73=0,"",I73+J73+K73+L73+M73+N73+O73) | Q73: =IF(H73<>0,H73-P73,"") | R73: =IF(H73<>0,Q73/H73,"") | S73: =IF(R73="","",IF(R73>=0.25,"◎ 優良",IF(R73>=0.15,"○ 良好",IF(R73>=0.05,"△ 要注意","× 赤字"))))

Sheet ルート別採算
A1: ルート別 採算管理 （ルート = 科目コード / 各営業担当）
A2: 【売上】⑤売上原票からVLOOKUPで自動参照 【原価】黄色セルに実績を入力 各ルートの粗利率で採算の良し悪しを確認できます
A3: ルートコード | B3: ルート名 | C3: 集計月 (YYYY-MM) | D3: 売上 (VLOOKUP) | E3: 原価 （黄色セル入力） | L3: 粗利益 | M3: 粗利率 | N3: 採算判定 | O3: 主担当 案件 | P3: 前月比 売上 | Q3: 月間回収量 (kg推算)
E4: 人件費 | F4: 燃料費 | G4: 車両費 | H4: 処理費 | I4: 運搬費 | J4: その他 | K4: 合計
A5: 612-1 | B5: 運送（本社） | C5: 2024-07 | D5: =IFERROR(VLOOKUP(C5,▼売上原票!$A:$P,3,0),0) | E5: =SUMPRODUCT((▼従業員マスター!$A$6:$A$300="本社")*(▼従業員マスター!$G$6:$G$300="直接")*▼従業員マスター!$F$6:$F$300) | K5: =E5+F5+G5+H5+I5+J5 | L5: =D5-K5 | M5: =IF(D5<>0,L5/D5,0) | N5: =IF(D5=0,"—",IF(M5>=0.25,"◎ 優良",IF(M5>=0.15,"○ 良好",IF(M5>=0.05,"△ 要注意","× 赤字")))) | O5: C003一般 | P5: — | Q5: =IFERROR(D5/100,0)
A6: 612-1 | B6: 運送（本社） | C6: 2024-08 | D6: =IFERROR(VLOOKUP(C6,▼売上原票!$A:$P,3,0),0) | E6: =SUMPRODUCT((▼従業員マスター!$A$6:$A$300="本社")*(▼従業員マスター!$G$6:$G$300="直接")*▼従業員マスター!$F$6:$F$300) | K6: =E6+F6+G6+H6+I6+J6 | L6: =D6-K6 | M6: =IF(D6<>0,L6/D6,0) | N6: =IF(D6=0,"—",IF(M6>=0.25,"◎ 優良",IF(M6>=0.15,"○ 良好",IF(M6>=0.05,"△ 要注意","× 赤字")))) | O6: C003一般 | P6: =IF(D5<>0,D6/D5-1,"") | Q6: =IFERROR(D6/100,0)
A7: 612-1 | B7: 運送（本社） | C7: 2024-09 | D7: =IFERROR(VLOOKUP(C7,▼売上原票!$A:$P,3,0),0) | E7: =SUMPRODUCT((▼従業員マスター!$A$6:$A$300="本社")*(▼従業員マスター!$G$6:$G$300="直接")*▼従業員マスター!$F$6:$F$300) | K7: =E7+F7+G7+H7+I7+J7 | L7: =D7-K7 | M7: =IF(D7<>0,L7/D7,0) | N7: =IF(D7=0,"—",IF(M7>=0.25,"◎ 優良",IF(M7>=0.15,"○ 良好",IF(M7>=0.05,"△ 要注意","× 赤字")))) | O7: C003一般 | P7: =IF(D6<>0,D7/D6-1,"") | Q7: =IFERROR(D7/100,0)
A8: 612-1 | B8: 運送（本社） | C8: 2024-10 | D8: =IFERROR(VLOOKUP(C8,▼売上原票!$A:$P,3,0),0) | E8: =SUMPRODUCT((▼従業員マスター!$A$6:$A$300="本社")*(▼従業員マスター!$G$6:$G$300="直接")*▼従業員マスター!$F$6:$F$300) | K8: =E8+F8+G8+H8+I8+J8 | L8: =D8-K8 | M8: =IF(D8<>0,L8/D8,0) | N8: =IF(D8=0,"—",IF(M8>=0.25,"◎ 優良",IF(M8>=0.15,"○ 良好",IF(M8>=0.05,"△ 要注意","× 赤字")))) | O8: C003一般 | P8: =IF(D7<>0,D8/D7-1,"") | Q8: =IFERROR(D8/100,0)
A9: 612-1 | B9: 運送（本社） | C9: 2024-11 | D9: =IFERROR(VLOOKUP(C9,▼売上原票!$A:$P,3,0),0) | E9: =SUMPRODUCT((▼従業員マスター!$A$6:$A$300="本社")*(▼従業員マスター!$G$6:$G$300="直接")*▼従業員マスター!$F$6:$F$300) | K9: =E9+F9+G9+H9+I9+J9 | L9: =D9-K9 | M9: =IF(D9<>0,L9/D9,0) | N9: =IF(D9=0,"—",IF(M9>=0.25,"◎ 優良",IF(M9>=0.15,"○ 良好",IF(M9>=0.05,"△ 要注意","× 赤字")))) | O9: C003一般 | P9: =IF(D8<>0,D9/D8-1,"") | Q9: =IFERROR(D9/100,0)
A10: 612-1 | B10: 運送（本社） | C10: 2024-12 | D10: =IFERROR(VLOOKUP(C10,▼売上原票!$A:$P,3,0),0) | E10: =SUMPRODUCT((▼従業員マスター!$A$6:$A$300="本社")*(▼従業員マスター!$G$6:$G$300="直接")*▼従業員マスター!$F$6:$F$300) | K10: =E10+F10+G10+H10+I10+J10 | L10: =D10-K10 | M10: =IF(D10<>0,L10/D10,0) | N10: =IF(D10=0,"—",IF(M10>=0.25,"◎ 優良",IF(M10>=0.15,"○ 良好",IF(M10>=0.05,"△ 要注意","× 赤字")))) | O10: C003一般 | P10: =IF(D9<>0,D10/D9-1,"") | Q10: =IFERROR(D10/100,0)
A11: 612-1 | B11: 運送（本社） | C11: 2025-01 | D11: =IFERROR(VLOOKUP(C11,▼売上原票!$A:$P,3,0),0) | E11: =SUMPRODUCT((▼従業員マスター!$A$6:$A$300="本社")*(▼従業員マスター!$G$6:$G$300="直接")*▼従業員マスター!$F$6:$F$300) | K11: =E11+F11+G11+H11+I11+J11 | L11: =D11-K11 | M11: =IF(D11<>0,L11/D11,0) | N11: =IF(D11=0,"—",IF(M11>=0.25,"◎ 優良",IF(M11>=0.15,"○ 良好",IF(M11>=0.05,"△ 要注意","× 赤字")))) | O11: C003一般 | P11: =IF(D10<>0,D11/D10-1,"") | Q11: =IFERROR(D11/100,0)
A12: 612-1 | B12: 運送（本社） | C12: 2025-02 | D12: =IFERROR(VLOOKUP(C12,▼売上原票!$A:$P,3,0),0) | E12: =SUMPRODUCT((▼従業員マスター!$A$6:$A$300="本社")*(▼従業員マスター!$G$6:$G$300="直接")*▼従業員マスター!$F$6:$F$300) | K12: =E12+F12+G12+H12+I12+J12 | L12: =D12-K12 | M12: =IF(D12<>0,L12/D12,0) | N12: =IF(D12=0,"—",IF(M12>=0.25,"◎ 優良",IF(M12>=0.15,"○ 良好",IF(M12>=0.05,"△ 要注意","× 赤字")))) | O12: C003一般 | P12: =IF(D11<>0,D12/D11-1,"") | Q12: =IFERROR(D12/100,0)
A13: 612-1 | B13: 運送（本社） | C13: 2025-03 | D13: =IFERROR(VLOOKUP(C13,▼売上原票!$A:$P,3,0),0) | E13: =SUMPRODUCT((▼従業員マスター!$A$6:$A$300="本社")*(▼従業員マスター!$G$6:$G$300="直接")*▼従業員マスター!$F$6:$F$300) | K13: =E13+F13+G13+H13+I13+J13 | L13: =D13-K13 | M13: =IF(D13<>0,L13/D13,0) | N13: =IF(D13=0,"—",IF(M13>=0.25,"◎ 優良",IF(M13>=0.15,"○ 良好",IF(M13>=0.05,"△ 要注意","× 赤字")))) | O13: C003一般 | P13: =IF(D12<>0,D13/D12-1,"") | Q13: =IFERROR(D13/100,0)
A14: 612-1 | B14: 運送（本社） | C14: 2025-04 | D14: =IFERROR(VLOOKUP(C14,▼売上原票!$A:$P,3,0),0) | E14: =SUMPRODUCT((▼従業員マスター!$A$6:$A$300="本社")*(▼従業員マスター!$G$6:$G$300="直接")*▼従業員マスター!$F$6:$F$300) | K14: =E14+F14+G14+H14+I14+J14 | L14: =D14-K14 | M14: =IF(D14<>0,L14/D14,0) | N14: =IF(D14=0,"—",IF(M14>=0.25,"◎ 優良",IF(M14>=0.15,"○ 良好",IF(M14>=0.05,"△ 要注意","× 赤字")))) | O14: C003一般 | P14: =IF(D13<>0,D14/D13-1,"") | Q14: =IFERROR(D14/100,0)
A15: 612-1 | B15: 運送（本社） | C15: 2025-05 | D15: =IFERROR(VLOOKUP(C15,▼売上原票!$A:$P,3,0),0) | E15: =SUMPRODUCT((▼従業員マスター!$A$6:$A$300="本社")*(▼従業員マスター!$G$6:$G$300="直接")*▼従業員マスター!$F$6:$F$300) | K15: =E15+F15+G15+H15+I15+J15 | L15: =D15-K15 | M15: =IF(D15<>0,L15/D15,0) | N15: =IF(D15=0,"—",IF(M15>=0.25,"◎ 優良",IF(M15>=0.15,"○ 良好",IF(M15>=0.05,"△ 要注意","× 赤字")))) | O15: C003一般 | P15: =IF(D14<>0,D15/D14-1,"") | Q15: =IFERROR(D15/100,0)
A16: 612-1 | B16: 運送（本社） | C16: 2025-06 | D16: =IFERROR(VLOOKUP(C16,▼売上原票!$A:$P,3,0),0) | E16: =SUMPRODUCT((▼従業員マスター!$A$6:$A$300="本社")*(▼従業員マスター!$G$6:$G$300="直接")*▼従業員マスター!$F$6:$F$300) | K16: =E16+F16+G16+H16+I16+J16 | L16: =D16-K16 | M16: =IF(D16<>0,L16/D16,0) | N16: =IF(D16=0,"—",IF(M16>=0.25,"◎ 優良",IF(M16>=0.15,"○ 良好",IF(M16>=0.05,"△ 要注意","× 赤字")))) | O16: C003一般 | P16: =IF(D15<>0,D16/D15-1,"") | Q16: =IFERROR(D16/100,0)
A17: 612-1 | B17: 運送（本社） | C17: 2025-07 | D17: =IFERROR(VLOOKUP(C17,▼売上原票!$A:$P,3,0),0) | E17: =SUMPRODUCT((▼従業員マスター!$A$6:$A$300="本社")*(▼従業員マスター!$G$6:$G$300="直接")*▼従業員マスター!$F$6:$F$300) | K17: =E17+F17+G17+H17+I17+J17 | L17: =D17-K17 | M17: =IF(D17<>0,L17/D17,0) | N17: =IF(D17=0,"—",IF(M17>=0.25,"◎ 優良",IF(M17>=0.15,"○ 良好",IF(M17>=0.05,"△ 要注意","× 赤字")))) | O17: C003一般 | P17: =IF(D16<>0,D17/D16-1,"") | Q17: =IFERROR(D17/100,0)
... A21: 612-1 | B21: 運送（本社） | C21: 2025-11 | D21: =IFERROR(VLOOKUP(C21,▼売上原票!$A:$P,3,0),0) | E21: =SUMPRODUCT((▼従業員マスター!$A$6:$A$300="本社")*(▼従業員マスター!$G$6:$G$300="直接")*▼従業員マスター!$F$6:$F$300) | K21: =E21+F21+G21+H21+I21+J21 | L21: =D21-K21 | M21: =IF(D21<>0,L21/D21,0) | N21: =IF(D21=0,"—",IF(M21>=0.25,"◎ 優良",IF(M21>=0.15,"○ 良好",IF(M21>=0.05,"△ 要注意","× 赤字")))) | O21: C003一般 | P21: =IF(D20<>0,D21/D20-1,"") | Q21: =IFERROR(D21/100,0)
A23: 612-2 | B23: 入札（公共） | C23: 2024-07 | D23: =IFERROR(VLOOKUP(C23,▼売上原票!$A:$P,4,0),0) | E23: =SUMPRODUCT((▼従業員マスター!$A$6:$A$300="埼玉")*(▼従業員マスター!$G$6:$G$300="直接")*▼従業員マスター!$F$6:$F$300) | K23: =E23+F23+G23+H23+I23+J23 | L23: =D23-K23 | M23: =IF(D23<>0,L23/D23,0) | N23: =IF(D23=0,"—",IF(M23>=0.25,"◎ 優良",IF(M23>=0.15,"○ 良好",IF(M23>=0.05,"△ 要注意","× 赤字")))) | O23: C002都営 | P23: — | Q23: =IFERROR(D23/100,0)
A24: 612-2 | B24: 入札（公共） | C24: 2024-08 | D24: =IFERROR(VLOOKUP(C24,▼売上原票!$A:$P,4,0),0) | E24: =SUMPRODUCT((▼従業員マスター!$A$6:$A$300="埼玉")*(▼従業員マスター!$G$6:$G$300="直接")*▼従業員マスター!$F$6:$F$300) | K24: =E24+F24+G24+H24+I24+J24 | L24: =D24-K24 | M24: =IF(D24<>0,L24/D24,0) | N24: =IF(D24=0,"—",IF(M24>=0.25,"◎ 優良",IF(M24>=0.15,"○ 良好",IF(M24>=0.05,"△ 要注意","× 赤字")))) | O24: C002都営 | P24: =IF(D23<>0,D24/D23-1,"") | Q24: =IFERROR(D24/100,0)
A25: 612-2 | B25: 入札（公共） | C25: 2024-09 | D25: =IFERROR(VLOOKUP(C25,▼売上原票!$A:$P,4,0),0) | E25: =SUMPRODUCT((▼従業員マスター!$A$6:$A$300="埼玉")*(▼従業員マスター!$G$6:$G$300="直接")*▼従業員マスター!$F$6:$F$300) | K25: =E25+F25+G25+H25+I25+J25 | L25: =D25-K25 | M25: =IF(D25<>0,L25/D25,0) | N25: =IF(D25=0,"—",IF(M25>=0.25,"◎ 優良",IF(M25>=0.15,"○ 良好",IF(M25>=0.05,"△ 要注意","× 赤字")))) | O25: C002都営 | P25: =IF(D24<>0,D25/D24-1,"") | Q25: =IFERROR(D25/100,0)
A26: 612-2 | B26: 入札（公共） | C26: 2024-10 | D26: =IFERROR(VLOOKUP(C26,▼売上原票!$A:$P,4,0),0) | E26: =SUMPRODUCT((▼従業員マスター!$A$6:$A$300="埼玉")*(▼従業員マスター!$G$6:$G$300="直接")*▼従業員マスター!$F$6:$F$300) | K26: =E26+F26+G26+H26+I26+J26 | L26: =D26-K26 | M26: =IF(D26<>0,L26/D26,0) | N26: =IF(D26=0,"—",IF(M26>=0.25,"◎ 優良",IF(M26>=0.15,"○ 良好",IF(M26>=0.05,"△ 要注意","× 赤字")))) | O26: C002都営 | P26: =IF(D25<>0,D26/D25-1,"") | Q26: =IFERROR(D26/100,0)
A27: 612-2 | B27: 入札（公共） | C27: 2024-11 | D27: =IFERROR(VLOOKUP(C27,▼売上原票!$A:$P,4,0),0) | E27: =SUMPRODUCT((▼従業員マスター!$A$6:$A$300="埼玉")*(▼従業員マスター!$G$6:$G$300="直接")*▼従業員マスター!$F$6:$F$300) | K27: =E27+F27+G27+H27+I27+J27 | L27: =D27-K27 | M27: =IF(D27<>0,L27/D27,0) | N27: =IF(D27=0,"—",IF(M27>=0.25,"◎ 優良",IF(M27>=0.15,"○ 良好",IF(M27>=0.05,"△ 要注意","× 赤字")))) | O27: C002都営 | P27: =IF(D26<>0,D27/D26-1,"") | Q27: =IFERROR(D27/100,0)
A28: 612-2 | B28: 入札（公共） | C28: 2024-12 | D28: =IFERROR(VLOOKUP(C28,▼売上原票!$A:$P,4,0),0) | E28: =SUMPRODUCT((▼従業員マスター!$A$6:$A$300="埼玉")*(▼従業員マスター!$G$6:$G$300="直接")*▼従業員マスター!$F$6:$F$300) | K28: =E28+F28+G28+H28+I28+J28 | L28: =D28-K28 | M28: =IF(D28<>0,L28/D28,0) | N28: =IF(D28=0,"—",IF(M28>=0.25,"◎ 優良",IF(M28>=0.15,"○ 良好",IF(M28>=0.05,"△ 要注意","× 赤字")))) | O28: C002都営 | P28: =IF(D27<>0,D28/D27-1,"") | Q28: =IFERROR(D28/100,0)
A29: 612-2 | B29: 入札（公共） | C29: 2025-01 | D29: =IFERROR(VLOOKUP(C29,▼売上原票!$A:$P,4,0),0) | E29: =SUMPRODUCT((▼従業員マスター!$A$6:$A$300="埼玉")*(▼従業員マスター!$G$6:$G$300="直接")*▼従業員マスター!$F$6:$F$300) | K29: =E29+F29+G29+H29+I29+J29 | L29: =D29-K29 | M29: =IF(D29<>0,L29/D29,0) | N29: =IF(D29=0,"—",IF(M29>=0.25,"◎ 優良",IF(M29>=0.15,"○ 良好",IF(M29>=0.05,"△ 要注意","× 赤字")))) | O29: C002都営 | P29: =IF(D28<>0,D29/D28-1,"") | Q29: =IFERROR(D29/100,0)
A30: 612-2 | B30: 入札（公共） | C30: 2025-02 | D30: =IFERROR(VLOOKUP(C30,▼売上原票!$A:$P,4,0),0) | E30: =SUMPRODUCT((▼従業員マスター!$A$6:$A$300="埼玉")*(▼従業員マスター!$G$6:$G$300="直接")*▼従業員マスター!$F$6:$F$300) | K30: =E30+F30+G30+H30+I30+J30 | L30: =D30-K30 | M30: =IF(D30<>0,L30/D30,0) | N30: =IF(D30=0,"—",IF(M30>=0.25,"◎ 優良",IF(M30>=0.15,"○ 良好",IF(M30>=0.05,"△ 要注意","× 赤字")))) | O30: C002都営 | P30: =IF(D29<>0,D30/D29-1,"") | Q30: =IFERROR(D30/100,0)
A31: 612-2 | B31: 入札（公共） | C31: 2025-03 | D31: =IFERROR(VLOOKUP(C31,▼売上原票!$A:$P,4,0),0) | E31: =SUMPRODUCT((▼従業員マスター!$A$6:$A$300="埼玉")*(▼従業員マスター!$G$6:$G$300="直接")*▼従業員マスター!$F$6:$F$300) | K31: =E31+F31+G31+H31+I31+J31 | L31: =D31-K31 | M31: =IF(D31<>0,L31/D31,0) | N31: =IF(D31=0,"—",IF(M31>=0.25,"◎ 優良",IF(M31>=0.15,"○ 良好",IF(M31>=0.05,"△ 要注意","× 赤字")))) | O31: C002都営 | P31: =IF(D30<>0,D31/D30-1,"") | Q31: =IFERROR(D31/100,0)
A32: 612-2 | B32: 入札（公共） | C32: 2025-04 | D32: =IFERROR(VLOOKUP(C32,▼売上原票!$A:$P,4,0),0) | E32: =SUMPRODUCT((▼従業員マスター!$A$6:$A$300="埼玉")*(▼従業員マスター!$G$6:$G$300="直接")*▼従業員マスター!$F$6:$F$300) | K32: =E32+F32+G32+H32+I32+J32 | L32: =D32-K32 | M32: =IF(D32<>0,L32/D32,0) | N32: =IF(D32=0,"—",IF(M32>=0.25,"◎ 優良",IF(M32>=0.15,"○ 良好",IF(M32>=0.05,"△ 要注意","× 赤字")))) | O32: C002都営 | P32: =IF(D31<>0,D32/D31-1,"") | Q32: =IFERROR(D32/100,0)
A33: 612-2 | B33: 入札（公共） | C33: 2025-05 | D33: =IFERROR(VLOOKUP(C33,▼売上原票!$A:$P,4,0),0) | E33: =SUMPRODUCT((▼従業員マスター!$A$6:$A$300="埼玉")*(▼従業員マスター!$G$6:$G$300="直接")*▼従業員マスター!$F$6:$F$300) | K33: =E33+F33+G33+H33+I33+J33 | L33: =D33-K33 | M33: =IF(D33<>0,L33/D33,0) | N33: =IF(D33=0,"—",IF(M33>=0.25,"◎ 優良",IF(M33>=0.15,"○ 良好",IF(M33>=0.05,"△ 要注意","× 赤字")))) | O33: C002都営 | P33: =IF(D32<>0,D33/D32-1,"") | Q33: =IFERROR(D33/100,0)
A34: 612-2 | B34: 入札（公共） | C34: 2025-06 | D34: =IFERROR(VLOOKUP(C34,▼売上原票!$A:$P,4,0),0) | E34: =SUMPRODUCT((▼従業員マスター!$A$6:$A$300="埼玉")*(▼従業員マスター!$G$6:$G$300="直接")*▼従業員マスター!$F$6:$F$300) | K34: =E34+F34+G34+H34+I34+J34 | L34: =D34-K34 | M34: =IF(D34<>0,L34/D34,0) | N34: =IF(D34=0,"—",IF(M34>=0.25,"◎ 優良",IF(M34>=0.15,"○ 良好",IF(M34>=0.05,"△ 要注意","× 赤字")))) | O34: C002都営 | P34: =IF(D33<>0,D34/D33-1,"") | Q34: =IFERROR(D34/100,0)
A35: 612-2 | B35: 入札（公共） | C35: 2025-07 | D35: =IFERROR(VLOOKUP(C35,▼売上原票!$A:$P,4,0),0) | E35: =SUMPRODUCT((▼従業員マスター!$A$6:$A$300="埼玉")*(▼従業員マスター!$G$6:$G$300="直接")*▼従業員マスター!$F$6:$F$300) | K35: =E35+F35+G35+H35+I35+J35 | L35: =D35-K35 | M35: =IF(D35<>0,L35/D35,0) | N35: =IF(D35=0,"—",IF(M35>=0.25,"◎ 優良",IF(M35>=0.15,"○ 良好",IF(M35>=0.05,"△ 要注意","× 赤字")))) | O35: C002都営 | P35: =IF(D34<>0,D35/D34-1,"") | Q35: =IFERROR(D35/100,0)
... A39: 612-2 | B39: 入札（公共） | C39: 2025-11 | D39: =IFERROR(VLOOKUP(C39,▼売上原票!$A:$P,4,0),0) | E39: =SUMPRODUCT((▼従業員マスター!$A$6:$A$300="埼玉")*(▼従業員マスター!$G$6:$G$300="直接")*▼従業員マスター!$F$6:$F$300) | K39: =E39+F39+G39+H39+I39+J39 | L39: =D39-K39 | M39: =IF(D39<>0,L39/D39,0) | N39: =IF(D39=0,"—",IF(M39>=0.25,"◎ 優良",IF(M39>=0.15,"○ 良好",IF(M39>=0.05,"△ 要注意","× 赤字")))) | O39: C002都営 | P39: =IF(D38<>0,D39/D38-1,"") | Q39: =IFERROR(D39/100,0)
A41: 613-1 | B41: 車輌 | C41: 2024-07 | D41: =IFERROR(VLOOKUP(C41,▼売上原票!$A:$P,5,0),0) | K41: =E41+F41+G41+H41+I41+J41 | L41: =D41-K41 | M41: =IF(D41<>0,L41/D41,0) | N41: =IF(D41=0,"—",IF(M41>=0.25,"◎ 優良",IF(M41>=0.15,"○ 良好",IF(M41>=0.05,"△ 要注意","× 赤字")))) | O41: C003一般 | P41: — | Q41: =IFERROR(D41/100,0)
A42: 613-1 | B42: 車輌 | C42: 2024-08 | D42: =IFERROR(VLOOKUP(C42,▼売上原票!$A:$P,5,0),0) | K42: =E42+F42+G42+H42+I42+J42 | L42: =D42-K42 | M42: =IF(D42<>0,L42/D42,0) | N42: =IF(D42=0,"—",IF(M42>=0.25,"◎ 優良",IF(M42>=0.15,"○ 良好",IF(M42>=0.05,"△ 要注意","× 赤字")))) | O42: C003一般 | P42: =IF(D41<>0,D42/D41-1,"") | Q42: =IFERROR(D42/100,0)
A43: 613-1 | B43: 車輌 | C43: 2024-09 | D43: =IFERROR(VLOOKUP(C43,▼売上原票!$A:$P,5,0),0) | K43: =E43+F43+G43+H43+I43+J43 | L43: =D43-K43 | M43: =IF(D43<>0,L43/D43,0) | N43: =IF(D43=0,"—",IF(M43>=0.25,"◎ 優良",IF(M43>=0.15,"○ 良好",IF(M43>=0.05,"△ 要注意","× 赤字")))) | O43: C003一般 | P43: =IF(D42<>0,D43/D42-1,"") | Q43: =IFERROR(D43/100,0)
A44: 613-1 | B44: 車輌 | C44: 2024-10 | D44: =IFERROR(VLOOKUP(C44,▼売上原票!$A:$P,5,0),0) | K44: =E44+F44+G44+H44+I44+J44 | L44: =D44-K44 | M44: =IF(D44<>0,L44/D44,0) | N44: =IF(D44=0,"—",IF(M44>=0.25,"◎ 優良",IF(M44>=0.15,"○ 良好",IF(M44>=0.05,"△ 要注意","× 赤字")))) | O44: C003一般 | P44: =IF(D43<>0,D44/D43-1,"") | Q44: =IFERROR(D44/100,0)
A45: 613-1 | B45: 車輌 | C45: 2024-11 | D45: =IFERROR(VLOOKUP(C45,▼売上原票!$A:$P,5,0),0) | K45: =E45+F45+G45+H45+I45+J45 | L45: =D45-K45 | M45: =IF(D45<>0,L45/D45,0) | N45: =IF(D45=0,"—",IF(M45>=0.25,"◎ 優良",IF(M45>=0.15,"○ 良好",IF(M45>=0.05,"△ 要注意","× 赤字")))) | O45: C003一般 | P45: =IF(D44<>0,D45/D44-1,"") | Q45: =IFERROR(D45/100,0)
A46: 613-1 | B46: 車輌 | C46: 2024-12 | D46: =IFERROR(VLOOKUP(C46,▼売上原票!$A:$P,5,0),0) | K46: =E46+F46+G46+H46+I46+J46 | L46: =D46-K46 | M46: =IF(D46<>0,L46/D46,0) | N46: =IF(D46=0,"—",IF(M46>=0.25,"◎ 優良",IF(M46>=0.15,"○ 良好",IF(M46>=0.05,"△ 要注意","× 赤字")))) | O46: C003一般 | P46: =IF(D45<>0,D46/D45-1,"") | Q46: =IFERROR(D46/100,0)
A47: 613-1 | B47: 車輌 | C47: 2025-01 | D47: =IFERROR(VLOOKUP(C47,▼売上原票!$A:$P,5,0),0) | K47: =E47+F47+G47+H47+I47+J47 | L47: =D47-K47 | M47: =IF(D47<>0,L47/D47,0) | N47: =IF(D47=0,"—",IF(M47>=0.25,"◎ 優良",IF(M47>=0.15,"○ 良好",IF(M47>=0.05,"△ 要注意","× 赤字")))) | O47: C003一般 | P47: =IF(D46<>0,D47/D46-1,"") | Q47: =IFERROR(D47/100,0)
A48: 613-1 | B48: 車輌 | C48: 2025-02 | D48: =IFERROR(VLOOKUP(C48,▼売上原票!$A:$P,5,0),0) | K48: =E48+F48+G48+H48+I48+J48 | L48: =D48-K48 | M48: =IF(D48<>0,L48/D48,0) | N48: =IF(D48=0,"—",IF(M48>=0.25,"◎ 優良",IF(M48>=0.15,"○ 良好",IF(M48>=0.05,"△ 要注意","× 赤字")))) | O48: C003一般 | P48: =IF(D47<>0,D48/D47-1,"") | Q48: =IFERROR(D48/100,0)
A49: 613-1 | B49: 車輌 | C49: 2025-03 | D49: =IFERROR(VLOOKUP(C49,▼売上原票!$A:$P,5,0),0) | K49: =E49+F49+G49+H49+I49+J49 | L49: =D49-K49 | M49: =IF(D49<>0,L49/D49,0) | N49: =IF(D49=0,"—",IF(M49>=0.25,"◎ 優良",IF(M49>=0.15,"○ 良好",IF(M49>=0.05,"△ 要注意","× 赤字")))) | O49: C003一般 | P49: =IF(D48<>0,D49/D48-1,"") | Q49: =IFERROR(D49/100,0)
A50: 613-1 | B50: 車輌 | C50: 2025-04 | D50: =IFERROR(VLOOKUP(C50,▼売上原票!$A:$P,5,0),0) | K50: =E50+F50+G50+H50+I50+J50 | L50: =D50-K50 | M50: =IF(D50<>0,L50/D50,0) | N50: =IF(D50=0,"—",IF(M50>=0.25,"◎ 優良",IF(M50>=0.15,"○ 良好",IF(M50>=0.05,"△ 要注意","× 赤字")))) | O50: C003一般 | P50: =IF(D49<>0,D50/D49-1,"") | Q50: =IFERROR(D50/100,0)
A51: 613-1 | B51: 車輌 | C51: 2025-05 | D51: =IFERROR(VLOOKUP(C51,▼売上原票!$A:$P,5,0),0) | K51: =E51+F51+G51+H51+I51+J51 | L51: =D51-K51 | M51: =IF(D51<>0,L51/D51,0) | N51: =IF(D51=0,"—",IF(M51>=0.25,"◎ 優良",IF(M51>=0.15,"○ 良好",IF(M51>=0.05,"△ 要注意","× 赤字")))) | O51: C003一般 | P51: =IF(D50<>0,D51/D50-1,"") | Q51: =IFERROR(D51/100,0)
A52: 613-1 | B52: 車輌 | C52: 2025-06 | D52: =IFERROR(VLOOKUP(C52,▼売上原票!$A:$P,5,0),0) | K52: =E52+F52+G52+H52+I52+J52 | L52: =D52-K52 | M52: =IF(D52<>0,L52/D52,0) | N52: =IF(D52=0,"—",IF(M52>=0.25,"◎ 優良",IF(M52>=0.15,"○ 良好",IF(M52>=0.05,"△ 要注意","× 赤字")))) | O52: C003一般 | P52: =IF(D51<>0,D52/D51-1,"") | Q52: =IFERROR(D52/100,0)
A53: 613-1 | B53: 車輌 | C53: 2025-07 | D53: =IFERROR(VLOOKUP(C53,▼売上原票!$A:$P,5,0),0) | K53: =E53+F53+G53+H53+I53+J53 | L53: =D53-K53 | M53: =IF(D53<>0,L53/D53,0) | N53: =IF(D53=0,"—",IF(M53>=0.25,"◎ 優良",IF(M53>=0.15,"○ 良好",IF(M53>=0.05,"△ 要注意","× 赤字")))) | O53: C003一般 | P53: =IF(D52<>0,D53/D52-1,"") | Q53: =IFERROR(D53/100,0)
... A57: 613-1 | B57: 車輌 | C57: 2025-11 | D57: =IFERROR(VLOOKUP(C57,▼売上原票!$A:$P,5,0),0) | K57: =E57+F57+G57+H57+I57+J57 | L57: =D57-K57 | M57: =IF(D57<>0,L57/D57,0) | N57: =IF(D57=0,"—",IF(M57>=0.25,"◎ 優良",IF(M57>=0.15,"○ 良好",IF(M57>=0.05,"△ 要注意","× 赤字")))) | O57: C003一般 | P57: =IF(D56<>0,D57/D56-1,"") | Q57: =IFERROR(D57/100,0)
A59: 613-2 | B59: KC | C59: 2024-07 | D59: =IFERROR(VLOOKUP(C59,▼売上原票!$A:$P,6,0),0) | K59: =E59+F59+G59+H59+I59+J59 | L59: =D59-K59 | M59: =IF(D59<>0,L59/D59,0) | N59: =IF(D59=0,"—",IF(M59>=0.25,"◎ 優良",IF(M59>=0.15,"○ 良好",IF(M59>=0.05,"△ 要注意","× 赤字")))) | O59: 別管理 | P59: — | Q59: =IFERROR(D59/100,0)
A60: 613-2 | B60: KC | C60: 2024-08 | D60: =IFERROR(VLOOKUP(C60,▼売上原票!$A:$P,6,0),0) | K60: =E60+F60+G60+H60+I60+J60 | L60: =D60-K60 | M60: =IF(D60<>0,L60/D60,0) | N60: =IF(D60=0,"—",IF(M60>=0.25,"◎ 優良",IF(M60>=0.15,"○ 良好",IF(M60>=0.05,"△ 要注意","× 赤字")))) | O60: 別管理 | P60: =IF(D59<>0,D60/D59-1,"") | Q60: =IFERROR(D60/100,0)
A61: 613-2 | B61: KC | C61: 2024-09 | D61: =IFERROR(VLOOKUP(C61,▼売上原票!$A:$P,6,0),0) | K61: =E61+F61+G61+H61+I61+J61 | L61: =D61-K61 | M61: =IF(D61<>0,L61/D61,0) | N61: =IF(D61=0,"—",IF(M61>=0.25,"◎ 優良",IF(M61>=0.15,"○ 良好",IF(M61>=0.05,"△ 要注意","× 赤字")))) | O61: 別管理 | P61: =IF(D60<>0,D61/D60-1,"") | Q61: =IFERROR(D61/100,0)
A62: 613-2 | B62: KC | C62: 2024-10 | D62: =IFERROR(VLOOKUP(C62,▼売上原票!$A:$P,6,0),0) | K62: =E62+F62+G62+H62+I62+J62 | L62: =D62-K62 | M62: =IF(D62<>0,L62/D62,0) | N62: =IF(D62=0,"—",IF(M62>=0.25,"◎ 優良",IF(M62>=0.15,"○ 良好",IF(M62>=0.05,"△ 要注意","× 赤字")))) | O62: 別管理 | P62: =IF(D61<>0,D62/D61-1,"") | Q62: =IFERROR(D62/100,0)
A63: 613-2 | B63: KC | C63: 2024-11 | D63: =IFERROR(VLOOKUP(C63,▼売上原票!$A:$P,6,0),0) | K63: =E63+F63+G63+H63+I63+J63 | L63: =D63-K63 | M63: =IF(D63<>0,L63/D63,0) | N63: =IF(D63=0,"—",IF(M63>=0.25,"◎ 優良",IF(M63>=0.15,"○ 良好",IF(M63>=0.05,"△ 要注意","× 赤字")))) | O63: 別管理 | P63: =IF(D62<>0,D63/D62-1,"") | Q63: =IFERROR(D63/100,0)
A64: 613-2 | B64: KC | C64: 2024-12 | D64: =IFERROR(VLOOKUP(C64,▼売上原票!$A:$P,6,0),0) | K64: =E64+F64+G64+H64+I64+J64 | L64: =D64-K64 | M64: =IF(D64<>0,L64/D64,0) | N64: =IF(D64=0,"—",IF(M64>=0.25,"◎ 優良",IF(M64>=0.15,"○ 良好",IF(M64>=0.05,"△ 要注意","× 赤字")))) | O64: 別管理 | P64: =IF(D63<>0,D64/D63-1,"") | Q64: =IFERROR(D64/100,0)
A65: 613-2 | B65: KC | C65: 2025-01 | D65: =IFERROR(VLOOKUP(C65,▼売上原票!$A:$P,6,0),0) | K65: =E65+F65+G65+H65+I65+J65 | L65: =D65-K65 | M65: =IF(D65<>0,L65/D65,0) | N65: =IF(D65=0,"—",IF(M65>=0.25,"◎ 優良",IF(M65>=0.15,"○ 良好",IF(M65>=0.05,"△ 要注意","× 赤字")))) | O65: 別管理 | P65: =IF(D64<>0,D65/D64-1,"") | Q65: =IFERROR(D65/100,0)
A66: 613-2 | B66: KC | C66: 2025-02 | D66: =IFERROR(VLOOKUP(C66,▼売上原票!$A:$P,6,0),0) | K66: =E66+F66+G66+H66+I66+J66 | L66: =D66-K66 | M66: =IF(D66<>0,L66/D66,0) | N66: =IF(D66=0,"—",IF(M66>=0.25,"◎ 優良",IF(M66>=0.15,"○ 良好",IF(M66>=0.05,"△ 要注意","× 赤字")))) | O66: 別管理 | P66: =IF(D65<>0,D66/D65-1,"") | Q66: =IFERROR(D66/100,0)
A67: 613-2 | B67: KC | C67: 2025-03 | D67: =IFERROR(VLOOKUP(C67,▼売上原票!$A:$P,6,0),0) | K67: =E67+F67+G67+H67+I67+J67 | L67: =D67-K67 | M67: =IF(D67<>0,L67/D67,0) | N67: =IF(D67=0,"—",IF(M67>=0.25,"◎ 優良",IF(M67>=0.15,"○ 良好",IF(M67>=0.05,"△ 要注意","× 赤字")))) | O67: 別管理 | P67: =IF(D66<>0,D67/D66-1,"") | Q67: =IFERROR(D67/100,0)
A68: 613-2 | B68: KC | C68: 2025-04 | D68: =IFERROR(VLOOKUP(C68,▼売上原票!$A:$P,6,0),0) | K68: =E68+F68+G68+H68+I68+J68 | L68: =D68-K68 | M68: =IF(D68<>0,L68/D68,0) | N68: =IF(D68=0,"—",IF(M68>=0.25,"◎ 優良",IF(M68>=0.15,"○ 良好",IF(M68>=0.05,"△ 要注意","× 赤字")))) | O68: 別管理 | P68: =IF(D67<>0,D68/D67-1,"") | Q68: =IFERROR(D68/100,0)
A69: 613-2 | B69: KC | C69: 2025-05 | D69: =IFERROR(VLOOKUP(C69,▼売上原票!$A:$P,6,0),0) | K69: =E69+F69+G69+H69+I69+J69 | L69: =D69-K69 | M69: =IF(D69<>0,L69/D69,0) | N69: =IF(D69=0,"—",IF(M69>=0.25,"◎ 優良",IF(M69>=0.15,"○ 良好",IF(M69>=0.05,"△ 要注意","× 赤字")))) | O69: 別管理 | P69: =IF(D68<>0,D69/D68-1,"") | Q69: =IFERROR(D69/100,0)
A70: 613-2 | B70: KC | C70: 2025-06 | D70: =IFERROR(VLOOKUP(C70,▼売上原票!$A:$P,6,0),0) | K70: =E70+F70+G70+H70+I70+J70 | L70: =D70-K70 | M70: =IF(D70<>0,L70/D70,0) | N70: =IF(D70=0,"—",IF(M70>=0.25,"◎ 優良",IF(M70>=0.15,"○ 良好",IF(M70>=0.05,"△ 要注意","× 赤字")))) | O70: 別管理 | P70: =IF(D69<>0,D70/D69-1,"") | Q70: =IFERROR(D70/100,0)
A71: 613-2 | B71: KC | C71: 2025-07 | D71: =IFERROR(VLOOKUP(C71,▼売上原票!$A:$P,6,0),0) | K71: =E71+F71+G71+H71+I71+J71 | L71: =D71-K71 | M71: =IF(D71<>0,L71/D71,0) | N71: =IF(D71=0,"—",IF(M71>=0.25,"◎ 優良",IF(M71>=0.15,"○ 良好",IF(M71>=0.05,"△ 要注意","× 赤字")))) | O71: 別管理 | P71: =IF(D70<>0,D71/D70-1,"") | Q71: =IFERROR(D71/100,0)
... A75: 613-2 | B75: KC | C75: 2025-11 | D75: =IFERROR(VLOOKUP(C75,▼売上原票!$A:$P,6,0),0) | K75: =E75+F75+G75+H75+I75+J75 | L75: =D75-K75 | M75: =IF(D75<>0,L75/D75,0) | N75: =IF(D75=0,"—",IF(M75>=0.25,"◎ 優良",IF(M75>=0.15,"○ 良好",IF(M75>=0.05,"△ 要注意","× 赤字")))) | O75: 別管理 | P75: =IF(D74<>0,D75/D74-1,"") | Q75: =IFERROR(D75/100,0)
A77: 614-1 | B77: コンテナ | C77: 2024-07 | D77: =IFERROR(VLOOKUP(C77,▼売上原票!$A:$P,7,0),0) | K77: =E77+F77+G77+H77+I77+J77 | L77: =D77-K77 | M77: =IF(D77<>0,L77/D77,0) | N77: =IF(D77=0,"—",IF(M77>=0.25,"◎ 優良",IF(M77>=0.15,"○ 良好",IF(M77>=0.05,"△ 要注意","× 赤字")))) | O77: C003一般 | P77: — | Q77: =IFERROR(D77/100,0)
A78: 614-1 | B78: コンテナ | C78: 2024-08 | D78: =IFERROR(VLOOKUP(C78,▼売上原票!$A:$P,7,0),0) | K78: =E78+F78+G78+H78+I78+J78 | L78: =D78-K78 | M78: =IF(D78<>0,L78/D78,0) | N78: =IF(D78=0,"—",IF(M78>=0.25,"◎ 優良",IF(M78>=0.15,"○ 良好",IF(M78>=0.05,"△ 要注意","× 赤字")))) | O78: C003一般 | P78: =IF(D77<>0,D78/D77-1,"") | Q78: =IFERROR(D78/100,0)
A79: 614-1 | B79: コンテナ | C79: 2024-09 | D79: =IFERROR(VLOOKUP(C79,▼売上原票!$A:$P,7,0),0) | K79: =E79+F79+G79+H79+I79+J79 | L79: =D79-K79 | M79: =IF(D79<>0,L79/D79,0) | N79: =IF(D79=0,"—",IF(M79>=0.25,"◎ 優良",IF(M79>=0.15,"○ 良好",IF(M79>=0.05,"△ 要注意","× 赤字")))) | O79: C003一般 | P79: =IF(D78<>0,D79/D78-1,"") | Q79: =IFERROR(D79/100,0)
A80: 614-1 | B80: コンテナ | C80: 2024-10 | D80: =IFERROR(VLOOKUP(C80,▼売上原票!$A:$P,7,0),0) | K80: =E80+F80+G80+H80+I80+J80 | L80: =D80-K80 | M80: =IF(D80<>0,L80/D80,0) | N80: =IF(D80=0,"—",IF(M80>=0.25,"◎ 優良",IF(M80>=0.15,"○ 良好",IF(M80>=0.05,"△ 要注意","× 赤字")))) | O80: C003一般 | P80: =IF(D79<>0,D80/D79-1,"") | Q80: =IFERROR(D80/100,0)
A81: 614-1 | B81: コンテナ | C81: 2024-11 | D81: =IFERROR(VLOOKUP(C81,▼売上原票!$A:$P,7,0),0) | K81: =E81+F81+G81+H81+I81+J81 | L81: =D81-K81 | M81: =IF(D81<>0,L81/D81,0) | N81: =IF(D81=0,"—",IF(M81>=0.25,"◎ 優良",IF(M81>=0.15,"○ 良好",IF(M81>=0.05,"△ 要注意","× 赤字")))) | O81: C003一般 | P81: =IF(D80<>0,D81/D80-1,"") | Q81: =IFERROR(D81/100,0)
A82: 614-1 | B82: コンテナ | C82: 2024-12 | D82: =IFERROR(VLOOKUP(C82,▼売上原票!$A:$P,7,0),0) | K82: =E82+F82+G82+H82+I82+J82 | L82: =D82-K82 | M82: =IF(D82<>0,L82/D82,0) | N82: =IF(D82=0,"—",IF(M82>=0.25,"◎ 優良",IF(M82>=0.15,"○ 良好",IF(M82>=0.05,"△ 要注意","× 赤字")))) | O82: C003一般 | P82: =IF(D81<>0,D82/D81-1,"") | Q82: =IFERROR(D82/100,0)
A83: 614-1 | B83: コンテナ | C83: 2025-01 | D83: =IFERROR(VLOOKUP(C83,▼売上原票!$A:$P,7,0),0) | K83: =E83+F83+G83+H83+I83+J83 | L83: =D83-K83 | M83: =IF(D83<>0,L83/D83,0) | N83: =IF(D83=0,"—",IF(M83>=0.25,"◎ 優良",IF(M83>=0.15,"○ 良好",IF(M83>=0.05,"△ 要注意","× 赤字")))) | O83: C003一般 | P83: =IF(D82<>0,D83/D82-1,"") | Q83: =IFERROR(D83/100,0)
A84: 614-1 | B84: コンテナ | C84: 2025-02 | D84: =IFERROR(VLOOKUP(C84,▼売上原票!$A:$P,7,0),0) | K84: =E84+F84+G84+H84+I84+J84 | L84: =D84-K84 | M84: =IF(D84<>0,L84/D84,0) | N84: =IF(D84=0,"—",IF(M84>=0.25,"◎ 優良",IF(M84>=0.15,"○ 良好",IF(M84>=0.05,"△ 要注意","× 赤字")))) | O84: C003一般 | P84: =IF(D83<>0,D84/D83-1,"") | Q84: =IFERROR(D84/100,0)
A85: 614-1 | B85: コンテナ | C85: 2025-03 | D85: =IFERROR(VLOOKUP(C85,▼売上原票!$A:$P,7,0),0) | K85: =E85+F85+G85+H85+I85+J85 | L85: =D85-K85 | M85: =IF(D85<>0,L85/D85,0) | N85: =IF(D85=0,"—",IF(M85>=0.25,"◎ 優良",IF(M85>=0.15,"○ 良好",IF(M85>=0.05,"△ 要注意","× 赤字")))) | O85: C003一般 | P85: =IF(D84<>0,D85/D84-1,"") | Q85: =IFERROR(D85/100,0)
A86: 614-1 | B86: コンテナ | C86: 2025-04 | D86: =IFERROR(VLOOKUP(C86,▼売上原票!$A:$P,7,0),0) | K86: =E86+F86+G86+H86+I86+J86 | L86: =D86-K86 | M86: =IF(D86<>0,L86/D86,0) | N86: =IF(D86=0,"—",IF(M86>=0.25,"◎ 優良",IF(M86>=0.15,"○ 良好",IF(M86>=0.05,"△ 要注意","× 赤字")))) | O86: C003一般 | P86: =IF(D85<>0,D86/D85-1,"") | Q86: =IFERROR(D86/100,0)
A87: 614-1 | B87: コンテナ | C87: 2025-05 | D87: =IFERROR(VLOOKUP(C87,▼売上原票!$A:$P,7,0),0) | K87: =E87+F87+G87+H87+I87+J87 | L87: =D87-K87 | M87: =IF(D87<>0,L87/D87,0) | N87: =IF(D87=0,"—",IF(M87>=0.25,"◎ 優良",IF(M87>=0.15,"○ 良好",IF(M87>=0.05,"△ 要注意","× 赤字")))) | O87: C003一般 | P87: =IF(D86<>0,D87/D86-1,"") | Q87: =IFERROR(D87/100,0)
A88: 614-1 | B88: コンテナ | C88: 2025-06 | D88: =IFERROR(VLOOKUP(C88,▼売上原票!$A:$P,7,0),0) | K88: =E88+F88+G88+H88+I88+J88 | L88: =D88-K88 | M88: =IF(D88<>0,L88/D88,0) | N88: =IF(D88=0,"—",IF(M88>=0.25,"◎ 優良",IF(M88>=0.15,"○ 良好",IF(M88>=0.05,"△ 要注意","× 赤字")))) | O88: C003一般 | P88: =IF(D87<>0,D88/D87-1,"") | Q88: =IFERROR(D88/100,0)
A89: 614-1 | B89: コンテナ | C89: 2025-07 | D89: =IFERROR(VLOOKUP(C89,▼売上原票!$A:$P,7,0),0) | K89: =E89+F89+G89+H89+I89+J89 | L89: =D89-K89 | M89: =IF(D89<>0,L89/D89,0) | N89: =IF(D89=0,"—",IF(M89>=0.25,"◎ 優良",IF(M89>=0.15,"○ 良好",IF(M89>=0.05,"△ 要注意","× 赤字")))) | O89: C003一般 | P89: =IF(D88<>0,D89/D88-1,"") | Q89: =IFERROR(D89/100,0)
... A93: 614-1 | B93: コンテナ | C93: 2025-11 | D93: =IFERROR(VLOOKUP(C93,▼売上原票!$A:$P,7,0),0) | K93: =E93+F93+G93+H93+I93+J93 | L93: =D93-K93 | M93: =IF(D93<>0,L93/D93,0) | N93: =IF(D93=0,"—",IF(M93>=0.25,"◎ 優良",IF(M93>=0.15,"○ 良好",IF(M93>=0.05,"△ 要注意","× 赤字")))) | O93: C003一般 | P93: =IF(D92<>0,D93/D92-1,"") | Q93: =IFERROR(D93/100,0)
A95: 614-2 | B95: ENDO | C95: 2024-07 | D95: =IFERROR(VLOOKUP(C95,▼売上原票!$A:$P,8,0),0) | K95: =E95+F95+G95+H95+I95+J95 | L95: =D95-K95 | M95: =IF(D95<>0,L95/D95,0) | N95: =IF(D95=0,"—",IF(M95>=0.25,"◎ 優良",IF(M95>=0.15,"○ 良好",IF(M95>=0.05,"△ 要注意","× 赤字")))) | O95: C003一般 | P95: — | Q95: =IFERROR(D95/100,0)
A96: 614-2 | B96: ENDO | C96: 2024-08 | D96: =IFERROR(VLOOKUP(C96,▼売上原票!$A:$P,8,0),0) | K96: =E96+F96+G96+H96+I96+J96 | L96: =D96-K96 | M96: =IF(D96<>0,L96/D96,0) | N96: =IF(D96=0,"—",IF(M96>=0.25,"◎ 優良",IF(M96>=0.15,"○ 良好",IF(M96>=0.05,"△ 要注意","× 赤字")))) | O96: C003一般 | P96: =IF(D95<>0,D96/D95-1,"") | Q96: =IFERROR(D96/100,0)
A97: 614-2 | B97: ENDO | C97: 2024-09 | D97: =IFERROR(VLOOKUP(C97,▼売上原票!$A:$P,8,0),0) | K97: =E97+F97+G97+H97+I97+J97 | L97: =D97-K97 | M97: =IF(D97<>0,L97/D97,0) | N97: =IF(D97=0,"—",IF(M97>=0.25,"◎ 優良",IF(M97>=0.15,"○ 良好",IF(M97>=0.05,"△ 要注意","× 赤字")))) | O97: C003一般 | P97: =IF(D96<>0,D97/D96-1,"") | Q97: =IFERROR(D97/100,0)
A98: 614-2 | B98: ENDO | C98: 2024-10 | D98: =IFERROR(VLOOKUP(C98,▼売上原票!$A:$P,8,0),0) | K98: =E98+F98+G98+H98+I98+J98 | L98: =D98-K98 | M98: =IF(D98<>0,L98/D98,0) | N98: =IF(D98=0,"—",IF(M98>=0.25,"◎ 優良",IF(M98>=0.15,"○ 良好",IF(M98>=0.05,"△ 要注意","× 赤字")))) | O98: C003一般 | P98: =IF(D97<>0,D98/D97-1,"") | Q98: =IFERROR(D98/100,0)
A99: 614-2 | B99: ENDO | C99: 2024-11 | D99: =IFERROR(VLOOKUP(C99,▼売上原票!$A:$P,8,0),0) | K99: =E99+F99+G99+H99+I99+J99 | L99: =D99-K99 | M99: =IF(D99<>0,L99/D99,0) | N99: =IF(D99=0,"—",IF(M99>=0.25,"◎ 優良",IF(M99>=0.15,"○ 良好",IF(M99>=0.05,"△ 要注意","× 赤字")))) | O99: C003一般 | P99: =IF(D98<>0,D99/D98-1,"") | Q99: =IFERROR(D99/100,0)
A100: 614-2 | B100: ENDO | C100: 2024-12 | D100: =IFERROR(VLOOKUP(C100,▼売上原票!$A:$P,8,0),0) | K100: =E100+F100+G100+H100+I100+J100 | L100: =D100-K100 | M100: =IF(D100<>0,L100/D100,0) | N100: =IF(D100=0,"—",IF(M100>=0.25,"◎ 優良",IF(M100>=0.15,"○ 良好",IF(M100>=0.05,"△ 要注意","× 赤字")))) | O100: C003一般 | P100: =IF(D99<>0,D100/D99-1,"") | Q100: =IFERROR(D100/100,0)
A101: 614-2 | B101: ENDO | C101: 2025-01 | D101: =IFERROR(VLOOKUP(C101,▼売上原票!$A:$P,8,0),0) | K101: =E101+F101+G101+H101+I101+J101 | L101: =D101-K101 | M101: =IF(D101<>0,L101/D101,0) | N101: =IF(D101=0,"—",IF(M101>=0.25,"◎ 優良",IF(M101>=0.15,"○ 良好",IF(M101>=0.05,"△ 要注意","× 赤字")))) | O101: C003一般 | P101: =IF(D100<>0,D101/D100-1,"") | Q101: =IFERROR(D101/100,0)
A102: 614-2 | B102: ENDO | C102: 2025-02 | D102: =IFERROR(VLOOKUP(C102,▼売上原票!$A:$P,8,0),0) | K102: =E102+F102+G102+H102+I102+J102 | L102: =D102-K102 | M102: =IF(D102<>0,L102/D102,0) | N102: =IF(D102=0,"—",IF(M102>=0.25,"◎ 優良",IF(M102>=0.15,"○ 良好",IF(M102>=0.05,"△ 要注意","× 赤字")))) | O102: C003一般 | P102: =IF(D101<>0,D102/D101-1,"") | Q102: =IFERROR(D102/100,0)
A103: 614-2 | B103: ENDO | C103: 2025-03 | D103: =IFERROR(VLOOKUP(C103,▼売上原票!$A:$P,8,0),0) | K103: =E103+F103+G103+H103+I103+J103 | L103: =D103-K103 | M103: =IF(D103<>0,L103/D103,0) | N103: =IF(D103=0,"—",IF(M103>=0.25,"◎ 優良",IF(M103>=0.15,"○ 良好",IF(M103>=0.05,"△ 要注意","× 赤字")))) | O103: C003一般 | P103: =IF(D102<>0,D103/D102-1,"") | Q103: =IFERROR(D103/100,0)
A104: 614-2 | B104: ENDO | C104: 2025-04 | D104: =IFERROR(VLOOKUP(C104,▼売上原票!$A:$P,8,0),0) | K104: =E104+F104+G104+H104+I104+J104 | L104: =D104-K104 | M104: =IF(D104<>0,L104/D104,0) | N104: =IF(D104=0,"—",IF(M104>=0.25,"◎ 優良",IF(M104>=0.15,"○ 良好",IF(M104>=0.05,"△ 要注意","× 赤字")))) | O104: C003一般 | P104: =IF(D103<>0,D104/D103-1,"") | Q104: =IFERROR(D104/100,0)
A105: 614-2 | B105: ENDO | C105: 2025-05 | D105: =IFERROR(VLOOKUP(C105,▼売上原票!$A:$P,8,0),0) | K105: =E105+F105+G105+H105+I105+J105 | L105: =D105-K105 | M105: =IF(D105<>0,L105/D105,0) | N105: =IF(D105=0,"—",IF(M105>=0.25,"◎ 優良",IF(M105>=0.15,"○ 良好",IF(M105>=0.05,"△ 要注意","× 赤字")))) | O105: C003一般 | P105: =IF(D104<>0,D105/D104-1,"") | Q105: =IFERROR(D105/100,0)
A106: 614-2 | B106: ENDO | C106: 2025-06 | D106: =IFERROR(VLOOKUP(C106,▼売上原票!$A:$P,8,0),0) | K106: =E106+F106+G106+H106+I106+J106 | L106: =D106-K106 | M106: =IF(D106<>0,L106/D106,0) | N106: =IF(D106=0,"—",IF(M106>=0.25,"◎ 優良",IF(M106>=0.15,"○ 良好",IF(M106>=0.05,"△ 要注意","× 赤字")))) | O106: C003一般 | P106: =IF(D105<>0,D106/D105-1,"") | Q106: =IFERROR(D106/100,0)
A107: 614-2 | B107: ENDO | C107: 2025-07 | D107: =IFERROR(VLOOKUP(C107,▼売上原票!$A:$P,8,0),0) | K107: =E107+F107+G107+H107+I107+J107 | L107: =D107-K107 | M107: =IF(D107<>0,L107/D107,0) | N107: =IF(D107=0,"—",IF(M107>=0.25,"◎ 優良",IF(M107>=0.15,"○ 良好",IF(M107>=0.05,"△ 要注意","× 赤字")))) | O107: C003一般 | P107: =IF(D106<>0,D107/D106-1,"") | Q107: =IFERROR(D107/100,0)
... A111: 614-2 | B111: ENDO | C111: 2025-11 | D111: =IFERROR(VLOOKUP(C111,▼売上原票!$A:$P,8,0),0) | K111: =E111+F111+G111+H111+I111+J111 | L111: =D111-K111 | M111: =IF(D111<>0,L111/D111,0) | N111: =IF(D111=0,"—",IF(M111>=0.25,"◎ 優良",IF(M111>=0.15,"○ 良好",IF(M111>=0.05,"△ 要注意","× 赤字")))) | O111: C003一般 | P111: =IF(D110<>0,D111/D110-1,"") | Q111: =IFERROR(D111/100,0)
A113: 614-3 | B113: 現金 | C113: 2024-07 | D113: =IFERROR(VLOOKUP(C113,▼売上原票!$A:$P,9,0),0) | K113: =E113+F113+G113+H113+I113+J113 | L113: =D113-K113 | M113: =IF(D113<>0,L113/D113,0) | N113: =IF(D113=0,"—",IF(M113>=0.25,"◎ 優良",IF(M113>=0.15,"○ 良好",IF(M113>=0.05,"△ 要注意","× 赤字")))) | O113: C003一般 | P113: — | Q113: =IFERROR(D113/100,0)
A114: 614-3 | B114: 現金 | C114: 2024-08 | D114: =IFERROR(VLOOKUP(C114,▼売上原票!$A:$P,9,0),0) | K114: =E114+F114+G114+H114+I114+J114 | L114: =D114-K114 | M114: =IF(D114<>0,L114/D114,0) | N114: =IF(D114=0,"—",IF(M114>=0.25,"◎ 優良",IF(M114>=0.15,"○ 良好",IF(M114>=0.05,"△ 要注意","× 赤字")))) | O114: C003一般 | P114: =IF(D113<>0,D114/D113-1,"") | Q114: =IFERROR(D114/100,0)
A115: 614-3 | B115: 現金 | C115: 2024-09 | D115: =IFERROR(VLOOKUP(C115,▼売上原票!$A:$P,9,0),0) | K115: =E115+F115+G115+H115+I115+J115 | L115: =D115-K115 | M115: =IF(D115<>0,L115/D115,0) | N115: =IF(D115=0,"—",IF(M115>=0.25,"◎ 優良",IF(M115>=0.15,"○ 良好",IF(M115>=0.05,"△ 要注意","× 赤字")))) | O115: C003一般 | P115: =IF(D114<>0,D115/D114-1,"") | Q115: =IFERROR(D115/100,0)
A116: 614-3 | B116: 現金 | C116: 2024-10 | D116: =IFERROR(VLOOKUP(C116,▼売上原票!$A:$P,9,0),0) | K116: =E116+F116+G116+H116+I116+J116 | L116: =D116-K116 | M116: =IF(D116<>0,L116/D116,0) | N116: =IF(D116=0,"—",IF(M116>=0.25,"◎ 優良",IF(M116>=0.15,"○ 良好",IF(M116>=0.05,"△ 要注意","× 赤字")))) | O116: C003一般 | P116: =IF(D115<>0,D116/D115-1,"") | Q116: =IFERROR(D116/100,0)
A117: 614-3 | B117: 現金 | C117: 2024-11 | D117: =IFERROR(VLOOKUP(C117,▼売上原票!$A:$P,9,0),0) | K117: =E117+F117+G117+H117+I117+J117 | L117: =D117-K117 | M117: =IF(D117<>0,L117/D117,0) | N117: =IF(D117=0,"—",IF(M117>=0.25,"◎ 優良",IF(M117>=0.15,"○ 良好",IF(M117>=0.05,"△ 要注意","× 赤字")))) | O117: C003一般 | P117: =IF(D116<>0,D117/D116-1,"") | Q117: =IFERROR(D117/100,0)
A118: 614-3 | B118: 現金 | C118: 2024-12 | D118: =IFERROR(VLOOKUP(C118,▼売上原票!$A:$P,9,0),0) | K118: =E118+F118+G118+H118+I118+J118 | L118: =D118-K118 | M118: =IF(D118<>0,L118/D118,0) | N118: =IF(D118=0,"—",IF(M118>=0.25,"◎ 優良",IF(M118>=0.15,"○ 良好",IF(M118>=0.05,"△ 要注意","× 赤字")))) | O118: C003一般 | P118: =IF(D117<>0,D118/D117-1,"") | Q118: =IFERROR(D118/100,0)
A119: 614-3 | B119: 現金 | C119: 2025-01 | D119: =IFERROR(VLOOKUP(C119,▼売上原票!$A:$P,9,0),0) | K119: =E119+F119+G119+H119+I119+J119 | L119: =D119-K119 | M119: =IF(D119<>0,L119/D119,0) | N119: =IF(D119=0,"—",IF(M119>=0.25,"◎ 優良",IF(M119>=0.15,"○ 良好",IF(M119>=0.05,"△ 要注意","× 赤字")))) | O119: C003一般 | P119: =IF(D118<>0,D119/D118-1,"") | Q119: =IFERROR(D119/100,0)
A120: 614-3 | B120: 現金 | C120: 2025-02 | D120: =IFERROR(VLOOKUP(C120,▼売上原票!$A:$P,9,0),0) | K120: =E120+F120+G120+H120+I120+J120 | L120: =D120-K120 | M120: =IF(D120<>0,L120/D120,0) | N120: =IF(D120=0,"—",IF(M120>=0.25,"◎ 優良",IF(M120>=0.15,"○ 良好",IF(M120>=0.05,"△ 要注意","× 赤字")))) | O120: C003一般 | P120: =IF(D119<>0,D120/D119-1,"") | Q120: =IFERROR(D120/100,0)
A121: 614-3 | B121: 現金 | C121: 2025-03 | D121: =IFERROR(VLOOKUP(C121,▼売上原票!$A:$P,9,0),0) | K121: =E121+F121+G121+H121+I121+J121 | L121: =D121-K121 | M121: =IF(D121<>0,L121/D121,0) | N121: =IF(D121=0,"—",IF(M121>=0.25,"◎ 優良",IF(M121>=0.15,"○ 良好",IF(M121>=0.05,"△ 要注意","× 赤字")))) | O121: C003一般 | P121: =IF(D120<>0,D121/D120-1,"") | Q121: =IFERROR(D121/100,0)
A122: 614-3 | B122: 現金 | C122: 2025-04 | D122: =IFERROR(VLOOKUP(C122,▼売上原票!$A:$P,9,0),0) | K122: =E122+F122+G122+H122+I122+J122 | L122: =D122-K122 | M122: =IF(D122<>0,L122/D122,0) | N122: =IF(D122=0,"—",IF(M122>=0.25,"◎ 優良",IF(M122>=0.15,"○ 良好",IF(M122>=0.05,"△ 要注意","× 赤字")))) | O122: C003一般 | P122: =IF(D121<>0,D122/D121-1,"") | Q122: =IFERROR(D122/100,0)
A123: 614-3 | B123: 現金 | C123: 2025-05 | D123: =IFERROR(VLOOKUP(C123,▼売上原票!$A:$P,9,0),0) | K123: =E123+F123+G123+H123+I123+J123 | L123: =D123-K123 | M123: =IF(D123<>0,L123/D123,0) | N123: =IF(D123=0,"—",IF(M123>=0.25,"◎ 優良",IF(M123>=0.15,"○ 良好",IF(M123>=0.05,"△ 要注意","× 赤字")))) | O123: C003一般 | P123: =IF(D122<>0,D123/D122-1,"") | Q123: =IFERROR(D123/100,0)
A124: 614-3 | B124: 現金 | C124: 2025-06 | D124: =IFERROR(VLOOKUP(C124,▼売上原票!$A:$P,9,0),0) | K124: =E124+F124+G124+H124+I124+J124 | L124: =D124-K124 | M124: =IF(D124<>0,L124/D124,0) | N124: =IF(D124=0,"—",IF(M124>=0.25,"◎ 優良",IF(M124>=0.15,"○ 良好",IF(M124>=0.05,"△ 要注意","× 赤字")))) | O124: C003一般 | P124: =IF(D123<>0,D124/D123-1,"") | Q124: =IFERROR(D124/100,0)
...

Sheet ▼売上原票
A1: ▼売上原票 月次売上実績（科目別・税抜） ※このシートは直接編集しないでください
A2: 【毎月の更新方法】 新しい月のデータを最終行の下に1行追加してください。A列=YYYY-MM、C〜M列=各科目売上（税抜円）
A3: 年月 ★VLOOKUPキー | B3: R表記 | C3: 612-1 運送（本社） | D3: 612-2 入札（公共） | E3: 613-1 車輌 | F3: 613-2 KC | G3: 614-1 コンテナ | H3: 614-2 ENDO | I3: 614-3 現金 | J3: 615-1 板橋 | K3: 615-2 新横浜 | L3: 615-3 現金2 | M3: 615-4 有価物 | N3: 合計 (税抜) | O3: 消費税 (△) | P3: 合計 (税込)
A4: 2024-07 | B4: R6.7 | C4: 13754437 | D4: 42726740 | E4: 777000 | F4: 40000 | G4: 504500 | H4: 527664 | I4: 261000 | J4: 25593317 | K4: 4417112 | L4: 36000 | M4: 138460 | N4: 88776230 | O4: -80705664 | P4: =IF(N4<>"",N4+O4,"")
A5: 2024-08 | B5: R6.8 | C5: 13060970 | D5: 36972090 | E5: 789000 | F5: 1000228 | G5: 507200 | H5: 518000 | J5: 20527297 | K5: 4953790 | L5: 57000 | M5: 172726 | N5: 78558301 | O5: -71416637 | P5: =IF(N5<>"",N5+O5,"")
A6: 2024-09 | B6: R6.9 | C6: 13837910 | D6: 37268605 | E6: 1143000 | G6: 513500 | H6: 480000 | J6: 22121458 | K6: 4072534 | L6: 54000 | M6: 162126 | N6: 79653133 | O6: -72411939 | P6: =IF(N6<>"",N6+O6,"")
A7: 2024-10 | B7: R6.10 | C7: 14538480 | D7: 39318469 | E7: 2859000 | F7: 3879338 | G7: 519500 | H7: 665902 | I7: 45000 | J7: 20930409 | K7: 4513589 | L7: 106000 | M7: 132040 | N7: 87507727 | O7: -79552479 | P7: =IF(N7<>"",N7+O7,"")
A8: 2024-11 | B8: R6.11 | C8: 12832260 | D8: 40166406 | E8: 891000 | F8: 2729582 | G8: 552500 | H8: 962040 | J8: 21039598 | K8: 4677613 | L8: 54000 | M8: 131610 | N8: 84036609 | O8: -76396917 | P8: =IF(N8<>"",N8+O8,"")
A9: 2024-12 | B9: R6.12 | C9: 13385794 | D9: 36230090 | E9: 885000 | F9: 3927473 | G9: 543500 | H9: 247700 | I9: 928500 | J9: 21774932 | K9: 4842835 | L9: 27000 | M9: 212926 | N9: 83005750 | O9: -75459773 | P9: =IF(N9<>"",N9+O9,"")
A10: 2025-01 | B10: R7.1 | C10: 11619926 | D10: 37239620 | F10: 1249028 | G10: 534500 | H10: 300000 | I10: 70000 | J10: 19408606 | K10: 4149715 | L10: 18000 | M10: 133330 | N10: 74722725 | O10: -67929750 | P10: =IF(N10<>"",N10+O10,"")
A11: 2025-02 | B11: R7.2 | C11: 12256849 | D11: 35273064 | E11: 716000 | G11: 534500 | H11: 150400 | J11: 18823147 | K11: 3791480 | L11: 75864 | M11: 163880 | N11: 71785184 | O11: -65259258 | P11: =IF(N11<>"",N11+O11,"")
A12: 2025-03 | B12: R7.3 | C12: 12036342 | D12: 39891431 | F12: 4399519 | G12: 534500 | H12: 35728 | I12: 177600 | J12: 21429591 | K12: 5604911 | L12: 73000 | M12: 167470 | N12: 84350092 | O12: -76681902 | P12: =IF(N12<>"",N12+O12,"")
A13: 2025-04 | B13: R7.4 | C13: 13732489 | D13: 42565460 | E13: 320000 | G13: 579000 | H13: 20000 | I13: 385190 | J13: 20293634 | K13: 4392253 | L13: 54000 | M13: 126695 | N13: 82468721 | O13: -74971565 | P13: =IF(N13<>"",N13+O13,"")
A14: 2025-05 | B14: R7.5 | C14: 12433945 | D14: 42621987 | E14: 24000 | G14: 399500 | H14: 375209 | I14: 4439900 | J14: 20536694 | K14: 4686122 | L14: 49068 | M14: 116600 | N14: 85683025 | O14: -77893659 | P14: =IF(N14<>"",N14+O14,"")
A15: 2025-06 | B15: R7.6 | C15: 12725923 | D15: 42039492 | E15: 560000 | F15: 6678437 | G15: 639500 | H15: 66155 | I15: 811380 | J15: 21382460 | K15: 4686956 | L15: 282934 | M15: 233890 | N15: 90107127 | O15: -81915570 | P15: =IF(N15<>"",N15+O15,"")
A16: 2025-07 | B16: R7.7 | C16: 14033460 | D16: 49551795 | E16: 70400 | G16: 439450 | H16: 522775 | I16: 3465 | J16: 24309231 | K16: 5799867 | L16: 19800 | M16: 299751 | N16: 95049994 | O16: -86409085 | P16: =IF(N16<>"",N16+O16,"")
A17: 2025-08 | B17: R7.8 | C17: 12775187 | D17: 45672694 | E17: 1859000 | F17: 6057720 | G17: 703450 | H17: 995236 | I17: 500 | J17: 21710565 | K17: 6235942 | L17: 85140 | M17: 297500 | N17: 96392934 | O17: -87629940 | P17: =IF(N17<>"",N17+O17,"")
A18: 2025-09 | B18: R7.9 | C18: 14091143 | D18: 43759116 | H18: 1015575 | J18: 23910829 | K18: 5910373 | M18: 322317 | N18: 89009353 | O18: -80917594 | P18: =IF(N18<>"",N18+O18,"")
A19: 2025-10 | B19: R7.10 | C19: 13803873 | D19: 50278847 | H19: 1208834 | J19: 24518032 | K19: 5582131 | M19: 312433 | N19: 95704150 | O19: -87003773 | P19: =IF(N19<>"",N19+O19,"")
A20: 2025-11 | B20: R7.11 | C20: 12084188 | D20: 44355003 | H20: 1208537 | J20: 23811782 | K20: 5414620 | M20: 301681 | N20: 87175811 | O20: -79250737 | P20: =IF(N20<>"",N20+O20,"")
A21: ←ここに入力 | N21: =IF(C21+D21+E21+F21+G21+H21+I21+J21+K21+L21+M21=0,"",C21+D21+E21+F21+G21+H21+I21+J21+K21+L21+M21) | O21: =IF(N21="","",ROUND(-N21/11,0)) | P21: =IF(N21="","",N21+O21)
A22: ←ここに入力 | N22: =IF(C22+D22+E22+F22+G22+H22+I22+J22+K22+L22+M22=0,"",C22+D22+E22+F22+G22+H22+I22+J22+K22+L22+M22) | O22: =IF(N22="","",ROUND(-N22/11,0)) | P22: =IF(N22="","",N22+O22)
A23: ←ここに入力 | N23: =IF(C23+D23+E23+F23+G23+H23+I23+J23+K23+L23+M23=0,"",C23+D23+E23+F23+G23+H23+I23+J23+K23+L23+M23) | O23: =IF(N23="","",ROUND(-N23/11,0)) | P23: =IF(N23="","",N23+O23)
A24: ←ここに入力 | N24: =IF(C24+D24+E24+F24+G24+H24+I24+J24+K24+L24+M24=0,"",C24+D24+E24+F24+G24+H24+I24+J24+K24+L24+M24) | O24: =IF(N24="","",ROUND(-N24/11,0)) | P24: =IF(N24="","",N24+O24)
A25: ←ここに入力 | N25: =IF(C25+D25+E25+F25+G25+H25+I25+J25+K25+L25+M25=0,"",C25+D25+E25+F25+G25+H25+I25+J25+K25+L25+M25) | O25: =IF(N25="","",ROUND(-N25/11,0)) | P25: =IF(N25="","",N25+O25)
A26: ←ここに入力 | N26: =IF(C26+D26+E26+F26+G26+H26+I26+J26+K26+L26+M26=0,"",C26+D26+E26+F26+G26+H26+I26+J26+K26+L26+M26) | O26: =IF(N26="","",ROUND(-N26/11,0)) | P26: =IF(N26="","",N26+O26)
A27: ←ここに入力 | N27: =IF(C27+D27+E27+F27+G27+H27+I27+J27+K27+L27+M27=0,"",C27+D27+E27+F27+G27+H27+I27+J27+K27+L27+M27) | O27: =IF(N27="","",ROUND(-N27/11,0)) | P27: =IF(N27="","",N27+O27)
A28: ←ここに入力 | N28: =IF(C28+D28+E28+F28+G28+H28+I28+J28+K28+L28+M28=0,"",C28+D28+E28+F28+G28+H28+I28+J28+K28+L28+M28) | O28: =IF(N28="","",ROUND(-N28/11,0)) | P28: =IF(N28="","",N28+O28)
A29: ←ここに入力 | N29: =IF(C29+D29+E29+F29+G29+H29+I29+J29+K29+L29+M29=0,"",C29+D29+E29+F29+G29+H29+I29+J29+K29+L29+M29) | O29: =IF(N29="","",ROUND(-N29/11,0)) | P29: =IF(N29="","",N29+O29)
A30: ←ここに入力 | N30: =IF(C30+D30+E30+F30+G30+H30+I30+J30+K30+L30+M30=0,"",C30+D30+E30+F30+G30+H30+I30+J30+K30+L30+M30) | O30: =IF(N30="","",ROUND(-N30/11,0)) | P30: =IF(N30="","",N30+O30)
A31: ←ここに入力 | N31: =IF(C31+D31+E31+F31+G31+H31+I31+J31+K31+L31+M31=0,"",C31+D31+E31+F31+G31+H31+I31+J31+K31+L31+M31) | O31: =IF(N31="","",ROUND(-N31/11,0)) | P31: =IF(N31="","",N31+O31)
A32: ←ここに入力 | N32: =IF(C32+D32+E32+F32+G32+H32+I32+J32+K32+L32+M32=0,"",C32+D32+E32+F32+G32+H32+I32+J32+K32+L32+M32) | O32: =IF(N32="","",ROUND(-N32/11,0)) | P32: =IF(N32="","",N32+O32)

Sheet ▼マッピング設定
A1: ▼マッピング設定 ルート(科目)→案件の配分率 ★初回のみ確認・調整してください
A2: 各行の D+E+F=100 になるよう設定してください。615-1(板橋)は東急グループと一般事業者の両方を担当しているため分割設定しています。
A3: 科目コード | B3: 科目名 | C3: 配分根拠（メモ） | D3: C001 東急グループ% | E3: C002 都営地下鉄% | F3: C003 一般事業者% | G3: 合計% (100が正常)
A4: 612-1 | B4: 運送（本社） | C4: 本社が受注する民間運送 → 一般事業者に100% | D4: 0 | E4: 0 | F4: 100 | G4: =D4+E4+F4
A5: 612-2 | B5: 入札（公共） | C5: 行政・公共入札案件 → 都営地下鉄・区役所等に100% | D5: 0 | E5: 100 | F5: 0 | G5: =D5+E5+F5
A6: 613-1 | B6: 車輌 | C6: 車輌売上（全案件に按分） | D6: 20 | E6: 10 | F6: 70 | G6: =D6+E6+F6
A7: 613-2 | B7: KC | C7: KCサキュレ分（別管理・0%） | D7: 0 | E7: 0 | F7: 0 | G7: =D7+E7+F7
A8: 614-1 | B8: コンテナ | C8: コンテナ → 一般事業者に100% | D8: 0 | E8: 0 | F8: 100 | G8: =D8+E8+F8
A9: 614-2 | B9: ENDO | C9: ENDO → 一般事業者に100% | D9: 0 | E9: 0 | F9: 100 | G9: =D9+E9+F9
A10: 614-3 | B10: 現金 | C10: 現金取引 → 一般事業者に100% | D10: 0 | E10: 0 | F10: 100 | G10: =D10+E10+F10
A11: 615-1 | B11: 板橋 | C11: 板橋営業所：東急グループ拠点60%・一般40% ★実績に応じて調整 | D11: 60 | E11: 0 | F11: 40 | G11: =D11+E11+F11
A12: 615-2 | B12: 新横浜 | C12: 新横浜営業所 → 一般事業者に100% | D12: 0 | E12: 0 | F12: 100 | G12: =D12+E12+F12
A13: 615-3 | B13: 現金2 | C13: 現金2 → 一般事業者に100% | D13: 0 | E13: 0 | F13: 100 | G13: =D13+E13+F13
A14: 615-4 | B14: 有価物 | C14: 有価物 → 一般事業者に100% | D14: 0 | E14: 0 | F14: 100 | G14: =D14+E14+F14
A16: 【判定基準】 ◎ 優良=粗利率25%以上 ○ 良好=15〜25% △ 要注意=5〜15% × 赤字=5%未満

Sheet ▼従業員マスター
A1: 従業員マスター（R6.10 新体系基準） ※給与データ機密 取扱注意
A2: 出典：令和6年10月変更 新体系 │ 月給制=合計欄の固定額 │ 日当制・時給制は稼働日数に応じて変動（E列入力）
A3: ▼ 月間稼働日数（日当制・時給制の計算基準） | D3: 22 | E3: ← ここを変更すると日当制・時給制の月額が自動更新されます（時給制は×8時間/日で計算）
A5: 所属 | B5: 氏名 | C5: 雇用区分 | D5: 月額/日当/時給 | E5: 月間稼働日数 (入力可) | F5: 月額人件費 (自動計算) | G5: 直間 区分 | H5: 備考 | I5: 参考:年間
A6: ■ 本社
A7: 本社 | B7: 横井 哲也 | C7: 月給 | D7: 269545 | E7: — | F7: 269545 | G7: 直接 | I7: 3234540
A8: 本社 | B8: 上林 幸二 | C8: 月給 | D8: 254545 | E8: — | F8: 254545 | G8: 直接 | I8: 3054540
A9: 本社 | B9: 加藤 光裕 | C9: 月給 | D9: 283545 | E9: — | F9: 283545 | G9: 直接 | I9: 3402540
A10: 本社 | B10: 吉田 創 | C10: 月給 | D10: 249395 | E10: — | F10: 249395 | G10: 直接 | I10: 2992740
A11: 本社 | B11: 原口 陽一 | C11: 月給 | D11: 243155 | E11: — | F11: 243155 | G11: 直接 | I11: 2917860
A12: 本社 | B12: 北川 善己 | C12: 月給 | D12: 266955 | E12: — | F12: 266955 | G12: 直接 | H12: 東京発送手当 | I12: 3203460
A13: 本社 | B13: 平野 裕幸 | C13: 月給 | D13: 263155 | E13: — | F13: 263155 | G13: 直接 | H13: 渡邊ベニヤ | I13: 3157860
A14: 本社 | B14: 山口 晃司 | C14: 月給 | D14: 243155 | E14: — | F14: 243155 | G14: 直接 | H14: いずみ | I14: 2917860
A15: 本社 | B15: 石垣眞一郎 | C15: 月給 | D15: 263155 | E15: — | F15: 263155 | G15: 直接 | H15: 菱倉 | I15: 3157860
A16: 本社 | B16: 高島 正人 | C16: 月給 | D16: 246155 | E16: — | F16: 246155 | G16: 直接 | H16: いずみ | I16: 2953860
A17: 本社 | B17: 綱島 博隆 | C17: 月給 | D17: 268155 | E17: — | F17: 268155 | G17: 直接 | H17: 千代田区 | I17: 3217860
A18: 本社 | B18: 後藤 実 | C18: 月給 | D18: 243155 | E18: — | F18: 243155 | G18: 直接 | I18: 2917860
A19: 本社 | B19: 嶋村 真実 | C19: 月給 | D19: 243155 | E19: — | F19: 243155 | G19: 直接 | I19: 2917860
A20: 本社 | B20: 岡田 学 | C20: 月給 | D20: 243155 | E20: — | F20: 243155 | G20: 間接 | H20: 文書 | I20: 2917860
A21: 本社 | B21: 横山 信廣 | C21: 月給 | D21: 243155 | E21: — | F21: 243155 | G21: 直接 | I21: 2917860
A22: 本社 | B22: 笹沼 信人 | C22: 月給 | D22: 263155 | E22: — | F22: 263155 | G22: 直接 | H22: 東京発送手当 | I22: 3157860
A23: 本社 | B23: 諏訪 清行 | C23: 月給 | D23: 243155 | E23: — | F23: 243155 | G23: 直接 | I23: 2917860
A24: 本社 | B24: 清水 孝之 | C24: 月給 | D24: 246155 | E24: — | F24: 246155 | G24: 直接 | H24: いずみ | I24: 2953860
A25: 本社 | B25: 山下 勝二 | C25: 月給 | D25: 243155 | E25: — | F25: 243155 | G25: 直接 | I25: 2917860
A26: 本社 | B26: 根本 純一 | C26: 月給 | D26: 278155 | E26: — | F26: 278155 | G26: 直接 | H26: 自転車撤去 | I26: 3337860
A27: 本社 | B27: 花木 凌 | C27: 月給 | D27: 243155 | E27: — | F27: 243155 | G27: 直接 | I27: 2917860
A28: 本社 | B28: 川井 良之 | C28: 月給 | D28: 243155 | E28: — | F28: 243155 | G28: 直接 | I28: 2917860
A29: 本社 | B29: 岡村 栄 | C29: 日当 | D29: 10000 | E29: =$D$3 | F29: =D29*$D$3 | G29: 直接 | I29: =F29*12
A30: 本社 | B30: 川端 保 | C30: 日当 | D30: 11000 | E30: =$D$3 | F30: =D30*$D$3 | G30: 直接 | I30: =F30*12
A31: 本社 | B31: 鈴木 賢二 | C31: 日当 | D31: 10000 | E31: =$D$3 | F31: =D31*$D$3 | G31: 直接 | I31: =F31*12
A32: 本社 | B32: 小西 正悦 | C32: 日当 | D32: 10000 | E32: =$D$3 | F32: =D32*$D$3 | G32: 直接 | I32: =F32*12
A33: 本社 | B33: 西開地良二 | C33: 日当 | D33: 10000 | E33: =$D$3 | F33: =D33*$D$3 | G33: 直接 | H33: いずみ手当 | I33: =F33*12
A34: 本社 | B34: 四位 宗光 | C34: 日当 | D34: 9320 | E34: =$D$3 | F34: =D34*$D$3 | G34: 直接 | I34: =F34*12
A35: 本社 | B35: 赤崎 博隆 | C35: 日当 | D35: 10000 | E35: =$D$3 | F35: =D35*$D$3 | G35: 直接 | I35: =F35*12
A36: 本社 | B36: 近藤 政夫 | C36: 日当 | D36: 10000 | E36: =$D$3 | F36: =D36*$D$3 | G36: 直接 | I36: =F36*12
A37: 本社 | B37: 佐藤 淳司 | C37: 日当 | D37: 10000 | E37: =$D$3 | F37: =D37*$D$3 | G37: 直接 | H37: 自転車撤去 | I37: =F37*12
A38: 本社 | B38: 門脇 明敏 | C38: 日当 | D38: 10000 | E38: =$D$3 | F38: =D38*$D$3 | G38: 直接 | H38: いずみ | I38: =F38*12
A39: 本社 | B39: 小島 一彦 | C39: 日当 | D39: 10000 | E39: =$D$3 | F39: =D39*$D$3 | G39: 直接 | I39: =F39*12
A40: 本社 | B40: 後藤 保幸 | C40: 日当 | D40: 10000 | E40: =$D$3 | F40: =D40*$D$3 | G40: 直接 | I40: =F40*12
A41: 本社 | B41: 昆野 良博 | C41: 日当 | D41: 10000 | E41: =$D$3 | F41: =D41*$D$3 | G41: 直接 | I41: =F41*12
A42: 本社 | B42: 伊藤 敏正 | C42: 日当 | D42: 10000 | E42: =$D$3 | F42: =D42*$D$3 | G42: 直接 | I42: =F42*12
A43: 本社 | B43: 石井 努 | C43: 日当 | D43: 10000 | E43: =$D$3 | F43: =D43*$D$3 | G43: 直接 | H43: いずみ | I43: =F43*12
A44: 本社 | B44: 金川 裕 | C44: 日当 | D44: 10000 | E44: =$D$3 | F44: =D44*$D$3 | G44: 直接 | H44: 文書交換 | I44: =F44*12
A45: 本社 | B45: 大澤 弘直 | C45: 日当 | D45: 8000 | E45: =$D$3 | F45: =D45*$D$3 | G45: 直接 | H45: 6.5h | I45: =F45*12
A46: 本社 | B46: 羽田 美惠 | C46: 日当 | D46: 10000 | E46: =$D$3 | F46: =D46*$D$3 | G46: 間接 | I46: =F46*12
A47: 本社 | B47: 赤石 政春 | C47: 日当 | D47: 10000 | E47: =$D$3 | F47: =D47*$D$3 | G47: 直接 | H47: 文書交換 | I47: =F47*12
A48: 本社 | B48: 小山内文夫 | C48: 日当 | D48: 10000 | E48: =$D$3 | F48: =D48*$D$3 | G48: 直接 | H48: 千代田区 | I48: =F48*12
A49: 本社 | B49: 林 重晴 | C49: 日当 | D49: 10000 | E49: =$D$3 | F49: =D49*$D$3 | G49: 直接 | H49: いずみ | I49: =F49*12
A50: 本社 | B50: 中原 健一 | C50: 日当 | D50: 10000 | E50: =$D$3 | F50: =D50*$D$3 | G50: 直接 | H50: 文書交換 | I50: =F50*12
A51: 本社 | B51: 樋口 隆一 | C51: 日当 | D51: 10000 | E51: =$D$3 | F51: =D51*$D$3 | G51: 直接 | H51: 自転車撤去 | I51: =F51*12
A52: 本社 | B52: 中村 史德 | C52: 日当 | D52: 10000 | E52: =$D$3 | F52: =D52*$D$3 | G52: 直接 | H52: 自転車撤去 | I52: =F52*12
A53: 本社 | B53: 金子 豊 | C53: 日当 | D53: 10000 | E53: =$D$3 | F53: =D53*$D$3 | G53: 直接 | H53: 自転車撤去 | I53: =F53*12
A54: 本社 | B54: 斉藤 善 | C54: 日当 | D54: 10000 | E54: =$D$3 | F54: =D54*$D$3 | G54: 直接 | H54: 自転車撤去 | I54: =F54*12
A55: 本社 | B55: 松崎 亨 | C55: 日当 | D55: 10000 | E55: =$D$3 | F55: =D55*$D$3 | G55: 直接 | I55: =F55*12
A56: 本社 | B56: 町田 昌明 | C56: 日当 | D56: 10000 | E56: =$D$3 | F56: =D56*$D$3 | G56: 直接 | I56: =F56*12
A57: 本社 | B57: 堀 富雄 | C57: 日当 | D57: 10000 | E57: =$D$3 | F57: =D57*$D$3 | G57: 直接 | I57: =F57*12
A58: 本社 | B58: 栗原文次郎 | C58: 日当 | D58: 10000 | E58: =$D$3 | F58: =D58*$D$3 | G58: 直接 | I58: =F58*12
A59: 本社 | B59: 高栁 恵州 | C59: 日当 | D59: 10000 | E59: =$D$3 | F59: =D59*$D$3 | G59: 直接 | I59: =F59*12
A60: 本社 | B60: 吉見 之男 | C60: 日当 | D60: 10000 | E60: =$D$3 | F60: =D60*$D$3 | G60: 直接 | I60: =F60*12
A61: 本社 | B61: 坂本 龍男 | C61: 日当 | D61: 10000 | E61: =$D$3 | F61: =D61*$D$3 | G61: 直接 | I61: =F61*12
A62: 本社 | B62: 桃谷 政良 | C62: 日当 | D62: 10000 | E62: =$D$3 | F62: =D62*$D$3 | G62: 直接 | I62: =F62*12
A63: 本社 | B63: 竹内 幸一 | C63: 日当 | D63: 10000 | E63: =$D$3 | F63: =D63*$D$3 | G63: 直接 | I63: =F63*12
A64: 本社 | B64: 林 幸夫 | C64: 日当 | D64: 10000 | E64: =$D$3 | F64: =D64*$D$3 | G64: 直接 | I64: =F64*12
A65: 本社 | B65: 加藤実都代 | C65: 時給 | D65: 1805 | E65: =$D$3 | F65: =D65*$D$3*8 | G65: 間接 | I65: =F65*12
A66: 本社 | B66: 林 典子 | C66: 時給 | D66: 1165 | E66: =$D$3 | F66: =D66*$D$3*8 | G66: 間接 | I66: =F66*12
A67: 本社 | B67: 足立秀次郎 | C67: 時給 | D67: 1165 | E67: =$D$3 | F67: =D67*$D$3*8 | G67: 間接 | H67: 文書交換室 | I67: =F67*12
A68: 本社 | B68: 松原 光年 | C68: 時給 | D68: 1165 | E68: =$D$3 | F68: =D68*$D$3*8 | G68: 間接 | H68: 文書交換室 | I68: =F68*12
A69: 本社 | B69: 吉川 洋平 | C69: 時給 | D69: 1165 | E69: =$D$3 | F69: =D69*$D$3*8 | G69: 間接 | H69: 文書交換室 | I69: =F69*12
A70: 本社 | B70: 野村 正信 | C70: 時給 | D70: 1165 | E70: =$D$3 | F70: =D70*$D$3*8 | G70: 間接 | H70: 文書交換室 | I70: =F70*12
A71: 本社 | B71: 野原 典子 | C71: 時給 | D71: 1165 | E71: =$D$3 | F71: =D71*$D$3*8 | G71: 間接 | H71: 文書交換室 | I71: =F71*12
A72: 本社 | B72: 坂本多枝子 | C72: 時給 | D72: 1165 | E72: =$D$3 | F72: =D72*$D$3*8 | G72: 間接 | H72: 文書交換室 | I72: =F72*12
A73: 本社 | B73: 矢作 明美 | C73: 時給 | D73: 1165 | E73: =$D$3 | F73: =D73*$D$3*8 | G73: 間接 | H73: 文書交換室 | I73: =F73*12
A74: 本社 | B74: 木村 貴子 | C74: 時給 | D74: 1165 | E74: =$D$3 | F74: =D74*$D$3*8 | G74: 間接 | H74: 文書交換室 | I74: =F74*12
A75: 本社 | B75: 稲富 笑子 | C75: 時給 | D75: 1165 | E75: =$D$3 | F75: =D75*$D$3*8 | G75: 間接 | H75: 文書交換室 | I75: =F75*12
A76: 本社 | B76: 芳本 智代 | C76: 時給 | D76: 1165 | E76: =$D$3 | F76: =D76*$D$3*8 | G76: 間接 | H76: 文書交換室 | I76: =F76*12
A77: 本社 | B77: 村上 博美 | C77: 自転車 | D77: 8447 | E77: =$D$3 | F77: =D77*$D$3 | G77: 直接 | H77: 7.25h | I77: =F77*12
A78: 本社 | B78: 渡邊 茂夫 | C78: 自転車 | D78: 8447 | E78: =$D$3 | F78: =D78*$D$3 | G78: 直接 | H78: 7.25h | I78: =F78*12
A79: 本社 | B79: 川満 俊一 | C79: 自転車 | D79: 8447 | E79: =$D$3 | F79: =D79*$D$3 | G79: 直接 | H79: 7.25h | I79: =F79*12
A80: 本社 | B80: 阿久津信介 | C80: 自転車 | D80: 8447 | E80: =$D$3 | F80: =D80*$D$3 | G80: 直接 | H80: 7.25h 班長手当 | I80: =F80*12
A81: 本社 | B81: 竹内 和夫 | C81: 自転車 | D81: 8447 | E81: =$D$3 | F81: =D81*$D$3 | G81: 直接 | H81: 7.25h | I81: =F81*12
A82: 本社 | B82: 橋本富士夫 | C82: 自転車 | D82: 8447 | E82: =$D$3 | F82: =D82*$D$3 | G82: 直接 | H82: 7.25h | I82: =F82*12
A83: 本社 | B83: 三浦 勲 | C83: 自転車 | D83: 8447 | E83: =$D$3 | F83: =D83*$D$3 | G83: 直接 | H83: 7.25h | I83: =F83*12
A84: 本社 | B84: 青木 茂 | C84: 自転車 | D84: 8447 | E84: =$D$3 | F84: =D84*$D$3 | G84: 直接 | H84: 7.25h | I84: =F84*12
A85: 本社 | B85: 後藤 高広 | C85: 自転車 | D85: 8447 | E85: =$D$3 | F85: =D85*$D$3 | G85: 直接 | H85: 7.25h | I85: =F85*12
A86: 本社 | B86: 平山 進 | C86: 自転車 | D86: 8447 | E86: =$D$3 | F86: =D86*$D$3 | G86: 直接 | H86: 7.25h | I86: =F86*12
A87: 本社 | B87: 小松 真裕 | C87: 自転車 | D87: 8447 | E87: =$D$3 | F87: =D87*$D$3 | G87: 直接 | H87: 7.25h | I87: =F87*12
A88: 本社 | B88: 奥園 達雄 | C88: 自転車 | D88: 8447 | E88: =$D$3 | F88: =D88*$D$3 | G88: 直接 | H88: 7.25h | I88: =F88*12
... A97: 本社 | B97: 森 涼太 | C97: 自転車 | D97: 8447 | E97: =$D$3 | F97: =D97*$D$3 | G97: 直接 | H97: 7.25h 能率2 | I97: =F97*12
A98: 本社 合計 (92名) | F98: =SUMIF(A6:A97,"本社",F6:F97)
A99: ■ 板橋
A100: 板橋 | B100: 舟山 真純 | C100: 月給 | D100: 278155 | E100: — | F100: 278155 | G100: 直接 | H100: KC | I100: 3337860
A101: 板橋 | B101: 真栄城玄昌 | C101: 月給 | D101: 278545 | E101: — | F101: 278545 | G101: 直接 | I101: 3342540
A102: 板橋 | B102: 長野 義昭 | C102: 月給 | D102: 269395 | E102: — | F102: 269395 | G102: 直接 | H102: 深夜 | I102: 3232740
A103: 板橋 | B103: 大森 茂 | C103: 月給 | D103: 276395 | E103: — | F103: 276395 | G103: 直接 | H103: 深夜 | I103: 3316740
A104: 板橋 | B104: 柳沼 清志 | C104: 月給 | D104: 276395 | E104: — | F104: 276395 | G104: 直接 | I104: 3316740
A105: 板橋 | B105: 内田 温城 | C105: 月給 | D105: 253155 | E105: — | F105: 253155 | G105: 直接 | I105: 3037860
A106: 板橋 | B106: 大迫 二郎 | C106: 月給 | D106: 253155 | E106: — | F106: 253155 | G106: 直接 | H106: 深夜 | I106: 3037860
A107: 板橋 | B107: 黒澤栄次郎 | C107: 月給 | D107: 253155 | E107: — | F107: 253155 | G107: 直接 | H107: 深夜 | I107: 3037860
A108: 板橋 | B108: 千葉 実 | C108: 月給 | D108: 253155 | E108: — | F108: 253155 | G108: 直接 | H108: 深夜 | I108: 3037860
A109: 板橋 | B109: 宮原 茂 | C109: 月給 | D109: 253155 | E109: — | F109: 253155 | G109: 直接 | H109: 深夜 | I109: 3037860
...
